Workbook
Name Products: OFFSET(Stock!$O$8,0,0,MAX(1,COUNTA(Stock!$A$8:$A$101)),1)
Name CartonList: OFFSET('Carton Stock'!$B$8,0,0,MAX(1,COUNTA('Carton Stock'!$B$8:$B$47)),1)

Sheet Read me
A1: PREMIER EXPORTS INTERNATIONAL
A2: STOCK REGISTER — HOW IT WORKS
B4: Every day, in one minute
B5: 1. On 'Daily Entry' add one row per product that moved — date, product from the
B6: dropdown, and the quantity in that product's own unit.
B7: 2. On 'Stock' set the Statement date and the US$ → ₹ rate for today.
B8: 3. Open 'Daily Report' — it has already rebuilt itself.
B9: 4. File ▸ Export ▸ Create PDF/XPS, "Selected sheet" — that is the directors' copy.
B11: Units: slabs and kilos are not the same thing
B12: Every product carries a Unit and a Kg / Unit on the Stock sheet.
B13: Slab, 2.00 - the shrimp brands — Blue Dolphin, Primus, AMF, THT, China, Deep Sea
B14: Kg, 1.00 - tuna and mackerel, where the balance is already in kilos
B15: Slab, other - squid, cuttlefish and shrimp whole, whose slab weight varies by buyer
B16: Because a slab and a kilo cannot be added together, every total in this workbook is
... B54: Cartons used are rounded up for each product: a part-filled carton is a carton used.

Sheet Stock
A1: PREMIER EXPORTS INTERNATIONAL
A2: STOCK REGISTER — LIVE POSITION
A3: Statement Date | E3: 46324 | F3: ← today; drives the two "today" columns and the Daily Report
A4: $ → ₹ Exchange Rate | E4: 94 | F4: ← rupees per US dollar; converts the per-kilo export rates
A5: Balances are counted in each product's own unit. Only kilos are comparable across products, so every total is taken in kilos.
A7: Brand | B7: Product | C7: Unit | D7: Kg / Unit | E7: Opening Balance | F7: Today's Production | G7: Today's Shipment | H7: Production to Date | I7: Shipment to Date | J7: Closing Balance | K7: Closing Stock (Kg) | L7: Rate / Kg ($) | M7: Stock Value (₹) | O7: Key (do not edit) | P7: Moved today | Q7: Rank | R7: Brand seq | S7: Opening kg | T7: Prod kg today | U7: Ship kg today | V7: Prod kg to date | W7: Ship kg to date | X7: Needs Kg/Unit | Y7: Duplicate key
A8: Blue Dolphin | B8: PD PVN 100/200 | C8: Slab | D8: 2 | E8: 11459 | F8: =IF($A8="","",SUMIFS('Daily Entry'!$C$7:$C$5003,'Daily Entry'!$B$7:$B$5003,$O8,'Daily Entry'!$A$7:$A$5003,$E$3)) | G8: =IF($A8="","",SUMIFS('Daily Entry'!$D$7:$D$5003,'Daily Entry'!$B$7:$B$5003,$O8,'Daily Entry'!$A$7:$A$5003,$E$3)) | H8: =IF($A8="","",SUMIFS('Daily Entry'!$C$7:$C$5003,'Daily Entry'!$B$7:$B$5003,$O8)) | I8: =IF($A8="","",SUMIFS('Daily Entry'!$D$7:$D$5003,'Daily Entry'!$B$7:$B$5003,$O8)) | J8: =IF($A8="","",$E8+$H8-$I8) | K8: =IF(OR($A8="",$D8=""),"",$J8*$D8) | L8: 7.25 | M8: =IF(OR($A8="",$D8="",$L8="",$E$4=""),"",$K8*$L8*$E$4) | O8: =IF($A8="","",$A8&" - "&$B8) | P8: =IF($A8="",0,IF(OR($F8<>0,$G8<>0),1,0)) | Q8: =IF($P8=1,SUM($P$8:$P8),"") | R8: =IF($A8="","",$A8&"#"&COUNTIF($A$8:$A8,$A8)) | S8: =IF(OR($A8="",$D8=""),0,$E8*$D8) | T8: =IF(OR($A8="",$D8=""),0,$F8*$D8) | U8: =IF(OR($A8="",$D8=""),0,$G8*$D8) | V8: =IF(OR($A8="",$D8=""),0,$H8*$D8) | W8: =IF(OR($A8="",$D8=""),0,$I8*$D8) | X8: =IF(AND($A8<>"",$D8=""),1,0) | Y8: =IF($A8="",0,IF(COUNTIF($O$8:$O$101,$O8)>1,1,0))
A9: Blue Dolphin | B9: PD KKD 100/200 | C9: Slab | D9: 2 | E9: 517 | F9: =IF($A9="","",SUMIFS('Daily Entry'!$C$7:$C$5003,'Daily Entry'!$B$7:$B$5003,$O9,'Daily Entry'!$A$7:$A$5003,$E$3)) | G9: =IF($A9="","",SUMIFS('Daily Entry'!$D$7:$D$5003,'Daily Entry'!$B$7:$B$5003,$O9,'Daily Entry'!$A$7:$A$5003,$E$3)) | H9: =IF($A9="","",SUMIFS('Daily Entry'!$C$7:$C$5003,'Daily Entry'!$B$7:$B$5003,$O9)) | I9: =IF($A9="","",SUMIFS('Daily Entry'!$D$7:$D$5003,'Daily Entry'!$B$7:$B$5003,$O9)) | J9: =IF($A9="","",$E9+$H9-$I9) | K9: =IF(OR($A9="",$D9=""),"",$J9*$D9) | L9: 7.25 | M9: =IF(OR($A9="",$D9="",$L9="",$E$4=""),"",$K9*$L9*$E$4) | O9: =IF($A9="","",$A9&" - "&$B9) | P9: =IF($A9="",0,IF(OR($F9<>0,$G9<>0),1,0)) | Q9: =IF($P9=1,SUM($P$8:$P9),"") | R9: =IF($A9="","",$A9&"#"&COUNTIF($A$8:$A9,$A9)) | S9: =IF(OR($A9="",$D9=""),0,$E9*$D9) | T9: =IF(OR($A9="",$D9=""),0,$F9*$D9) | U9: =IF(OR($A9="",$D9=""),0,$G9*$D9) | V9: =IF(OR($A9="",$D9=""),0,$H9*$D9) | W9: =IF(OR($A9="",$D9=""),0,$I9*$D9) | X9: =IF(AND($A9<>"",$D9=""),1,0) | Y9: =IF($A9="",0,IF(COUNTIF($O$8:$O$101,$O9)>1,1,0))
A10: Blue Dolphin | B10: PD PVN 200/300 | C10: Slab | D10: 2 | E10: 2357 | F10: =IF($A10="","",SUMIFS('Daily Entry'!$C$7:$C$5003,'Daily Entry'!$B$7:$B$5003,$O10,'Daily Entry'!$A$7:$A$5003,$E$3)) | G10: =IF($A10="","",SUMIFS('Daily Entry'!$D$7:$D$5003,'Daily Entry'!$B$7:$B$5003,$O10,'Daily Entry'!$A$7:$A$5003,$E$3)) | H10: =IF($A10="","",SUMIFS('Daily Entry'!$C$7:$C$5003,'Daily Entry'!$B$7:$B$5003,$O10)) | I10: =IF($A10="","",SUMIFS('Daily Entry'!$D$7:$D$5003,'Daily Entry'!$B$7:$B$5003,$O10)) | J10: =IF($A10="","",$E10+$H10-$I10) | K10: =IF(OR($A10="",$D10=""),"",$J10*$D10) | L10: 6.65 | M10: =IF(OR($A10="",$D10="",$L10="",$E$4=""),"",$K10*$L10*$E$4) | O10: =IF($A10="","",$A10&" - "&$B10) | P10: =IF($A10="",0,IF(OR($F10<>0,$G10<>0),1,0)) | Q10: =IF($P10=1,SUM($P$8:$P10),"") | R10: =IF($A10="","",$A10&"#"&COUNTIF($A$8:$A10,$A10)) | S10: =IF(OR($A10="",$D10=""),0,$E10*$D10) | T10: =IF(OR($A10="",$D10=""),0,$F10*$D10) | U10: =IF(OR($A10="",$D10=""),0,$G10*$D10) | V10: =IF(OR($A10="",$D10=""),0,$H10*$D10) | W10: =IF(OR($A10="",$D10=""),0,$I10*$D10) | X10: =IF(AND($A10<>"",$D10=""),1,0) | Y10: =IF($A10="",0,IF(COUNTIF($O$8:$O$101,$O10)>1,1,0))
A11: Blue Dolphin | B11: PD KKD 200/300 | C11: Slab | D11: 2 | E11: 0 | F11: =IF($A11="","",SUMIFS('Daily Entry'!$C$7:$C$5003,'Daily Entry'!$B$7:$B$5003,$O11,'Daily Entry'!$A$7:$A$5003,$E$3)) | G11: =IF($A11="","",SUMIFS('Daily Entry'!$D$7:$D$5003,'Daily Entry'!$B$7:$B$5003,$O11,'Daily Entry'!$A$7:$A$5003,$E$3)) | H11: =IF($A11="","",SUMIFS('Daily Entry'!$C$7:$C$5003,'Daily Entry'!$B$7:$B$5003,$O11)) | I11: =IF($A11="","",SUMIFS('Daily Entry'!$D$7:$D$5003,'Daily Entry'!$B$7:$B$5003,$O11)) | J11: =IF($A11="","",$E11+$H11-$I11) | K11: =IF(OR($A11="",$D11=""),"",$J11*$D11) | L11: 6.65 | M11: =IF(OR($A11="",$D11="",$L11="",$E$4=""),"",$K11*$L11*$E$4) | O11: =IF($A11="","",$A11&" - "&$B11) | P11: =IF($A11="",0,IF(OR($F11<>0,$G11<>0),1,0)) | Q11: =IF($P11=1,SUM($P$8:$P11),"") | R11: =IF($A11="","",$A11&"#"&COUNTIF($A$8:$A11,$A11)) | S11: =IF(OR($A11="",$D11=""),0,$E11*$D11) | T11: =IF(OR($A11="",$D11=""),0,$F11*$D11) | U11: =IF(OR($A11="",$D11=""),0,$G11*$D11) | V11: =IF(OR($A11="",$D11=""),0,$H11*$D11) | W11: =IF(OR($A11="",$D11=""),0,$I11*$D11) | X11: =IF(AND($A11<>"",$D11=""),1,0) | Y11: =IF($A11="",0,IF(COUNTIF($O$8:$O$101,$O11)>1,1,0))
A12: Blue Dolphin | B12: PUD PVN 200/300 | C12: Slab | D12: 2 | E12: 2262 | F12: =IF($A12="","",SUMIFS('Daily Entry'!$C$7:$C$5003,'Daily Entry'!$B$7:$B$5003,$O12,'Daily Entry'!$A$7:$A$5003,$E$3)) | G12: =IF($A12="","",SUMIFS('Daily Entry'!$D$7:$D$5003,'Daily Entry'!$B$7:$B$5003,$O12,'Daily Entry'!$A$7:$A$5003,$E$3)) | H12: =IF($A12="","",SUMIFS('Daily Entry'!$C$7:$C$5003,'Daily Entry'!$B$7:$B$5003,$O12)) | I12: =IF($A12="","",SUMIFS('Daily Entry'!$D$7:$D$5003,'Daily Entry'!$B$7:$B$5003,$O12)) | J12: =IF($A12="","",$E12+$H12-$I12) | K12: =IF(OR($A12="",$D12=""),"",$J12*$D12) | L12: 6.3 | M12: =IF(OR($A12="",$D12="",$L12="",$E$4=""),"",$K12*$L12*$E$4) | O12: =IF($A12="","",$A12&" - "&$B12) | P12: =IF($A12="",0,IF(OR($F12<>0,$G12<>0),1,0)) | Q12: =IF($P12=1,SUM($P$8:$P12),"") | R12: =IF($A12="","",$A12&"#"&COUNTIF($A$8:$A12,$A12)) | S12: =IF(OR($A12="",$D12=""),0,$E12*$D12) | T12: =IF(OR($A12="",$D12=""),0,$F12*$D12) | U12: =IF(OR($A12="",$D12=""),0,$G12*$D12) | V12: =IF(OR($A12="",$D12=""),0,$H12*$D12) | W12: =IF(OR($A12="",$D12=""),0,$I12*$D12) | X12: =IF(AND($A12<>"",$D12=""),1,0) | Y12: =IF($A12="",0,IF(COUNTIF($O$8:$O$101,$O12)>1,1,0))
A13: Blue Dolphin | B13: PUD KKD 200/300 | C13: Slab | D13: 2 | E13: 2835 | F13: =IF($A13="","",SUMIFS('Daily Entry'!$C$7:$C$5003,'Daily Entry'!$B$7:$B$5003,$O13,'Daily Entry'!$A$7:$A$5003,$E$3)) | G13: =IF($A13="","",SUMIFS('Daily Entry'!$D$7:$D$5003,'Daily Entry'!$B$7:$B$5003,$O13,'Daily Entry'!$A$7:$A$5003,$E$3)) | H13: =IF($A13="","",SUMIFS('Daily Entry'!$C$7:$C$5003,'Daily Entry'!$B$7:$B$5003,$O13)) | I13: =IF($A13="","",SUMIFS('Daily Entry'!$D$7:$D$5003,'Daily Entry'!$B$7:$B$5003,$O13)) | J13: =IF($A13="","",$E13+$H13-$I13) | K13: =IF(OR($A13="",$D13=""),"",$J13*$D13) | L13: 6.3 | M13: =IF(OR($A13="",$D13="",$L13="",$E$4=""),"",$K13*$L13*$E$4) | O13: =IF($A13="","",$A13&" - "&$B13) | P13: =IF($A13="",0,IF(OR($F13<>0,$G13<>0),1,0)) | Q13: =IF($P13=1,SUM($P$8:$P13),"") | R13: =IF($A13="","",$A13&"#"&COUNTIF($A$8:$A13,$A13)) | S13: =IF(OR($A13="",$D13=""),0,$E13*$D13) | T13: =IF(OR($A13="",$D13=""),0,$F13*$D13) | U13: =IF(OR($A13="",$D13=""),0,$G13*$D13) | V13: =IF(OR($A13="",$D13=""),0,$H13*$D13) | W13: =IF(OR($A13="",$D13=""),0,$I13*$D13) | X13: =IF(AND($A13<>"",$D13=""),1,0) | Y13: =IF($A13="",0,IF(COUNTIF($O$8:$O$101,$O13)>1,1,0))
A14: Blue Dolphin | B14: PUD PVN 300/500 | C14: Slab | D14: 2 | E14: 1673 | F14: =IF($A14="","",SUMIFS('Daily Entry'!$C$7:$C$5003,'Daily Entry'!$B$7:$B$5003,$O14,'Daily Entry'!$A$7:$A$5003,$E$3)) | G14: =IF($A14="","",SUMIFS('Daily Entry'!$D$7:$D$5003,'Daily Entry'!$B$7:$B$5003,$O14,'Daily Entry'!$A$7:$A$5003,$E$3)) | H14: =IF($A14="","",SUMIFS('Daily Entry'!$C$7:$C$5003,'Daily Entry'!$B$7:$B$5003,$O14)) | I14: =IF($A14="","",SUMIFS('Daily Entry'!$D$7:$D$5003,'Daily Entry'!$B$7:$B$5003,$O14)) | J14: =IF($A14="","",$E14+$H14-$I14) | K14: =IF(OR($A14="",$D14=""),"",$J14*$D14) | L14: 6.25 | M14: =IF(OR($A14="",$D14="",$L14="",$E$4=""),"",$K14*$L14*$E$4) | O14: =IF($A14="","",$A14&" - "&$B14) | P14: =IF($A14="",0,IF(OR($F14<>0,$G14<>0),1,0)) | Q14: =IF($P14=1,SUM($P$8:$P14),"") | R14: =IF($A14="","",$A14&"#"&COUNTIF($A$8:$A14,$A14)) | S14: =IF(OR($A14="",$D14=""),0,$E14*$D14) | T14: =IF(OR($A14="",$D14=""),0,$F14*$D14) | U14: =IF(OR($A14="",$D14=""),0,$G14*$D14) | V14: =IF(OR($A14="",$D14=""),0,$H14*$D14) | W14: =IF(OR($A14="",$D14=""),0,$I14*$D14) | X14: =IF(AND($A14<>"",$D14=""),1,0) | Y14: =IF($A14="",0,IF(COUNTIF($O$8:$O$101,$O14)>1,1,0))
A15: Blue Dolphin | B15: PUD KKD 300/500 | C15: Slab | D15: 2 | E15: 7542 | F15: =IF($A15="","",SUMIFS('Daily Entry'!$C$7:$C$5003,'Daily Entry'!$B$7:$B$5003,$O15,'Daily Entry'!$A$7:$A$5003,$E$3)) | G15: =IF($A15="","",SUMIFS('Daily Entry'!$D$7:$D$5003,'Daily Entry'!$B$7:$B$5003,$O15,'Daily Entry'!$A$7:$A$5003,$E$3)) | H15: =IF($A15="","",SUMIFS('Daily Entry'!$C$7:$C$5003,'Daily Entry'!$B$7:$B$5003,$O15)) | I15: =IF($A15="","",SUMIFS('Daily Entry'!$D$7:$D$5003,'Daily Entry'!$B$7:$B$5003,$O15)) | J15: =IF($A15="","",$E15+$H15-$I15) | K15: =IF(OR($A15="",$D15=""),"",$J15*$D15) | L15: 6.25 | M15: =IF(OR($A15="",$D15="",$L15="",$E$4=""),"",$K15*$L15*$E$4) | O15: =IF($A15="","",$A15&" - "&$B15) | P15: =IF($A15="",0,IF(OR($F15<>0,$G15<>0),1,0)) | Q15: =IF($P15=1,SUM($P$8:$P15),"") | R15: =IF($A15="","",$A15&"#"&COUNTIF($A$8:$A15,$A15)) | S15: =IF(OR($A15="",$D15=""),0,$E15*$D15) | T15: =IF(OR($A15="",$D15=""),0,$F15*$D15) | U15: =IF(OR($A15="",$D15=""),0,$G15*$D15) | V15: =IF(OR($A15="",$D15=""),0,$H15*$D15) | W15: =IF(OR($A15="",$D15=""),0,$I15*$D15) | X15: =IF(AND($A15<>"",$D15=""),1,0) | Y15: =IF($A15="",0,IF(COUNTIF($O$8:$O$101,$O15)>1,1,0))
A16: Primus Japan | B16: PD PVN 100/200 | C16: Slab | D16: 2 | E16: 0 | F16: =IF($A16="","",SUMIFS('Daily Entry'!$C$7:$C$5003,'Daily Entry'!$B$7:$B$5003,$O16,'Daily Entry'!$A$7:$A$5003,$E$3)) | G16: =IF($A16="","",SUMIFS('Daily Entry'!$D$7:$D$5003,'Daily Entry'!$B$7:$B$5003,$O16,'Daily Entry'!$A$7:$A$5003,$E$3)) | H16: =IF($A16="","",SUMIFS('Daily Entry'!$C$7:$C$5003,'Daily Entry'!$B$7:$B$5003,$O16)) | I16: =IF($A16="","",SUMIFS('Daily Entry'!$D$7:$D$5003,'Daily Entry'!$B$7:$B$5003,$O16)) | J16: =IF($A16="","",$E16+$H16-$I16) | K16: =IF(OR($A16="",$D16=""),"",$J16*$D16) | L16: 7 | M16: =IF(OR($A16="",$D16="",$L16="",$E$4=""),"",$K16*$L16*$E$4) | O16: =IF($A16="","",$A16&" - "&$B16) | P16: =IF($A16="",0,IF(OR($F16<>0,$G16<>0),1,0)) | Q16: =IF($P16=1,SUM($P$8:$P16),"") | R16: =IF($A16="","",$A16&"#"&COUNTIF($A$8:$A16,$A16)) | S16: =IF(OR($A16="",$D16=""),0,$E16*$D16) | T16: =IF(OR($A16="",$D16=""),0,$F16*$D16) | U16: =IF(OR($A16="",$D16=""),0,$G16*$D16) | V16: =IF(OR($A16="",$D16=""),0,$H16*$D16) | W16: =IF(OR($A16="",$D16=""),0,$I16*$D16) | X16: =IF(AND($A16<>"",$D16=""),1,0) | Y16: =IF($A16="",0,IF(COUNTIF($O$8:$O$101,$O16)>1,1,0))
A17: Primus Japan | B17: PD KKD 100/200 | C17: Slab | D17: 2 | E17: 0 | F17: =IF($A17="","",SUMIFS('Daily Entry'!$C$7:$C$5003,'Daily Entry'!$B$7:$B$5003,$O17,'Daily Entry'!$A$7:$A$5003,$E$3)) | G17: =IF($A17="","",SUMIFS('Daily Entry'!$D$7:$D$5003,'Daily Entry'!$B$7:$B$5003,$O17,'Daily Entry'!$A$7:$A$5003,$E$3)) | H17: =IF($A17="","",SUMIFS('Daily Entry'!$C$7:$C$5003,'Daily Entry'!$B$7:$B$5003,$O17)) | I17: =IF($A17="","",SUMIFS('Daily Entry'!$D$7:$D$5003,'Daily Entry'!$B$7:$B$5003,$O17)) | J17: =IF($A17="","",$E17+$H17-$I17) | K17: =IF(OR($A17="",$D17=""),"",$J17*$D17) | M17: =IF(OR($A17="",$D17="",$L17="",$E$4=""),"",$K17*$L17*$E$4) | O17: =IF($A17="","",$A17&" - "&$B17) | P17: =IF($A17="",0,IF(OR($F17<>0,$G17<>0),1,0)) | Q17: =IF($P17=1,SUM($P$8:$P17),"") | R17: =IF($A17="","",$A17&"#"&COUNTIF($A$8:$A17,$A17)) | S17: =IF(OR($A17="",$D17=""),0,$E17*$D17) | T17: =IF(OR($A17="",$D17=""),0,$F17*$D17) | U17: =IF(OR($A17="",$D17=""),0,$G17*$D17) | V17: =IF(OR($A17="",$D17=""),0,$H17*$D17) | W17: =IF(OR($A17="",$D17=""),0,$I17*$D17) | X17: =IF(AND($A17<>"",$D17=""),1,0) | Y17: =IF($A17="",0,IF(COUNTIF($O$8:$O$101,$O17)>1,1,0))
A18: Primus Japan | B18: PD PVN 200/300 | C18: Slab | D18: 2 | E18: 0 | F18: =IF($A18="","",SUMIFS('Daily Entry'!$C$7:$C$5003,'Daily Entry'!$B$7:$B$5003,$O18,'Daily Entry'!$A$7:$A$5003,$E$3)) | G18: =IF($A18="","",SUMIFS('Daily Entry'!$D$7:$D$5003,'Daily Entry'!$B$7:$B$5003,$O18,'Daily Entry'!$A$7:$A$5003,$E$3)) | H18: =IF($A18="","",SUMIFS('Daily Entry'!$C$7:$C$5003,'Daily Entry'!$B$7:$B$5003,$O18)) | I18: =IF($A18="","",SUMIFS('Daily Entry'!$D$7:$D$5003,'Daily Entry'!$B$7:$B$5003,$O18)) | J18: =IF($A18="","",$E18+$H18-$I18) | K18: =IF(OR($A18="",$D18=""),"",$J18*$D18) | M18: =IF(OR($A18="",$D18="",$L18="",$E$4=""),"",$K18*$L18*$E$4) | O18: =IF($A18="","",$A18&" - "&$B18) | P18: =IF($A18="",0,IF(OR($F18<>0,$G18<>0),1,0)) | Q18: =IF($P18=1,SUM($P$8:$P18),"") | R18: =IF($A18="","",$A18&"#"&COUNTIF($A$8:$A18,$A18)) | S18: =IF(OR($A18="",$D18=""),0,$E18*$D18) | T18: =IF(OR($A18="",$D18=""),0,$F18*$D18) | U18: =IF(OR($A18="",$D18=""),0,$G18*$D18) | V18: =IF(OR($A18="",$D18=""),0,$H18*$D18) | W18: =IF(OR($A18="",$D18=""),0,$I18*$D18) | X18: =IF(AND($A18<>"",$D18=""),1,0) | Y18: =IF($A18="",0,IF(COUNTIF($O$8:$O$101,$O18)>1,1,0))
A19: Primus Japan | B19: PD KKD 200/300 | C19: Slab | D19: 2 | E19: 0 | F19: =IF($A19="","",SUMIFS('Daily Entry'!$C$7:$C$5003,'Daily Entry'!$B$7:$B$5003,$O19,'Daily Entry'!$A$7:$A$5003,$E$3)) | G19: =IF($A19="","",SUMIFS('Daily Entry'!$D$7:$D$5003,'Daily Entry'!$B$7:$B$5003,$O19,'Daily Entry'!$A$7:$A$5003,$E$3)) | H19: =IF($A19="","",SUMIFS('Daily Entry'!$C$7:$C$5003,'Daily Entry'!$B$7:$B$5003,$O19)) | I19: =IF($A19="","",SUMIFS('Daily Entry'!$D$7:$D$5003,'Daily Entry'!$B$7:$B$5003,$O19)) | J19: =IF($A19="","",$E19+$H19-$I19) | K19: =IF(OR($A19="",$D19=""),"",$J19*$D19) | M19: =IF(OR($A19="",$D19="",$L19="",$E$4=""),"",$K19*$L19*$E$4) | O19: =IF($A19="","",$A19&" - "&$B19) | P19: =IF($A19="",0,IF(OR($F19<>0,$G19<>0),1,0)) | Q19: =IF($P19=1,SUM($P$8:$P19),"") | R19: =IF($A19="","",$A19&"#"&COUNTIF($A$8:$A19,$A19)) | S19: =IF(OR($A19="",$D19=""),0,$E19*$D19) | T19: =IF(OR($A19="",$D19=""),0,$F19*$D19) | U19: =IF(OR($A19="",$D19=""),0,$G19*$D19) | V19: =IF(OR($A19="",$D19=""),0,$H19*$D19) | W19: =IF(OR($A19="",$D19=""),0,$I19*$D19) | X19: =IF(AND($A19<>"",$D19=""),1,0) | Y19: =IF($A19="",0,IF(COUNTIF($O$8:$O$101,$O19)>1,1,0))
A20: Primus Japan | B20: PUD KZN 40/60 | C20: Slab | D20: 2 | E20: 64 | F20: =IF($A20="","",SUMIFS('Daily Entry'!$C$7:$C$5003,'Daily Entry'!$B$7:$B$5003,$O20,'Daily Entry'!$A$7:$A$5003,$E$3)) | G20: =IF($A20="","",SUMIFS('Daily Entry'!$D$7:$D$5003,'Daily Entry'!$B$7:$B$5003,$O20,'Daily Entry'!$A$7:$A$5003,$E$3)) | H20: =IF($A20="","",SUMIFS('Daily Entry'!$C$7:$C$5003,'Daily Entry'!$B$7:$B$5003,$O20)) | I20: =IF($A20="","",SUMIFS('Daily Entry'!$D$7:$D$5003,'Daily Entry'!$B$7:$B$5003,$O20)) | J20: =IF($A20="","",$E20+$H20-$I20) | K20: =IF(OR($A20="",$D20=""),"",$J20*$D20) | L20: 6.5 | M20: =IF(OR($A20="",$D20="",$L20="",$E$4=""),"",$K20*$L20*$E$4) | O20: =IF($A20="","",$A20&" - "&$B20) | P20: =IF($A20="",0,IF(OR($F20<>0,$G20<>0),1,0)) | Q20: =IF($P20=1,SUM($P$8:$P20),"") | R20: =IF($A20="","",$A20&"#"&COUNTIF($A$8:$A20,$A20)) | S20: =IF(OR($A20="",$D20=""),0,$E20*$D20) | T20: =IF(OR($A20="",$D20=""),0,$F20*$D20) | U20: =IF(OR($A20="",$D20=""),0,$G20*$D20) | V20: =IF(OR($A20="",$D20=""),0,$H20*$D20) | W20: =IF(OR($A20="",$D20=""),0,$I20*$D20) | X20: =IF(AND($A20<>"",$D20=""),1,0) | Y20: =IF($A20="",0,IF(COUNTIF($O$8:$O$101,$O20)>1,1,0))
A21: Primus Japan | B21: PUD KZN 60/80 | C21: Slab | D21: 2 | E21: 191 | F21: =IF($A21="","",SUMIFS('Daily Entry'!$C$7:$C$5003,'Daily Entry'!$B$7:$B$5003,$O21,'Daily Entry'!$A$7:$A$5003,$E$3)) | G21: =IF($A21="","",SUMIFS('Daily Entry'!$D$7:$D$5003,'Daily Entry'!$B$7:$B$5003,$O21,'Daily Entry'!$A$7:$A$5003,$E$3)) | H21: =IF($A21="","",SUMIFS('Daily Entry'!$C$7:$C$5003,'Daily Entry'!$B$7:$B$5003,$O21)) | I21: =IF($A21="","",SUMIFS('Daily Entry'!$D$7:$D$5003,'Daily Entry'!$B$7:$B$5003,$O21)) | J21: =IF($A21="","",$E21+$H21-$I21) | K21: =IF(OR($A21="",$D21=""),"",$J21*$D21) | L21: 6.5 | M21: =IF(OR($A21="",$D21="",$L21="",$E$4=""),"",$K21*$L21*$E$4) | O21: =IF($A21="","",$A21&" - "&$B21) | P21: =IF($A21="",0,IF(OR($F21<>0,$G21<>0),1,0)) | Q21: =IF($P21=1,SUM($P$8:$P21),"") | R21: =IF($A21="","",$A21&"#"&COUNTIF($A$8:$A21,$A21)) | S21: =IF(OR($A21="",$D21=""),0,$E21*$D21) | T21: =IF(OR($A21="",$D21=""),0,$F21*$D21) | U21: =IF(OR($A21="",$D21=""),0,$G21*$D21) | V21: =IF(OR($A21="",$D21=""),0,$H21*$D21) | W21: =IF(OR($A21="",$D21=""),0,$I21*$D21) | X21: =IF(AND($A21<>"",$D21=""),1,0) | Y21: =IF($A21="",0,IF(COUNTIF($O$8:$O$101,$O21)>1,1,0))
A22: Primus Japan | B22: PUD PVN 80/120 | C22: Slab | D22: 2 | E22: 16849 | F22: =IF($A22="","",SUMIFS('Daily Entry'!$C$7:$C$5003,'Daily Entry'!$B$7:$B$5003,$O22,'Daily Entry'!$A$7:$A$5003,$E$3)) | G22: =IF($A22="","",SUMIFS('Daily Entry'!$D$7:$D$5003,'Daily Entry'!$B$7:$B$5003,$O22,'Daily Entry'!$A$7:$A$5003,$E$3)) | H22: =IF($A22="","",SUMIFS('Daily Entry'!$C$7:$C$5003,'Daily Entry'!$B$7:$B$5003,$O22)) | I22: =IF($A22="","",SUMIFS('Daily Entry'!$D$7:$D$5003,'Daily Entry'!$B$7:$B$5003,$O22)) | J22: =IF($A22="","",$E22+$H22-$I22) | K22: =IF(OR($A22="",$D22=""),"",$J22*$D22) | L22: 6.5 | M22: =IF(OR($A22="",$D22="",$L22="",$E$4=""),"",$K22*$L22*$E$4) | O22: =IF($A22="","",$A22&" - "&$B22) | P22: =IF($A22="",0,IF(OR($F22<>0,$G22<>0),1,0)) | Q22: =IF($P22=1,SUM($P$8:$P22),"") | R22: =IF($A22="","",$A22&"#"&COUNTIF($A$8:$A22,$A22)) | S22: =IF(OR($A22="",$D22=""),0,$E22*$D22) | T22: =IF(OR($A22="",$D22=""),0,$F22*$D22) | U22: =IF(OR($A22="",$D22=""),0,$G22*$D22) | V22: =IF(OR($A22="",$D22=""),0,$H22*$D22) | W22: =IF(OR($A22="",$D22=""),0,$I22*$D22) | X22: =IF(AND($A22<>"",$D22=""),1,0) | Y22: =IF($A22="",0,IF(COUNTIF($O$8:$O$101,$O22)>1,1,0))
A23: Primus Japan | B23: PUD KZN 80/120 | C23: Slab | D23: 2 | E23: 466 | F23: =IF($A23="","",SUMIFS('Daily Entry'!$C$7:$C$5003,'Daily Entry'!$B$7:$B$5003,$O23,'Daily Entry'!$A$7:$A$5003,$E$3)) | G23: =IF($A23="","",SUMIFS('Daily Entry'!$D$7:$D$5003,'Daily Entry'!$B$7:$B$5003,$O23,'Daily Entry'!$A$7:$A$5003,$E$3)) | H23: =IF($A23="","",SUMIFS('Daily Entry'!$C$7:$C$5003,'Daily Entry'!$B$7:$B$5003,$O23)) | I23: =IF($A23="","",SUMIFS('Daily Entry'!$D$7:$D$5003,'Daily Entry'!$B$7:$B$5003,$O23)) | J23: =IF($A23="","",$E23+$H23-$I23) | K23: =IF(OR($A23="",$D23=""),"",$J23*$D23) | L23: 6.5 | M23: =IF(OR($A23="",$D23="",$L23="",$E$4=""),"",$K23*$L23*$E$4) | O23: =IF($A23="","",$A23&" - "&$B23) | P23: =IF($A23="",0,IF(OR($F23<>0,$G23<>0),1,0)) | Q23: =IF($P23=1,SUM($P$8:$P23),"") | R23: =IF($A23="","",$A23&"#"&COUNTIF($A$8:$A23,$A23)) | S23: =IF(OR($A23="",$D23=""),0,$E23*$D23) | T23: =IF(OR($A23="",$D23=""),0,$F23*$D23) | U23: =IF(OR($A23="",$D23=""),0,$G23*$D23) | V23: =IF(OR($A23="",$D23=""),0,$H23*$D23) | W23: =IF(OR($A23="",$D23=""),0,$I23*$D23) | X23: =IF(AND($A23<>"",$D23=""),1,0) | Y23: =IF($A23="",0,IF(COUNTIF($O$8:$O$101,$O23)>1,1,0))
A24: Primus Japan | B24: PUD NRN 80/120 | C24: Slab | D24: 2 | E24: 69 | F24: =IF($A24="","",SUMIFS('Daily Entry'!$C$7:$C$5003,'Daily Entry'!$B$7:$B$5003,$O24,'Daily Entry'!$A$7:$A$5003,$E$3)) | G24: =IF($A24="","",SUMIFS('Daily Entry'!$D$7:$D$5003,'Daily Entry'!$B$7:$B$5003,$O24,'Daily Entry'!$A$7:$A$5003,$E$3)) | H24: =IF($A24="","",SUMIFS('Daily Entry'!$C$7:$C$5003,'Daily Entry'!$B$7:$B$5003,$O24)) | I24: =IF($A24="","",SUMIFS('Daily Entry'!$D$7:$D$5003,'Daily Entry'!$B$7:$B$5003,$O24)) | J24: =IF($A24="","",$E24+$H24-$I24) | K24: =IF(OR($A24="",$D24=""),"",$J24*$D24) | L24: 6.5 | M24: =IF(OR($A24="",$D24="",$L24="",$E$4=""),"",$K24*$L24*$E$4) | O24: =IF($A24="","",$A24&" - "&$B24) | P24: =IF($A24="",0,IF(OR($F24<>0,$G24<>0),1,0)) | Q24: =IF($P24=1,SUM($P$8:$P24),"") | R24: =IF($A24="","",$A24&"#"&COUNTIF($A$8:$A24,$A24)) | S24: =IF(OR($A24="",$D24=""),0,$E24*$D24) | T24: =IF(OR($A24="",$D24=""),0,$F24*$D24) | U24: =IF(OR($A24="",$D24=""),0,$G24*$D24) | V24: =IF(OR($A24="",$D24=""),0,$H24*$D24) | W24: =IF(OR($A24="",$D24=""),0,$I24*$D24) | X24: =IF(AND($A24<>"",$D24=""),1,0) | Y24: =IF($A24="",0,IF(COUNTIF($O$8:$O$101,$O24)>1,1,0))
A25: Primus Japan | B25: PUD PVN 100/200 | C25: Slab | D25: 2 | E25: 2617 | F25: =IF($A25="","",SUMIFS('Daily Entry'!$C$7:$C$5003,'Daily Entry'!$B$7:$B$5003,$O25,'Daily Entry'!$A$7:$A$5003,$E$3)) | G25: =IF($A25="","",SUMIFS('Daily Entry'!$D$7:$D$5003,'Daily Entry'!$B$7:$B$5003,$O25,'Daily Entry'!$A$7:$A$5003,$E$3)) | H25: =IF($A25="","",SUMIFS('Daily Entry'!$C$7:$C$5003,'Daily Entry'!$B$7:$B$5003,$O25)) | I25: =IF($A25="","",SUMIFS('Daily Entry'!$D$7:$D$5003,'Daily Entry'!$B$7:$B$5003,$O25)) | J25: =IF($A25="","",$E25+$H25-$I25) | K25: =IF(OR($A25="",$D25=""),"",$J25*$D25) | L25: 6.5 | M25: =IF(OR($A25="",$D25="",$L25="",$E$4=""),"",$K25*$L25*$E$4) | O25: =IF($A25="","",$A25&" - "&$B25) | P25: =IF($A25="",0,IF(OR($F25<>0,$G25<>0),1,0)) | Q25: =IF($P25=1,SUM($P$8:$P25),"") | R25: =IF($A25="","",$A25&"#"&COUNTIF($A$8:$A25,$A25)) | S25: =IF(OR($A25="",$D25=""),0,$E25*$D25) | T25: =IF(OR($A25="",$D25=""),0,$F25*$D25) | U25: =IF(OR($A25="",$D25=""),0,$G25*$D25) | V25: =IF(OR($A25="",$D25=""),0,$H25*$D25) | W25: =IF(OR($A25="",$D25=""),0,$I25*$D25) | X25: =IF(AND($A25<>"",$D25=""),1,0) | Y25: =IF($A25="",0,IF(COUNTIF($O$8:$O$101,$O25)>1,1,0))
A26: Primus Japan | B26: PUD KKD 100/200 | C26: Slab | D26: 2 | E26: 0 | F26: =IF($A26="","",SUMIFS('Daily Entry'!$C$7:$C$5003,'Daily Entry'!$B$7:$B$5003,$O26,'Daily Entry'!$A$7:$A$5003,$E$3)) | G26: =IF($A26="","",SUMIFS('Daily Entry'!$D$7:$D$5003,'Daily Entry'!$B$7:$B$5003,$O26,'Daily Entry'!$A$7:$A$5003,$E$3)) | H26: =IF($A26="","",SUMIFS('Daily Entry'!$C$7:$C$5003,'Daily Entry'!$B$7:$B$5003,$O26)) | I26: =IF($A26="","",SUMIFS('Daily Entry'!$D$7:$D$5003,'Daily Entry'!$B$7:$B$5003,$O26)) | J26: =IF($A26="","",$E26+$H26-$I26) | K26: =IF(OR($A26="",$D26=""),"",$J26*$D26) | M26: =IF(OR($A26="",$D26="",$L26="",$E$4=""),"",$K26*$L26*$E$4) | O26: =IF($A26="","",$A26&" - "&$B26) | P26: =IF($A26="",0,IF(OR($F26<>0,$G26<>0),1,0)) | Q26: =IF($P26=1,SUM($P$8:$P26),"") | R26: =IF($A26="","",$A26&"#"&COUNTIF($A$8:$A26,$A26)) | S26: =IF(OR($A26="",$D26=""),0,$E26*$D26) | T26: =IF(OR($A26="",$D26=""),0,$F26*$D26) | U26: =IF(OR($A26="",$D26=""),0,$G26*$D26) | V26: =IF(OR($A26="",$D26=""),0,$H26*$D26) | W26: =IF(OR($A26="",$D26=""),0,$I26*$D26) | X26: =IF(AND($A26<>"",$D26=""),1,0) | Y26: =IF($A26="",0,IF(COUNTIF($O$8:$O$101,$O26)>1,1,0))
A27: Primus Japan | B27: PUD KZN 100/200 | C27: Slab | D27: 2 | E27: 4209 | F27: =IF($A27="","",SUMIFS('Daily Entry'!$C$7:$C$5003,'Daily Entry'!$B$7:$B$5003,$O27,'Daily Entry'!$A$7:$A$5003,$E$3)) | G27: =IF($A27="","",SUMIFS('Daily Entry'!$D$7:$D$5003,'Daily Entry'!$B$7:$B$5003,$O27,'Daily Entry'!$A$7:$A$5003,$E$3)) | H27: =IF($A27="","",SUMIFS('Daily Entry'!$C$7:$C$5003,'Daily Entry'!$B$7:$B$5003,$O27)) | I27: =IF($A27="","",SUMIFS('Daily Entry'!$D$7:$D$5003,'Daily Entry'!$B$7:$B$5003,$O27)) | J27: =IF($A27="","",$E27+$H27-$I27) | K27: =IF(OR($A27="",$D27=""),"",$J27*$D27) | L27: 5.5 | M27: =IF(OR($A27="",$D27="",$L27="",$E$4=""),"",$K27*$L27*$E$4) | O27: =IF($A27="","",$A27&" - "&$B27) | P27: =IF($A27="",0,IF(OR($F27<>0,$G27<>0),1,0)) | Q27: =IF($P27=1,SUM($P$8:$P27),"") | R27: =IF($A27="","",$A27&"#"&COUNTIF($A$8:$A27,$A27)) | S27: =IF(OR($A27="",$D27=""),0,$E27*$D27) | T27: =IF(OR($A27="",$D27=""),0,$F27*$D27) | U27: =IF(OR($A27="",$D27=""),0,$G27*$D27) | V27: =IF(OR($A27="",$D27=""),0,$H27*$D27) | W27: =IF(OR($A27="",$D27=""),0,$I27*$D27) | X27: =IF(AND($A27<>"",$D27=""),1,0) | Y27: =IF($A27="",0,IF(COUNTIF($O$8:$O$101,$O27)>1,1,0))
A28: Primus Japan | B28: PUD NRN 100/200 | C28: Slab | D28: 2 | E28: 13 | F28: =IF($A28="","",SUMIFS('Daily Entry'!$C$7:$C$5003,'Daily Entry'!$B$7:$B$5003,$O28,'Daily Entry'!$A$7:$A$5003,$E$3)) | G28: =IF($A28="","",SUMIFS('Daily Entry'!$D$7:$D$5003,'Daily Entry'!$B$7:$B$5003,$O28,'Daily Entry'!$A$7:$A$5003,$E$3)) | H28: =IF($A28="","",SUMIFS('Daily Entry'!$C$7:$C$5003,'Daily Entry'!$B$7:$B$5003,$O28)) | I28: =IF($A28="","",SUMIFS('Daily Entry'!$D$7:$D$5003,'Daily Entry'!$B$7:$B$5003,$O28)) | J28: =IF($A28="","",$E28+$H28-$I28) | K28: =IF(OR($A28="",$D28=""),"",$J28*$D28) | L28: 5.5 | M28: =IF(OR($A28="",$D28="",$L28="",$E$4=""),"",$K28*$L28*$E$4) | O28: =IF($A28="","",$A28&" - "&$B28) | P28: =IF($A28="",0,IF(OR($F28<>0,$G28<>0),1,0)) | Q28: =IF($P28=1,SUM($P$8:$P28),"") | R28: =IF($A28="","",$A28&"#"&COUNTIF($A$8:$A28,$A28)) | S28: =IF(OR($A28="",$D28=""),0,$E28*$D28) | T28: =IF(OR($A28="",$D28=""),0,$F28*$D28) | U28: =IF(OR($A28="",$D28=""),0,$G28*$D28) | V28: =IF(OR($A28="",$D28=""),0,$H28*$D28) | W28: =IF(OR($A28="",$D28=""),0,$I28*$D28) | X28: =IF(AND($A28<>"",$D28=""),1,0) | Y28: =IF($A28="",0,IF(COUNTIF($O$8:$O$101,$O28)>1,1,0))
A29: Primus Japan | B29: PUD PVN 200/300 | C29: Slab | D29: 2 | E29: 0 | F29: =IF($A29="","",SUMIFS('Daily Entry'!$C$7:$C$5003,'Daily Entry'!$B$7:$B$5003,$O29,'Daily Entry'!$A$7:$A$5003,$E$3)) | G29: =IF($A29="","",SUMIFS('Daily Entry'!$D$7:$D$5003,'Daily Entry'!$B$7:$B$5003,$O29,'Daily Entry'!$A$7:$A$5003,$E$3)) | H29: =IF($A29="","",SUMIFS('Daily Entry'!$C$7:$C$5003,'Daily Entry'!$B$7:$B$5003,$O29)) | I29: =IF($A29="","",SUMIFS('Daily Entry'!$D$7:$D$5003,'Daily Entry'!$B$7:$B$5003,$O29)) | J29: =IF($A29="","",$E29+$H29-$I29) | K29: =IF(OR($A29="",$D29=""),"",$J29*$D29) | L29: 6.15 | M29: =IF(OR($A29="",$D29="",$L29="",$E$4=""),"",$K29*$L29*$E$4) | O29: =IF($A29="","",$A29&" - "&$B29) | P29: =IF($A29="",0,IF(OR($F29<>0,$G29<>0),1,0)) | Q29: =IF($P29=1,SUM($P$8:$P29),"") | R29: =IF($A29="","",$A29&"#"&COUNTIF($A$8:$A29,$A29)) | S29: =IF(OR($A29="",$D29=""),0,$E29*$D29) | T29: =IF(OR($A29="",$D29=""),0,$F29*$D29) | U29: =IF(OR($A29="",$D29=""),0,$G29*$D29) | V29: =IF(OR($A29="",$D29=""),0,$H29*$D29) | W29: =IF(OR($A29="",$D29=""),0,$I29*$D29) | X29: =IF(AND($A29<>"",$D29=""),1,0) | Y29: =IF($A29="",0,IF(COUNTIF($O$8:$O$101,$O29)>1,1,0))
A30: Primus Japan | B30: PUD KKD 200/300 | C30: Slab | D30: 2 | E30: 2757 | F30: =IF($A30="","",SUMIFS('Daily Entry'!$C$7:$C$5003,'Daily Entry'!$B$7:$B$5003,$O30,'Daily Entry'!$A$7:$A$5003,$E$3)) | G30: =IF($A30="","",SUMIFS('Daily Entry'!$D$7:$D$5003,'Daily Entry'!$B$7:$B$5003,$O30,'Daily Entry'!$A$7:$A$5003,$E$3)) | H30: =IF($A30="","",SUMIFS('Daily Entry'!$C$7:$C$5003,'Daily Entry'!$B$7:$B$5003,$O30)) | I30: =IF($A30="","",SUMIFS('Daily Entry'!$D$7:$D$5003,'Daily Entry'!$B$7:$B$5003,$O30)) | J30: =IF($A30="","",$E30+$H30-$I30) | K30: =IF(OR($A30="",$D30=""),"",$J30*$D30) | L30: 6.15 | M30: =IF(OR($A30="",$D30="",$L30="",$E$4=""),"",$K30*$L30*$E$4) | O30: =IF($A30="","",$A30&" - "&$B30) | P30: =IF($A30="",0,IF(OR($F30<>0,$G30<>0),1,0)) | Q30: =IF($P30=1,SUM($P$8:$P30),"") | R30: =IF($A30="","",$A30&"#"&COUNTIF($A$8:$A30,$A30)) | S30: =IF(OR($A30="",$D30=""),0,$E30*$D30) | T30: =IF(OR($A30="",$D30=""),0,$F30*$D30) | U30: =IF(OR($A30="",$D30=""),0,$G30*$D30) | V30: =IF(OR($A30="",$D30=""),0,$H30*$D30) | W30: =IF(OR($A30="",$D30=""),0,$I30*$D30) | X30: =IF(AND($A30<>"",$D30=""),1,0) | Y30: =IF($A30="",0,IF(COUNTIF($O$8:$O$101,$O30)>1,1,0))
A31: Primus Japan | B31: PUD KZN 200/300 | C31: Slab | D31: 2 | E31: 1080 | F31: =IF($A31="","",SUMIFS('Daily Entry'!$C$7:$C$5003,'Daily Entry'!$B$7:$B$5003,$O31,'Daily Entry'!$A$7:$A$5003,$E$3)) | G31: =IF($A31="","",SUMIFS('Daily Entry'!$D$7:$D$5003,'Daily Entry'!$B$7:$B$5003,$O31,'Daily Entry'!$A$7:$A$5003,$E$3)) | H31: =IF($A31="","",SUMIFS('Daily Entry'!$C$7:$C$5003,'Daily Entry'!$B$7:$B$5003,$O31)) | I31: =IF($A31="","",SUMIFS('Daily Entry'!$D$7:$D$5003,'Daily Entry'!$B$7:$B$5003,$O31)) | J31: =IF($A31="","",$E31+$H31-$I31) | K31: =IF(OR($A31="",$D31=""),"",$J31*$D31) | L31: 5 | M31: =IF(OR($A31="",$D31="",$L31="",$E$4=""),"",$K31*$L31*$E$4) | O31: =IF($A31="","",$A31&" - "&$B31) | P31: =IF($A31="",0,IF(OR($F31<>0,$G31<>0),1,0)) | Q31: =IF($P31=1,SUM($P$8:$P31),"") | R31: =IF($A31="","",$A31&"#"&COUNTIF($A$8:$A31,$A31)) | S31: =IF(OR($A31="",$D31=""),0,$E31*$D31) | T31: =IF(OR($A31="",$D31=""),0,$F31*$D31) | U31: =IF(OR($A31="",$D31=""),0,$G31*$D31) | V31: =IF(OR($A31="",$D31=""),0,$H31*$D31) | W31: =IF(OR($A31="",$D31=""),0,$I31*$D31) | X31: =IF(AND($A31<>"",$D31=""),1,0) | Y31: =IF($A31="",0,IF(COUNTIF($O$8:$O$101,$O31)>1,1,0))
A32: Primus Japan | B32: PUD NRN 200/300 | C32: Slab | D32: 2 | E32: 0 | F32: =IF($A32="","",SUMIFS('Daily Entry'!$C$7:$C$5003,'Daily Entry'!$B$7:$B$5003,$O32,'Daily Entry'!$A$7:$A$5003,$E$3)) | G32: =IF($A32="","",SUMIFS('Daily Entry'!$D$7:$D$5003,'Daily Entry'!$B$7:$B$5003,$O32,'Daily Entry'!$A$7:$A$5003,$E$3)) | H32: =IF($A32="","",SUMIFS('Daily Entry'!$C$7:$C$5003,'Daily Entry'!$B$7:$B$5003,$O32)) | I32: =IF($A32="","",SUMIFS('Daily Entry'!$D$7:$D$5003,'Daily Entry'!$B$7:$B$5003,$O32)) | J32: =IF($A32="","",$E32+$H32-$I32) | K32: =IF(OR($A32="",$D32=""),"",$J32*$D32) | L32: 5 | M32: =IF(OR($A32="",$D32="",$L32="",$E$4=""),"",$K32*$L32*$E$4) | O32: =IF($A32="","",$A32&" - "&$B32) | P32: =IF($A32="",0,IF(OR($F32<>0,$G32<>0),1,0)) | Q32: =IF($P32=1,SUM($P$8:$P32),"") | R32: =IF($A32="","",$A32&"#"&COUNTIF($A$8:$A32,$A32)) | S32: =IF(OR($A32="",$D32=""),0,$E32*$D32) | T32: =IF(OR($A32="",$D32=""),0,$F32*$D32) | U32: =IF(OR($A32="",$D32=""),0,$G32*$D32) | V32: =IF(OR($A32="",$D32=""),0,$H32*$D32) | W32: =IF(OR($A32="",$D32=""),0,$I32*$D32) | X32: =IF(AND($A32<>"",$D32=""),1,0) | Y32: =IF($A32="",0,IF(COUNTIF($O$8:$O$101,$O32)>1,1,0))
A33: Primus Japan | B33: PUD PVN 300/500 | C33: Slab | D33: 2 | E33: 421 | F33: =IF($A33="","",SUMIFS('Daily Entry'!$C$7:$C$5003,'Daily Entry'!$B$7:$B$5003,$O33,'Daily Entry'!$A$7:$A$5003,$E$3)) | G33: =IF($A33="","",SUMIFS('Daily Entry'!$D$7:$D$5003,'Daily Entry'!$B$7:$B$5003,$O33,'Daily Entry'!$A$7:$A$5003,$E$3)) | H33: =IF($A33="","",SUMIFS('Daily Entry'!$C$7:$C$5003,'Daily Entry'!$B$7:$B$5003,$O33)) | I33: =IF($A33="","",SUMIFS('Daily Entry'!$D$7:$D$5003,'Daily Entry'!$B$7:$B$5003,$O33)) | J33: =IF($A33="","",$E33+$H33-$I33) | K33: =IF(OR($A33="",$D33=""),"",$J33*$D33) | L33: 6.1 | M33: =IF(OR($A33="",$D33="",$L33="",$E$4=""),"",$K33*$L33*$E$4) | O33: =IF($A33="","",$A33&" - "&$B33) | P33: =IF($A33="",0,IF(OR($F33<>0,$G33<>0),1,0)) | Q33: =IF($P33=1,SUM($P$8:$P33),"") | R33: =IF($A33="","",$A33&"#"&COUNTIF($A$8:$A33,$A33)) | S33: =IF(OR($A33="",$D33=""),0,$E33*$D33) | T33: =IF(OR($A33="",$D33=""),0,$F33*$D33) | U33: =IF(OR($A33="",$D33=""),0,$G33*$D33) | V33: =IF(OR($A33="",$D33=""),0,$H33*$D33) | W33: =IF(OR($A33="",$D33=""),0,$I33*$D33) | X33: =IF(AND($A33<>"",$D33=""),1,0) | Y33: =IF($A33="",0,IF(COUNTIF($O$8:$O$101,$O33)>1,1,0))
A34: Primus Japan | B34: PUD KKD 300/500 | C34: Slab | D34: 2 | E34: 580 | F34: =IF($A34="","",SUMIFS('Daily Entry'!$C$7:$C$5003,'Daily Entry'!$B$7:$B$5003,$O34,'Daily Entry'!$A$7:$A$5003,$E$3)) | G34: =IF($A34="","",SUMIFS('Daily Entry'!$D$7:$D$5003,'Daily Entry'!$B$7:$B$5003,$O34,'Daily Entry'!$A$7:$A$5003,$E$3)) | H34: =IF($A34="","",SUMIFS('Daily Entry'!$C$7:$C$5003,'Daily Entry'!$B$7:$B$5003,$O34)) | I34: =IF($A34="","",SUMIFS('Daily Entry'!$D$7:$D$5003,'Daily Entry'!$B$7:$B$5003,$O34)) | J34: =IF($A34="","",$E34+$H34-$I34) | K34: =IF(OR($A34="",$D34=""),"",$J34*$D34) | L34: 6.1 | M34: =IF(OR($A34="",$D34="",$L34="",$E$4=""),"",$K34*$L34*$E$4) | O34: =IF($A34="","",$A34&" - "&$B34) | P34: =IF($A34="",0,IF(OR($F34<>0,$G34<>0),1,0)) | Q34: =IF($P34=1,SUM($P$8:$P34),"") | R34: =IF($A34="","",$A34&"#"&COUNTIF($A$8:$A34,$A34)) | S34: =IF(OR($A34="",$D34=""),0,$E34*$D34) | T34: =IF(OR($A34="",$D34=""),0,$F34*$D34) | U34: =IF(OR($A34="",$D34=""),0,$G34*$D34) | V34: =IF(OR($A34="",$D34=""),0,$H34*$D34) | W34: =IF(OR($A34="",$D34=""),0,$I34*$D34) | X34: =IF(AND($A34<>"",$D34=""),1,0) | Y34: =IF($A34="",0,IF(COUNTIF($O$8:$O$101,$O34)>1,1,0))
A35: Primus EU | B35: PUD 20/40 | C35: Slab | D35: 2 | E35: 185 | F35: =IF($A35="","",SUMIFS('Daily Entry'!$C$7:$C$5003,'Daily Entry'!$B$7:$B$5003,$O35,'Daily Entry'!$A$7:$A$5003,$E$3)) | G35: =IF($A35="","",SUMIFS('Daily Entry'!$D$7:$D$5003,'Daily Entry'!$B$7:$B$5003,$O35,'Daily Entry'!$A$7:$A$5003,$E$3)) | H35: =IF($A35="","",SUMIFS('Daily Entry'!$C$7:$C$5003,'Daily Entry'!$B$7:$B$5003,$O35)) | I35: =IF($A35="","",SUMIFS('Daily Entry'!$D$7:$D$5003,'Daily Entry'!$B$7:$B$5003,$O35)) | J35: =IF($A35="","",$E35+$H35-$I35) | K35: =IF(OR($A35="",$D35=""),"",$J35*$D35) | L35: 6.5 | M35: =IF(OR($A35="",$D35="",$L35="",$E$4=""),"",$K35*$L35*$E$4) | O35: =IF($A35="","",$A35&" - "&$B35) | P35: =IF($A35="",0,IF(OR($F35<>0,$G35<>0),1,0)) | Q35: =IF($P35=1,SUM($P$8:$P35),"") | R35: =IF($A35="","",$A35&"#"&COUNTIF($A$8:$A35,$A35)) | S35: =IF(OR($A35="",$D35=""),0,$E35*$D35) | T35: =IF(OR($A35="",$D35=""),0,$F35*$D35) | U35: =IF(OR($A35="",$D35=""),0,$G35*$D35) | V35: =IF(OR($A35="",$D35=""),0,$H35*$D35) | W35: =IF(OR($A35="",$D35=""),0,$I35*$D35) | X35: =IF(AND($A35<>"",$D35=""),1,0) | Y35: =IF($A35="",0,IF(COUNTIF($O$8:$O$101,$O35)>1,1,0))
A36: Primus EU | B36: PUD 40/60 | C36: Slab | D36: 2 | E36: 368 | F36: =IF($A36="","",SUMIFS('Daily Entry'!$C$7:$C$5003,'Daily Entry'!$B$7:$B$5003,$O36,'Daily Entry'!$A$7:$A$5003,$E$3)) | G36: =IF($A36="","",SUMIFS('Daily Entry'!$D$7:$D$5003,'Daily Entry'!$B$7:$B$5003,$O36,'Daily Entry'!$A$7:$A$5003,$E$3)) | H36: =IF($A36="","",SUMIFS('Daily Entry'!$C$7:$C$5003,'Daily Entry'!$B$7:$B$5003,$O36)) | I36: =IF($A36="","",SUMIFS('Daily Entry'!$D$7:$D$5003,'Daily Entry'!$B$7:$B$5003,$O36)) | J36: =IF($A36="","",$E36+$H36-$I36) | K36: =IF(OR($A36="",$D36=""),"",$J36*$D36) | L36: 6.5 | M36: =IF(OR($A36="",$D36="",$L36="",$E$4=""),"",$K36*$L36*$E$4) | O36: =IF($A36="","",$A36&" - "&$B36) | P36: =IF($A36="",0,IF(OR($F36<>0,$G36<>0),1,0)) | Q36: =IF($P36=1,SUM($P$8:$P36),"") | R36: =IF($A36="","",$A36&"#"&COUNTIF($A$8:$A36,$A36)) | S36: =IF(OR($A36="",$D36=""),0,$E36*$D36) | T36: =IF(OR($A36="",$D36=""),0,$F36*$D36) | U36: =IF(OR($A36="",$D36=""),0,$G36*$D36) | V36: =IF(OR($A36="",$D36=""),0,$H36*$D36) | W36: =IF(OR($A36="",$D36=""),0,$I36*$D36) | X36: =IF(AND($A36<>"",$D36=""),1,0) | Y36: =IF($A36="",0,IF(COUNTIF($O$8:$O$101,$O36)>1,1,0))
A37: Primus EU | B37: PUD 60/80 | C37: Slab | D37: 2 | E37: 380 | F37: =IF($A37="","",SUMIFS('Daily Entry'!$C$7:$C$5003,'Daily Entry'!$B$7:$B$5003,$O37,'Daily Entry'!$A$7:$A$5003,$E$3)) | G37: =IF($A37="","",SUMIFS('Daily Entry'!$D$7:$D$5003,'Daily Entry'!$B$7:$B$5003,$O37,'Daily Entry'!$A$7:$A$5003,$E$3)) | H37: =IF($A37="","",SUMIFS('Daily Entry'!$C$7:$C$5003,'Daily Entry'!$B$7:$B$5003,$O37)) | I37: =IF($A37="","",SUMIFS('Daily Entry'!$D$7:$D$5003,'Daily Entry'!$B$7:$B$5003,$O37)) | J37: =IF($A37="","",$E37+$H37-$I37) | K37: =IF(OR($A37="",$D37=""),"",$J37*$D37) | L37: 6.5 | M37: =IF(OR($A37="",$D37="",$L37="",$E$4=""),"",$K37*$L37*$E$4) | O37: =IF($A37="","",$A37&" - "&$B37) | P37: =IF($A37="",0,IF(OR($F37<>0,$G37<>0),1,0)) | Q37: =IF($P37=1,SUM($P$8:$P37),"") | R37: =IF($A37="","",$A37&"#"&COUNTIF($A$8:$A37,$A37)) | S37: =IF(OR($A37="",$D37=""),0,$E37*$D37) | T37: =IF(OR($A37="",$D37=""),0,$F37*$D37) | U37: =IF(OR($A37="",$D37=""),0,$G37*$D37) | V37: =IF(OR($A37="",$D37=""),0,$H37*$D37) | W37: =IF(OR($A37="",$D37=""),0,$I37*$D37) | X37: =IF(AND($A37<>"",$D37=""),1,0) | Y37: =IF($A37="",0,IF(COUNTIF($O$8:$O$101,$O37)>1,1,0))
A38: Primus EU | B38: PUD 80/120 | C38: Slab | D38: 2 | E38: 1151 | F38: =IF($A38="","",SUMIFS('Daily Entry'!$C$7:$C$5003,'Daily Entry'!$B$7:$B$5003,$O38,'Daily Entry'!$A$7:$A$5003,$E$3)) | G38: =IF($A38="","",SUMIFS('Daily Entry'!$D$7:$D$5003,'Daily Entry'!$B$7:$B$5003,$O38,'Daily Entry'!$A$7:$A$5003,$E$3)) | H38: =IF($A38="","",SUMIFS('Daily Entry'!$C$7:$C$5003,'Daily Entry'!$B$7:$B$5003,$O38)) | I38: =IF($A38="","",SUMIFS('Daily Entry'!$D$7:$D$5003,'Daily Entry'!$B$7:$B$5003,$O38)) | J38: =IF($A38="","",$E38+$H38-$I38) | K38: =IF(OR($A38="",$D38=""),"",$J38*$D38) | L38: 6.5 | M38: =IF(OR($A38="",$D38="",$L38="",$E$4=""),"",$K38*$L38*$E$4) | O38: =IF($A38="","",$A38&" - "&$B38) | P38: =IF($A38="",0,IF(OR($F38<>0,$G38<>0),1,0)) | Q38: =IF($P38=1,SUM($P$8:$P38),"") | R38: =IF($A38="","",$A38&"#"&COUNTIF($A$8:$A38,$A38)) | S38: =IF(OR($A38="",$D38=""),0,$E38*$D38) | T38: =IF(OR($A38="",$D38=""),0,$F38*$D38) | U38: =IF(OR($A38="",$D38=""),0,$G38*$D38) | V38: =IF(OR($A38="",$D38=""),0,$H38*$D38) | W38: =IF(OR($A38="",$D38=""),0,$I38*$D38) | X38: =IF(AND($A38<>"",$D38=""),1,0) | Y38: =IF($A38="",0,IF(COUNTIF($O$8:$O$101,$O38)>1,1,0))
... A59: Shrimp Whole | B59: HOSO PVN 4-7 | C59: Slab | D59: 3 | E59: 0 | F59: =IF($A59="","",SUMIFS('Daily Entry'!$C$7:$C$5003,'Daily Entry'!$B$7:$B$5003,$O59,'Daily Entry'!$A$7:$A$5003,$E$3)) | G59: =IF($A59="","",SUMIFS('Daily Entry'!$D$7:$D$5003,'Daily Entry'!$B$7:$B$5003,$O59,'Daily Entry'!$A$7:$A$5003,$E$3)) | H59: =IF($A59="","",SUMIFS('Daily Entry'!$C$7:$C$5003,'Daily Entry'!$B$7:$B$5003,$O59)) | I59: =IF($A59="","",SUMIFS('Daily Entry'!$D$7:$D$5003,'Daily Entry'!$B$7:$B$5003,$O59)) | J59: =IF($A59="","",$E59+$H59-$I59) | K59: =IF(OR($A59="",$D59=""),"",$J59*$D59) | L59: 4 | M59: =IF(OR($A59="",$D59="",$L59="",$E$4=""),"",$K59*$L59*$E$4) | O59: =IF($A59="","",$A59&" - "&$B59) | P59: =IF($A59="",0,IF(OR($F59<>0,$G59<>0),1,0)) | Q59: =IF($P59=1,SUM($P$8:$P59),"") | R59: =IF($A59="","",$A59&"#"&COUNTIF($A$8:$A59,$A59)) | S59: =IF(OR($A59="",$D59=""),0,$E59*$D59) | T59: =IF(OR($A59="",$D59=""),0,$F59*$D59) | U59: =IF(OR($A59="",$D59=""),0,$G59*$D59) | V59: =IF(OR($A59="",$D59=""),0,$H59*$D59) | W59: =IF(OR($A59="",$D59=""),0,$I59*$D59) | X59: =IF(AND($A59<>"",$D59=""),1,0) | Y59: =IF($A59="",0,IF(COUNTIF($O$8:$O$101,$O59)>1,1,0))
A60: Tuna | B60: SKIPJACK 1/2 | C60: Kg | D60: 1 | E60: 0 | F60: =IF($A60="","",SUMIFS('Daily Entry'!$C$7:$C$5003,'Daily Entry'!$B$7:$B$5003,$O60,'Daily Entry'!$A$7:$A$5003,$E$3)) | G60: =IF($A60="","",SUMIFS('Daily Entry'!$D$7:$D$5003,'Daily Entry'!$B$7:$B$5003,$O60,'Daily Entry'!$A$7:$A$5003,$E$3)) | H60: =IF($A60="","",SUMIFS('Daily Entry'!$C$7:$C$5003,'Daily Entry'!$B$7:$B$5003,$O60)) | I60: =IF($A60="","",SUMIFS('Daily Entry'!$D$7:$D$5003,'Daily Entry'!$B$7:$B$5003,$O60)) | J60: =IF($A60="","",$E60+$H60-$I60) | K60: =IF(OR($A60="",$D60=""),"",$J60*$D60) | M60: =IF(OR($A60="",$D60="",$L60="",$E$4=""),"",$K60*$L60*$E$4) | O60: =IF($A60="","",$A60&" - "&$B60) | P60: =IF($A60="",0,IF(OR($F60<>0,$G60<>0),1,0)) | Q60: =IF($P60=1,SUM($P$8:$P60),"") | R60: =IF($A60="","",$A60&"#"&COUNTIF($A$8:$A60,$A60)) | S60: =IF(OR($A60="",$D60=""),0,$E60*$D60) | T60: =IF(OR($A60="",$D60=""),0,$F60*$D60) | U60: =IF(OR($A60="",$D60=""),0,$G60*$D60) | V60: =IF(OR($A60="",$D60=""),0,$H60*$D60) | W60: =IF(OR($A60="",$D60=""),0,$I60*$D60) | X60: =IF(AND($A60<>"",$D60=""),1,0) | Y60: =IF($A60="",0,IF(COUNTIF($O$8:$O$101,$O60)>1,1,0))
A61: Tuna | B61: SKIPJACK 2/4 | C61: Kg | D61: 1 | E61: 14946.5 | F61: =IF($A61="","",SUMIFS('Daily Entry'!$C$7:$C$5003,'Daily Entry'!$B$7:$B$5003,$O61,'Daily Entry'!$A$7:$A$5003,$E$3)) | G61: =IF($A61="","",SUMIFS('Daily Entry'!$D$7:$D$5003,'Daily Entry'!$B$7:$B$5003,$O61,'Daily Entry'!$A$7:$A$5003,$E$3)) | H61: =IF($A61="","",SUMIFS('Daily Entry'!$C$7:$C$5003,'Daily Entry'!$B$7:$B$5003,$O61)) | I61: =IF($A61="","",SUMIFS('Daily Entry'!$D$7:$D$5003,'Daily Entry'!$B$7:$B$5003,$O61)) | J61: =IF($A61="","",$E61+$H61-$I61) | K61: =IF(OR($A61="",$D61=""),"",$J61*$D61) | L61: 1.58 | M61: =IF(OR($A61="",$D61="",$L61="",$E$4=""),"",$K61*$L61*$E$4) | O61: =IF($A61="","",$A61&" - "&$B61) | P61: =IF($A61="",0,IF(OR($F61<>0,$G61<>0),1,0)) | Q61: =IF($P61=1,SUM($P$8:$P61),"") | R61: =IF($A61="","",$A61&"#"&COUNTIF($A$8:$A61,$A61)) | S61: =IF(OR($A61="",$D61=""),0,$E61*$D61) | T61: =IF(OR($A61="",$D61=""),0,$F61*$D61) | U61: =IF(OR($A61="",$D61=""),0,$G61*$D61) | V61: =IF(OR($A61="",$D61=""),0,$H61*$D61) | W61: =IF(OR($A61="",$D61=""),0,$I61*$D61) | X61: =IF(AND($A61<>"",$D61=""),1,0) | Y61: =IF($A61="",0,IF(COUNTIF($O$8:$O$101,$O61)>1,1,0))
A62: Tuna | B62: SKIPJACK 4/10 | C62: Kg | D62: 1 | E62: 913.5 | F62: =IF($A62="","",SUMIFS('Daily Entry'!$C$7:$C$5003,'Daily Entry'!$B$7:$B$5003,$O62,'Daily Entry'!$A$7:$A$5003,$E$3)) | G62: =IF($A62="","",SUMIFS('Daily Entry'!$D$7:$D$5003,'Daily Entry'!$B$7:$B$5003,$O62,'Daily Entry'!$A$7:$A$5003,$E$3)) | H62: =IF($A62="","",SUMIFS('Daily Entry'!$C$7:$C$5003,'Daily Entry'!$B$7:$B$5003,$O62)) | I62: =IF($A62="","",SUMIFS('Daily Entry'!$D$7:$D$5003,'Daily Entry'!$B$7:$B$5003,$O62)) | J62: =IF($A62="","",$E62+$H62-$I62) | K62: =IF(OR($A62="",$D62=""),"",$J62*$D62) | L62: 1.58 | M62: =IF(OR($A62="",$D62="",$L62="",$E$4=""),"",$K62*$L62*$E$4) | O62: =IF($A62="","",$A62&" - "&$B62) | P62: =IF($A62="",0,IF(OR($F62<>0,$G62<>0),1,0)) | Q62: =IF($P62=1,SUM($P$8:$P62),"") | R62: =IF($A62="","",$A62&"#"&COUNTIF($A$8:$A62,$A62)) | S62: =IF(OR($A62="",$D62=""),0,$E62*$D62) | T62: =IF(OR($A62="",$D62=""),0,$F62*$D62) | U62: =IF(OR($A62="",$D62=""),0,$G62*$D62) | V62: =IF(OR($A62="",$D62=""),0,$H62*$D62) | W62: =IF(OR($A62="",$D62=""),0,$I62*$D62) | X62: =IF(AND($A62<>"",$D62=""),1,0) | Y62: =IF($A62="",0,IF(COUNTIF($O$8:$O$101,$O62)>1,1,0))
A63: Tuna | B63: YELLOW FIN 1/2 | C63: Kg | D63: 1 | E63: 0 | F63: =IF($A63="","",SUMIFS('Daily Entry'!$C$7:$C$5003,'Daily Entry'!$B$7:$B$5003,$O63,'Daily Entry'!$A$7:$A$5003,$E$3)) | G63: =IF($A63="","",SUMIFS('Daily Entry'!$D$7:$D$5003,'Daily Entry'!$B$7:$B$5003,$O63,'Daily Entry'!$A$7:$A$5003,$E$3)) | H63: =IF($A63="","",SUMIFS('Daily Entry'!$C$7:$C$5003,'Daily Entry'!$B$7:$B$5003,$O63)) | I63: =IF($A63="","",SUMIFS('Daily Entry'!$D$7:$D$5003,'Daily Entry'!$B$7:$B$5003,$O63)) | J63: =IF($A63="","",$E63+$H63-$I63) | K63: =IF(OR($A63="",$D63=""),"",$J63*$D63) | M63: =IF(OR($A63="",$D63="",$L63="",$E$4=""),"",$K63*$L63*$E$4) | O63: =IF($A63="","",$A63&" - "&$B63) | P63: =IF($A63="",0,IF(OR($F63<>0,$G63<>0),1,0)) | Q63: =IF($P63=1,SUM($P$8:$P63),"") | R63: =IF($A63="","",$A63&"#"&COUNTIF($A$8:$A63,$A63)) | S63: =IF(OR($A63="",$D63=""),0,$E63*$D63) | T63: =IF(OR($A63="",$D63=""),0,$F63*$D63) | U63: =IF(OR($A63="",$D63=""),0,$G63*$D63) | V63: =IF(OR($A63="",$D63=""),0,$H63*$D63) | W63: =IF(OR($A63="",$D63=""),0,$I63*$D63) | X63: =IF(AND($A63<>"",$D63=""),1,0) | Y63: =IF($A63="",0,IF(COUNTIF($O$8:$O$101,$O63)>1,1,0))
A64: Tuna | B64: YELLOW FIN 2/4 | C64: Kg | D64: 1 | E64: 32 | F64: =IF($A64="","",SUMIFS('Daily Entry'!$C$7:$C$5003,'Daily Entry'!$B$7:$B$5003,$O64,'Daily Entry'!$A$7:$A$5003,$E$3)) | G64: =IF($A64="","",SUMIFS('Daily Entry'!$D$7:$D$5003,'Daily Entry'!$B$7:$B$5003,$O64,'Daily Entry'!$A$7:$A$5003,$E$3)) | H64: =IF($A64="","",SUMIFS('Daily Entry'!$C$7:$C$5003,'Daily Entry'!$B$7:$B$5003,$O64)) | I64: =IF($A64="","",SUMIFS('Daily Entry'!$D$7:$D$5003,'Daily Entry'!$B$7:$B$5003,$O64)) | J64: =IF($A64="","",$E64+$H64-$I64) | K64: =IF(OR($A64="",$D64=""),"",$J64*$D64) | L64: 1.58 | M64: =IF(OR($A64="",$D64="",$L64="",$E$4=""),"",$K64*$L64*$E$4) | O64: =IF($A64="","",$A64&" - "&$B64) | P64: =IF($A64="",0,IF(OR($F64<>0,$G64<>0),1,0)) | Q64: =IF($P64=1,SUM($P$8:$P64),"") | R64: =IF($A64="","",$A64&"#"&COUNTIF($A$8:$A64,$A64)) | S64: =IF(OR($A64="",$D64=""),0,$E64*$D64) | T64: =IF(OR($A64="",$D64=""),0,$F64*$D64) | U64: =IF(OR($A64="",$D64=""),0,$G64*$D64) | V64: =IF(OR($A64="",$D64=""),0,$H64*$D64) | W64: =IF(OR($A64="",$D64=""),0,$I64*$D64) | X64: =IF(AND($A64<>"",$D64=""),1,0) | Y64: =IF($A64="",0,IF(COUNTIF($O$8:$O$101,$O64)>1,1,0))
A65: Tuna | B65: YELLOW FIN 4/10 | C65: Kg | D65: 1 | E65: 1138 | F65: =IF($A65="","",SUMIFS('Daily Entry'!$C$7:$C$5003,'Daily Entry'!$B$7:$B$5003,$O65,'Daily Entry'!$A$7:$A$5003,$E$3)) | G65: =IF($A65="","",SUMIFS('Daily Entry'!$D$7:$D$5003,'Daily Entry'!$B$7:$B$5003,$O65,'Daily Entry'!$A$7:$A$5003,$E$3)) | H65: =IF($A65="","",SUMIFS('Daily Entry'!$C$7:$C$5003,'Daily Entry'!$B$7:$B$5003,$O65)) | I65: =IF($A65="","",SUMIFS('Daily Entry'!$D$7:$D$5003,'Daily Entry'!$B$7:$B$5003,$O65)) | J65: =IF($A65="","",$E65+$H65-$I65) | K65: =IF(OR($A65="",$D65=""),"",$J65*$D65) | L65: 1.7 | M65: =IF(OR($A65="",$D65="",$L65="",$E$4=""),"",$K65*$L65*$E$4) | O65: =IF($A65="","",$A65&" - "&$B65) | P65: =IF($A65="",0,IF(OR($F65<>0,$G65<>0),1,0)) | Q65: =IF($P65=1,SUM($P$8:$P65),"") | R65: =IF($A65="","",$A65&"#"&COUNTIF($A$8:$A65,$A65)) | S65: =IF(OR($A65="",$D65=""),0,$E65*$D65) | T65: =IF(OR($A65="",$D65=""),0,$F65*$D65) | U65: =IF(OR($A65="",$D65=""),0,$G65*$D65) | V65: =IF(OR($A65="",$D65=""),0,$H65*$D65) | W65: =IF(OR($A65="",$D65=""),0,$I65*$D65) | X65: =IF(AND($A65<>"",$D65=""),1,0) | Y65: =IF($A65="",0,IF(COUNTIF($O$8:$O$101,$O65)>1,1,0))
A66: Mackerel | B66: WHOLE 2/4 | C66: Kg | D66: 1 | E66: 0 | F66: =IF($A66="","",SUMIFS('Daily Entry'!$C$7:$C$5003,'Daily Entry'!$B$7:$B$5003,$O66,'Daily Entry'!$A$7:$A$5003,$E$3)) | G66: =IF($A66="","",SUMIFS('Daily Entry'!$D$7:$D$5003,'Daily Entry'!$B$7:$B$5003,$O66,'Daily Entry'!$A$7:$A$5003,$E$3)) | H66: =IF($A66="","",SUMIFS('Daily Entry'!$C$7:$C$5003,'Daily Entry'!$B$7:$B$5003,$O66)) | I66: =IF($A66="","",SUMIFS('Daily Entry'!$D$7:$D$5003,'Daily Entry'!$B$7:$B$5003,$O66)) | J66: =IF($A66="","",$E66+$H66-$I66) | K66: =IF(OR($A66="",$D66=""),"",$J66*$D66) | M66: =IF(OR($A66="",$D66="",$L66="",$E$4=""),"",$K66*$L66*$E$4) | O66: =IF($A66="","",$A66&" - "&$B66) | P66: =IF($A66="",0,IF(OR($F66<>0,$G66<>0),1,0)) | Q66: =IF($P66=1,SUM($P$8:$P66),"") | R66: =IF($A66="","",$A66&"#"&COUNTIF($A$8:$A66,$A66)) | S66: =IF(OR($A66="",$D66=""),0,$E66*$D66) | T66: =IF(OR($A66="",$D66=""),0,$F66*$D66) | U66: =IF(OR($A66="",$D66=""),0,$G66*$D66) | V66: =IF(OR($A66="",$D66=""),0,$H66*$D66) | W66: =IF(OR($A66="",$D66=""),0,$I66*$D66) | X66: =IF(AND($A66<>"",$D66=""),1,0) | Y66: =IF($A66="",0,IF(COUNTIF($O$8:$O$101,$O66)>1,1,0))
A67: Mackerel | B67: WHOLE 4/6 | C67: Kg | D67: 1 | E67: 0 | F67: =IF($A67="","",SUMIFS('Daily Entry'!$C$7:$C$5003,'Daily Entry'!$B$7:$B$5003,$O67,'Daily Entry'!$A$7:$A$5003,$E$3)) | G67: =IF($A67="","",SUMIFS('Daily Entry'!$D$7:$D$5003,'Daily Entry'!$B$7:$B$5003,$O67,'Daily Entry'!$A$7:$A$5003,$E$3)) | H67: =IF($A67="","",SUMIFS('Daily Entry'!$C$7:$C$5003,'Daily Entry'!$B$7:$B$5003,$O67)) | I67: =IF($A67="","",SUMIFS('Daily Entry'!$D$7:$D$5003,'Daily Entry'!$B$7:$B$5003,$O67)) | J67: =IF($A67="","",$E67+$H67-$I67) | K67: =IF(OR($A67="",$D67=""),"",$J67*$D67) | M67: =IF(OR($A67="",$D67="",$L67="",$E$4=""),"",$K67*$L67*$E$4) | O67: =IF($A67="","",$A67&" - "&$B67) | P67: =IF($A67="",0,IF(OR($F67<>0,$G67<>0),1,0)) | Q67: =IF($P67=1,SUM($P$8:$P67),"") | R67: =IF($A67="","",$A67&"#"&COUNTIF($A$8:$A67,$A67)) | S67: =IF(OR($A67="",$D67=""),0,$E67*$D67) | T67: =IF(OR($A67="",$D67=""),0,$F67*$D67) | U67: =IF(OR($A67="",$D67=""),0,$G67*$D67) | V67: =IF(OR($A67="",$D67=""),0,$H67*$D67) | W67: =IF(OR($A67="",$D67=""),0,$I67*$D67) | X67: =IF(AND($A67<>"",$D67=""),1,0) | Y67: =IF($A67="",0,IF(COUNTIF($O$8:$O$101,$O67)>1,1,0))
A68: Mackerel | B68: WHOLE 6/8 | C68: Kg | D68: 1 | E68: 0 | F68: =IF($A68="","",SUMIFS('Daily Entry'!$C$7:$C$5003,'Daily Entry'!$B$7:$B$5003,$O68,'Daily Entry'!$A$7:$A$5003,$E$3)) | G68: =IF($A68="","",SUMIFS('Daily Entry'!$D$7:$D$5003,'Daily Entry'!$B$7:$B$5003,$O68,'Daily Entry'!$A$7:$A$5003,$E$3)) | H68: =IF($A68="","",SUMIFS('Daily Entry'!$C$7:$C$5003,'Daily Entry'!$B$7:$B$5003,$O68)) | I68: =IF($A68="","",SUMIFS('Daily Entry'!$D$7:$D$5003,'Daily Entry'!$B$7:$B$5003,$O68)) | J68: =IF($A68="","",$E68+$H68-$I68) | K68: =IF(OR($A68="",$D68=""),"",$J68*$D68) | L68: 2.35 | M68: =IF(OR($A68="",$D68="",$L68="",$E$4=""),"",$K68*$L68*$E$4) | O68: =IF($A68="","",$A68&" - "&$B68) | P68: =IF($A68="",0,IF(OR($F68<>0,$G68<>0),1,0)) | Q68: =IF($P68=1,SUM($P$8:$P68),"") | R68: =IF($A68="","",$A68&"#"&COUNTIF($A$8:$A68,$A68)) | S68: =IF(OR($A68="",$D68=""),0,$E68*$D68) | T68: =IF(OR($A68="",$D68=""),0,$F68*$D68) | U68: =IF(OR($A68="",$D68=""),0,$G68*$D68) | V68: =IF(OR($A68="",$D68=""),0,$H68*$D68) | W68: =IF(OR($A68="",$D68=""),0,$I68*$D68) | X68: =IF(AND($A68<>"",$D68=""),1,0) | Y68: =IF($A68="",0,IF(COUNTIF($O$8:$O$101,$O68)>1,1,0))
A69: Mackerel | B69: WHOLE 8/10 | C69: Kg | D69: 1 | E69: 0 | F69: =IF($A69="","",SUMIFS('Daily Entry'!$C$7:$C$5003,'Daily Entry'!$B$7:$B$5003,$O69,'Daily Entry'!$A$7:$A$5003,$E$3)) | G69: =IF($A69="","",SUMIFS('Daily Entry'!$D$7:$D$5003,'Daily Entry'!$B$7:$B$5003,$O69,'Daily Entry'!$A$7:$A$5003,$E$3)) | H69: =IF($A69="","",SUMIFS('Daily Entry'!$C$7:$C$5003,'Daily Entry'!$B$7:$B$5003,$O69)) | I69: =IF($A69="","",SUMIFS('Daily Entry'!$D$7:$D$5003,'Daily Entry'!$B$7:$B$5003,$O69)) | J69: =IF($A69="","",$E69+$H69-$I69) | K69: =IF(OR($A69="",$D69=""),"",$J69*$D69) | L69: 2.25 | M69: =IF(OR($A69="",$D69="",$L69="",$E$4=""),"",$K69*$L69*$E$4) | O69: =IF($A69="","",$A69&" - "&$B69) | P69: =IF($A69="",0,IF(OR($F69<>0,$G69<>0),1,0)) | Q69: =IF($P69=1,SUM($P$8:$P69),"") | R69: =IF($A69="","",$A69&"#"&COUNTIF($A$8:$A69,$A69)) | S69: =IF(OR($A69="",$D69=""),0,$E69*$D69) | T69: =IF(OR($A69="",$D69=""),0,$F69*$D69) | U69: =IF(OR($A69="",$D69=""),0,$G69*$D69) | V69: =IF(OR($A69="",$D69=""),0,$H69*$D69) | W69: =IF(OR($A69="",$D69=""),0,$I69*$D69) | X69: =IF(AND($A69<>"",$D69=""),1,0) | Y69: =IF($A69="",0,IF(COUNTIF($O$8:$O$101,$O69)>1,1,0))
A70: Mackerel | B70: WHOLE 8/12 | C70: Kg | D70: 1 | E70: 0 | F70: =IF($A70="","",SUMIFS('Daily Entry'!$C$7:$C$5003,'Daily Entry'!$B$7:$B$5003,$O70,'Daily Entry'!$A$7:$A$5003,$E$3)) | G70: =IF($A70="","",SUMIFS('Daily Entry'!$D$7:$D$5003,'Daily Entry'!$B$7:$B$5003,$O70,'Daily Entry'!$A$7:$A$5003,$E$3)) | H70: =IF($A70="","",SUMIFS('Daily Entry'!$C$7:$C$5003,'Daily Entry'!$B$7:$B$5003,$O70)) | I70: =IF($A70="","",SUMIFS('Daily Entry'!$D$7:$D$5003,'Daily Entry'!$B$7:$B$5003,$O70)) | J70: =IF($A70="","",$E70+$H70-$I70) | K70: =IF(OR($A70="",$D70=""),"",$J70*$D70) | L70: 2.05 | M70: =IF(OR($A70="",$D70="",$L70="",$E$4=""),"",$K70*$L70*$E$4) | O70: =IF($A70="","",$A70&" - "&$B70) | P70: =IF($A70="",0,IF(OR($F70<>0,$G70<>0),1,0)) | Q70: =IF($P70=1,SUM($P$8:$P70),"") | R70: =IF($A70="","",$A70&"#"&COUNTIF($A$8:$A70,$A70)) | S70: =IF(OR($A70="",$D70=""),0,$E70*$D70) | T70: =IF(OR($A70="",$D70=""),0,$F70*$D70) | U70: =IF(OR($A70="",$D70=""),0,$G70*$D70) | V70: =IF(OR($A70="",$D70=""),0,$H70*$D70) | W70: =IF(OR($A70="",$D70=""),0,$I70*$D70) | X70: =IF(AND($A70<>"",$D70=""),1,0) | Y70: =IF($A70="",0,IF(COUNTIF($O$8:$O$101,$O70)>1,1,0))
A71: Mackerel | B71: WHOLE 10/12 | C71: Kg | D71: 1 | E71: 0 | F71: =IF($A71="","",SUMIFS('Daily Entry'!$C$7:$C$5003,'Daily Entry'!$B$7:$B$5003,$O71,'Daily Entry'!$A$7:$A$5003,$E$3)) | G71: =IF($A71="","",SUMIFS('Daily Entry'!$D$7:$D$5003,'Daily Entry'!$B$7:$B$5003,$O71,'Daily Entry'!$A$7:$A$5003,$E$3)) | H71: =IF($A71="","",SUMIFS('Daily Entry'!$C$7:$C$5003,'Daily Entry'!$B$7:$B$5003,$O71)) | I71: =IF($A71="","",SUMIFS('Daily Entry'!$D$7:$D$5003,'Daily Entry'!$B$7:$B$5003,$O71)) | J71: =IF($A71="","",$E71+$H71-$I71) | K71: =IF(OR($A71="",$D71=""),"",$J71*$D71) | L71: 1.95 | M71: =IF(OR($A71="",$D71="",$L71="",$E$4=""),"",$K71*$L71*$E$4) | O71: =IF($A71="","",$A71&" - "&$B71) | P71: =IF($A71="",0,IF(OR($F71<>0,$G71<>0),1,0)) | Q71: =IF($P71=1,SUM($P$8:$P71),"") | R71: =IF($A71="","",$A71&"#"&COUNTIF($A$8:$A71,$A71)) | S71: =IF(OR($A71="",$D71=""),0,$E71*$D71) | T71: =IF(OR($A71="",$D71=""),0,$F71*$D71) | U71: =IF(OR($A71="",$D71=""),0,$G71*$D71) | V71: =IF(OR($A71="",$D71=""),0,$H71*$D71) | W71: =IF(OR($A71="",$D71=""),0,$I71*$D71) | X71: =IF(AND($A71<>"",$D71=""),1,0) | Y71: =IF($A71="",0,IF(COUNTIF($O$8:$O$101,$O71)>1,1,0))
A72: Mackerel | B72: WHOLE 12/15 | C72: Kg | D72: 1 | E72: 0 | F72: =IF($A72="","",SUMIFS('Daily Entry'!$C$7:$C$5003,'Daily Entry'!$B$7:$B$5003,$O72,'Daily Entry'!$A$7:$A$5003,$E$3)) | G72: =IF($A72="","",SUMIFS('Daily Entry'!$D$7:$D$5003,'Daily Entry'!$B$7:$B$5003,$O72,'Daily Entry'!$A$7:$A$5003,$E$3)) | H72: =IF($A72="","",SUMIFS('Daily Entry'!$C$7:$C$5003,'Daily Entry'!$B$7:$B$5003,$O72)) | I72: =IF($A72="","",SUMIFS('Daily Entry'!$D$7:$D$5003,'Daily Entry'!$B$7:$B$5003,$O72)) | J72: =IF($A72="","",$E72+$H72-$I72) | K72: =IF(OR($A72="",$D72=""),"",$J72*$D72) | L72: 1.7 | M72: =IF(OR($A72="",$D72="",$L72="",$E$4=""),"",$K72*$L72*$E$4) | O72: =IF($A72="","",$A72&" - "&$B72) | P72: =IF($A72="",0,IF(OR($F72<>0,$G72<>0),1,0)) | Q72: =IF($P72=1,SUM($P$8:$P72),"") | R72: =IF($A72="","",$A72&"#"&COUNTIF($A$8:$A72,$A72)) | S72: =IF(OR($A72="",$D72=""),0,$E72*$D72) | T72: =IF(OR($A72="",$D72=""),0,$F72*$D72) | U72: =IF(OR($A72="",$D72=""),0,$G72*$D72) | V72: =IF(OR($A72="",$D72=""),0,$H72*$D72) | W72: =IF(OR($A72="",$D72=""),0,$I72*$D72) | X72: =IF(AND($A72<>"",$D72=""),1,0) | Y72: =IF($A72="",0,IF(COUNTIF($O$8:$O$101,$O72)>1,1,0))
A73: Mackerel | B73: WHOLE 15/20 | C73: Kg | D73: 1 | E73: 0 | F73: =IF($A73="","",SUMIFS('Daily Entry'!$C$7:$C$5003,'Daily Entry'!$B$7:$B$5003,$O73,'Daily Entry'!$A$7:$A$5003,$E$3)) | G73: =IF($A73="","",SUMIFS('Daily Entry'!$D$7:$D$5003,'Daily Entry'!$B$7:$B$5003,$O73,'Daily Entry'!$A$7:$A$5003,$E$3)) | H73: =IF($A73="","",SUMIFS('Daily Entry'!$C$7:$C$5003,'Daily Entry'!$B$7:$B$5003,$O73)) | I73: =IF($A73="","",SUMIFS('Daily Entry'!$D$7:$D$5003,'Daily Entry'!$B$7:$B$5003,$O73)) | J73: =IF($A73="","",$E73+$H73-$I73) | K73: =IF(OR($A73="",$D73=""),"",$J73*$D73) | M73: =IF(OR($A73="",$D73="",$L73="",$E$4=""),"",$K73*$L73*$E$4) | O73: =IF($A73="","",$A73&" - "&$B73) | P73: =IF($A73="",0,IF(OR($F73<>0,$G73<>0),1,0)) | Q73: =IF($P73=1,SUM($P$8:$P73),"") | R73: =IF($A73="","",$A73&"#"&COUNTIF($A$8:$A73,$A73)) | S73: =IF(OR($A73="",$D73=""),0,$E73*$D73) | T73: =IF(OR($A73="",$D73=""),0,$F73*$D73) | U73: =IF(OR($A73="",$D73=""),0,$G73*$D73) | V73: =IF(OR($A73="",$D73=""),0,$H73*$D73) | W73: =IF(OR($A73="",$D73=""),0,$I73*$D73) | X73: =IF(AND($A73<>"",$D73=""),1,0) | Y73: =IF($A73="",0,IF(COUNTIF($O$8:$O$101,$O73)>1,1,0))
A74: Cuttlefish | B74: CFWC U/1 10% | C74: Slab | D74: 4 | E74: 0 | F74: =IF($A74="","",SUMIFS('Daily Entry'!$C$7:$C$5003,'Daily Entry'!$B$7:$B$5003,$O74,'Daily Entry'!$A$7:$A$5003,$E$3)) | G74: =IF($A74="","",SUMIFS('Daily Entry'!$D$7:$D$5003,'Daily Entry'!$B$7:$B$5003,$O74,'Daily Entry'!$A$7:$A$5003,$E$3)) | H74: =IF($A74="","",SUMIFS('Daily Entry'!$C$7:$C$5003,'Daily Entry'!$B$7:$B$5003,$O74)) | I74: =IF($A74="","",SUMIFS('Daily Entry'!$D$7:$D$5003,'Daily Entry'!$B$7:$B$5003,$O74)) | J74: =IF($A74="","",$E74+$H74-$I74) | K74: =IF(OR($A74="",$D74=""),"",$J74*$D74) | M74: =IF(OR($A74="",$D74="",$L74="",$E$4=""),"",$K74*$L74*$E$4) | O74: =IF($A74="","",$A74&" - "&$B74) | P74: =IF($A74="",0,IF(OR($F74<>0,$G74<>0),1,0)) | Q74: =IF($P74=1,SUM($P$8:$P74),"") | R74: =IF($A74="","",$A74&"#"&COUNTIF($A$8:$A74,$A74)) | S74: =IF(OR($A74="",$D74=""),0,$E74*$D74) | T74: =IF(OR($A74="",$D74=""),0,$F74*$D74) | U74: =IF(OR($A74="",$D74=""),0,$G74*$D74) | V74: =IF(OR($A74="",$D74=""),0,$H74*$D74) | W74: =IF(OR($A74="",$D74=""),0,$I74*$D74) | X74: =IF(AND($A74<>"",$D74=""),1,0) | Y74: =IF($A74="",0,IF(COUNTIF($O$8:$O$101,$O74)>1,1,0))
A75: Cuttlefish | B75: CFWC 1/2 10% | C75: Slab | D75: 4 | E75: 0 | F75: =IF($A75="","",SUMIFS('Daily Entry'!$C$7:$C$5003,'Daily Entry'!$B$7:$B$5003,$O75,'Daily Entry'!$A$7:$A$5003,$E$3)) | G75: =IF($A75="","",SUMIFS('Daily Entry'!$D$7:$D$5003,'Daily Entry'!$B$7:$B$5003,$O75,'Daily Entry'!$A$7:$A$5003,$E$3)) | H75: =IF($A75="","",SUMIFS('Daily Entry'!$C$7:$C$5003,'Daily Entry'!$B$7:$B$5003,$O75)) | I75: =IF($A75="","",SUMIFS('Daily Entry'!$D$7:$D$5003,'Daily Entry'!$B$7:$B$5003,$O75)) | J75: =IF($A75="","",$E75+$H75-$I75) | K75: =IF(OR($A75="",$D75=""),"",$J75*$D75) | M75: =IF(OR($A75="",$D75="",$L75="",$E$4=""),"",$K75*$L75*$E$4) | O75: =IF($A75="","",$A75&" - "&$B75) | P75: =IF($A75="",0,IF(OR($F75<>0,$G75<>0),1,0)) | Q75: =IF($P75=1,SUM($P$8:$P75),"") | R75: =IF($A75="","",$A75&"#"&COUNTIF($A$8:$A75,$A75)) | S75: =IF(OR($A75="",$D75=""),0,$E75*$D75) | T75: =IF(OR($A75="",$D75=""),0,$F75*$D75) | U75: =IF(OR($A75="",$D75=""),0,$G75*$D75) | V75: =IF(OR($A75="",$D75=""),0,$H75*$D75) | W75: =IF(OR($A75="",$D75=""),0,$I75*$D75) | X75: =IF(AND($A75<>"",$D75=""),1,0) | Y75: =IF($A75="",0,IF(COUNTIF($O$8:$O$101,$O75)>1,1,0))
A76: Cuttlefish | B76: CFWC 2/4 10% | C76: Slab | D76: 4 | E76: 0 | F76: =IF($A76="","",SUMIFS('Daily Entry'!$C$7:$C$5003,'Daily Entry'!$B$7:$B$5003,$O76,'Daily Entry'!$A$7:$A$5003,$E$3)) | G76: =IF($A76="","",SUMIFS('Daily Entry'!$D$7:$D$5003,'Daily Entry'!$B$7:$B$5003,$O76,'Daily Entry'!$A$7:$A$5003,$E$3)) | H76: =IF($A76="","",SUMIFS('Daily Entry'!$C$7:$C$5003,'Daily Entry'!$B$7:$B$5003,$O76)) | I76: =IF($A76="","",SUMIFS('Daily Entry'!$D$7:$D$5003,'Daily Entry'!$B$7:$B$5003,$O76)) | J76: =IF($A76="","",$E76+$H76-$I76) | K76: =IF(OR($A76="",$D76=""),"",$J76*$D76) | M76: =IF(OR($A76="",$D76="",$L76="",$E$4=""),"",$K76*$L76*$E$4) | O76: =IF($A76="","",$A76&" - "&$B76) | P76: =IF($A76="",0,IF(OR($F76<>0,$G76<>0),1,0)) | Q76: =IF($P76=1,SUM($P$8:$P76),"") | R76: =IF($A76="","",$A76&"#"&COUNTIF($A$8:$A76,$A76)) | S76: =IF(OR($A76="",$D76=""),0,$E76*$D76) | T76: =IF(OR($A76="",$D76=""),0,$F76*$D76) | U76: =IF(OR($A76="",$D76=""),0,$G76*$D76) | V76: =IF(OR($A76="",$D76=""),0,$H76*$D76) | W76: =IF(OR($A76="",$D76=""),0,$I76*$D76) | X76: =IF(AND($A76<>"",$D76=""),1,0) | Y76: =IF($A76="",0,IF(COUNTIF($O$8:$O$101,$O76)>1,1,0))
A77: Cuttlefish | B77: CFWC 5/7 10% | C77: Slab | D77: 4 | E77: 0 | F77: =IF($A77="","",SUMIFS('Daily Entry'!$C$7:$C$5003,'Daily Entry'!$B$7:$B$5003,$O77,'Daily Entry'!$A$7:$A$5003,$E$3)) | G77: =IF($A77="","",SUMIFS('Daily Entry'!$D$7:$D$5003,'Daily Entry'!$B$7:$B$5003,$O77,'Daily Entry'!$A$7:$A$5003,$E$3)) | H77: =IF($A77="","",SUMIFS('Daily Entry'!$C$7:$C$5003,'Daily Entry'!$B$7:$B$5003,$O77)) | I77: =IF($A77="","",SUMIFS('Daily Entry'!$D$7:$D$5003,'Daily Entry'!$B$7:$B$5003,$O77)) | J77: =IF($A77="","",$E77+$H77-$I77) | K77: =IF(OR($A77="",$D77=""),"",$J77*$D77) | M77: =IF(OR($A77="",$D77="",$L77="",$E$4=""),"",$K77*$L77*$E$4) | O77: =IF($A77="","",$A77&" - "&$B77) | P77: =IF($A77="",0,IF(OR($F77<>0,$G77<>0),1,0)) | Q77: =IF($P77=1,SUM($P$8:$P77),"") | R77: =IF($A77="","",$A77&"#"&COUNTIF($A$8:$A77,$A77)) | S77: =IF(OR($A77="",$D77=""),0,$E77*$D77) | T77: =IF(OR($A77="",$D77=""),0,$F77*$D77) | U77: =IF(OR($A77="",$D77=""),0,$G77*$D77) | V77: =IF(OR($A77="",$D77=""),0,$H77*$D77) | W77: =IF(OR($A77="",$D77=""),0,$I77*$D77) | X77: =IF(AND($A77<>"",$D77=""),1,0) | Y77: =IF($A77="",0,IF(COUNTIF($O$8:$O$101,$O77)>1,1,0))
A78: Cuttlefish | B78: CFWC 8/12 10% | C78: Slab | D78: 4 | E78: 0 | F78: =IF($A78="","",SUMIFS('Daily Entry'!$C$7:$C$5003,'Daily Entry'!$B$7:$B$5003,$O78,'Daily Entry'!$A$7:$A$5003,$E$3)) | G78: =IF($A78="","",SUMIFS('Daily Entry'!$D$7:$D$5003,'Daily Entry'!$B$7:$B$5003,$O78,'Daily Entry'!$A$7:$A$5003,$E$3)) | H78: =IF($A78="","",SUMIFS('Daily Entry'!$C$7:$C$5003,'Daily Entry'!$B$7:$B$5003,$O78)) | I78: =IF($A78="","",SUMIFS('Daily Entry'!$D$7:$D$5003,'Daily Entry'!$B$7:$B$5003,$O78)) | J78: =IF($A78="","",$E78+$H78-$I78) | K78: =IF(OR($A78="",$D78=""),"",$J78*$D78) | M78: =IF(OR($A78="",$D78="",$L78="",$E$4=""),"",$K78*$L78*$E$4) | O78: =IF($A78="","",$A78&" - "&$B78) | P78: =IF($A78="",0,IF(OR($F78<>0,$G78<>0),1,0)) | Q78: =IF($P78=1,SUM($P$8:$P78),"") | R78: =IF($A78="","",$A78&"#"&COUNTIF($A$8:$A78,$A78)) | S78: =IF(OR($A78="",$D78=""),0,$E78*$D78) | T78: =IF(OR($A78="",$D78=""),0,$F78*$D78) | U78: =IF(OR($A78="",$D78=""),0,$G78*$D78) | V78: =IF(OR($A78="",$D78=""),0,$H78*$D78) | W78: =IF(OR($A78="",$D78=""),0,$I78*$D78) | X78: =IF(AND($A78<>"",$D78=""),1,0) | Y78: =IF($A78="",0,IF(COUNTIF($O$8:$O$101,$O78)>1,1,0))
A79: Cuttlefish | B79: CFWC 13/20 10% | C79: Slab | D79: 4 | E79: 0 | F79: =IF($A79="","",SUMIFS('Daily Entry'!$C$7:$C$5003,'Daily Entry'!$B$7:$B$5003,$O79,'Daily Entry'!$A$7:$A$5003,$E$3)) | G79: =IF($A79="","",SUMIFS('Daily Entry'!$D$7:$D$5003,'Daily Entry'!$B$7:$B$5003,$O79,'Daily Entry'!$A$7:$A$5003,$E$3)) | H79: =IF($A79="","",SUMIFS('Daily Entry'!$C$7:$C$5003,'Daily Entry'!$B$7:$B$5003,$O79)) | I79: =IF($A79="","",SUMIFS('Daily Entry'!$D$7:$D$5003,'Daily Entry'!$B$7:$B$5003,$O79)) | J79: =IF($A79="","",$E79+$H79-$I79) | K79: =IF(OR($A79="",$D79=""),"",$J79*$D79) | M79: =IF(OR($A79="",$D79="",$L79="",$E$4=""),"",$K79*$L79*$E$4) | O79: =IF($A79="","",$A79&" - "&$B79) | P79: =IF($A79="",0,IF(OR($F79<>0,$G79<>0),1,0)) | Q79: =IF($P79=1,SUM($P$8:$P79),"") | R79: =IF($A79="","",$A79&"#"&COUNTIF($A$8:$A79,$A79)) | S79: =IF(OR($A79="",$D79=""),0,$E79*$D79) | T79: =IF(OR($A79="",$D79=""),0,$F79*$D79) | U79: =IF(OR($A79="",$D79=""),0,$G79*$D79) | V79: =IF(OR($A79="",$D79=""),0,$H79*$D79) | W79: =IF(OR($A79="",$D79=""),0,$I79*$D79) | X79: =IF(AND($A79<>"",$D79=""),1,0) | Y79: =IF($A79="",0,IF(COUNTIF($O$8:$O$101,$O79)>1,1,0))
A80: White Squid | B80: SQW U/3 10% | C80: Slab | D80: 2 | E80: 0 | F80: =IF($A80="","",SUMIFS('Daily Entry'!$C$7:$C$5003,'Daily Entry'!$B$7:$B$5003,$O80,'Daily Entry'!$A$7:$A$5003,$E$3)) | G80: =IF($A80="","",SUMIFS('Daily Entry'!$D$7:$D$5003,'Daily Entry'!$B$7:$B$5003,$O80,'Daily Entry'!$A$7:$A$5003,$E$3)) | H80: =IF($A80="","",SUMIFS('Daily Entry'!$C$7:$C$5003,'Daily Entry'!$B$7:$B$5003,$O80)) | I80: =IF($A80="","",SUMIFS('Daily Entry'!$D$7:$D$5003,'Daily Entry'!$B$7:$B$5003,$O80)) | J80: =IF($A80="","",$E80+$H80-$I80) | K80: =IF(OR($A80="",$D80=""),"",$J80*$D80) | L80: 6 | M80: =IF(OR($A80="",$D80="",$L80="",$E$4=""),"",$K80*$L80*$E$4) | O80: =IF($A80="","",$A80&" - "&$B80) | P80: =IF($A80="",0,IF(OR($F80<>0,$G80<>0),1,0)) | Q80: =IF($P80=1,SUM($P$8:$P80),"") | R80: =IF($A80="","",$A80&"#"&COUNTIF($A$8:$A80,$A80)) | S80: =IF(OR($A80="",$D80=""),0,$E80*$D80) | T80: =IF(OR($A80="",$D80=""),0,$F80*$D80) | U80: =IF(OR($A80="",$D80=""),0,$G80*$D80) | V80: =IF(OR($A80="",$D80=""),0,$H80*$D80) | W80: =IF(OR($A80="",$D80=""),0,$I80*$D80) | X80: =IF(AND($A80<>"",$D80=""),1,0) | Y80: =IF($A80="",0,IF(COUNTIF($O$8:$O$101,$O80)>1,1,0))
A81: White Squid | B81: SQW 3/6 10% | C81: Slab | D81: 2 | E81: 0 | F81: =IF($A81="","",SUMIFS('Daily Entry'!$C$7:$C$5003,'Daily Entry'!$B$7:$B$5003,$O81,'Daily Entry'!$A$7:$A$5003,$E$3)) | G81: =IF($A81="","",SUMIFS('Daily Entry'!$D$7:$D$5003,'Daily Entry'!$B$7:$B$5003,$O81,'Daily Entry'!$A$7:$A$5003,$E$3)) | H81: =IF($A81="","",SUMIFS('Daily Entry'!$C$7:$C$5003,'Daily Entry'!$B$7:$B$5003,$O81)) | I81: =IF($A81="","",SUMIFS('Daily Entry'!$D$7:$D$5003,'Daily Entry'!$B$7:$B$5003,$O81)) | J81: =IF($A81="","",$E81+$H81-$I81) | K81: =IF(OR($A81="",$D81=""),"",$J81*$D81) | L81: 5.5 | M81: =IF(OR($A81="",$D81="",$L81="",$E$4=""),"",$K81*$L81*$E$4) | O81: =IF($A81="","",$A81&" - "&$B81) | P81: =IF($A81="",0,IF(OR($F81<>0,$G81<>0),1,0)) | Q81: =IF($P81=1,SUM($P$8:$P81),"") | R81: =IF($A81="","",$A81&"#"&COUNTIF($A$8:$A81,$A81)) | S81: =IF(OR($A81="",$D81=""),0,$E81*$D81) | T81: =IF(OR($A81="",$D81=""),0,$F81*$D81) | U81: =IF(OR($A81="",$D81=""),0,$G81*$D81) | V81: =IF(OR($A81="",$D81=""),0,$H81*$D81) | W81: =IF(OR($A81="",$D81=""),0,$I81*$D81) | X81: =IF(AND($A81<>"",$D81=""),1,0) | Y81: =IF($A81="",0,IF(COUNTIF($O$8:$O$101,$O81)>1,1,0))
A82: White Squid | B82: SQW 6/10 10% | C82: Slab | D82: 2 | E82: 0 | F82: =IF($A82="","",SUMIFS('Daily Entry'!$C$7:$C$5003,'Daily Entry'!$B$7:$B$5003,$O82,'Daily Entry'!$A$7:$A$5003,$E$3)) | G82: =IF($A82="","",SUMIFS('Daily Entry'!$D$7:$D$5003,'Daily Entry'!$B$7:$B$5003,$O82,'Daily Entry'!$A$7:$A$5003,$E$3)) | H82: =IF($A82="","",SUMIFS('Daily Entry'!$C$7:$C$5003,'Daily Entry'!$B$7:$B$5003,$O82)) | I82: =IF($A82="","",SUMIFS('Daily Entry'!$D$7:$D$5003,'Daily Entry'!$B$7:$B$5003,$O82)) | J82: =IF($A82="","",$E82+$H82-$I82) | K82: =IF(OR($A82="",$D82=""),"",$J82*$D82) | L82: 5 | M82: =IF(OR($A82="",$D82="",$L82="",$E$4=""),"",$K82*$L82*$E$4) | O82: =IF($A82="","",$A82&" - "&$B82) | P82: =IF($A82="",0,IF(OR($F82<>0,$G82<>0),1,0)) | Q82: =IF($P82=1,SUM($P$8:$P82),"") | R82: =IF($A82="","",$A82&"#"&COUNTIF($A$8:$A82,$A82)) | S82: =IF(OR($A82="",$D82=""),0,$E82*$D82) | T82: =IF(OR($A82="",$D82=""),0,$F82*$D82) | U82: =IF(OR($A82="",$D82=""),0,$G82*$D82) | V82: =IF(OR($A82="",$D82=""),0,$H82*$D82) | W82: =IF(OR($A82="",$D82=""),0,$I82*$D82) | X82: =IF(AND($A82<>"",$D82=""),1,0) | Y82: =IF($A82="",0,IF(COUNTIF($O$8:$O$101,$O82)>1,1,0))
A83: White Squid | B83: SQW 10/20 10% | C83: Slab | D83: 2 | E83: 0 | F83: =IF($A83="","",SUMIFS('Daily Entry'!$C$7:$C$5003,'Daily Entry'!$B$7:$B$5003,$O83,'Daily Entry'!$A$7:$A$5003,$E$3)) | G83: =IF($A83="","",SUMIFS('Daily Entry'!$D$7:$D$5003,'Daily Entry'!$B$7:$B$5003,$O83,'Daily Entry'!$A$7:$A$5003,$E$3)) | H83: =IF($A83="","",SUMIFS('Daily Entry'!$C$7:$C$5003,'Daily Entry'!$B$7:$B$5003,$O83)) | I83: =IF($A83="","",SUMIFS('Daily Entry'!$D$7:$D$5003,'Daily Entry'!$B$7:$B$5003,$O83)) | J83: =IF($A83="","",$E83+$H83-$I83) | K83: =IF(OR($A83="",$D83=""),"",$J83*$D83) | L83: 4.5 | M83: =IF(OR($A83="",$D83="",$L83="",$E$4=""),"",$K83*$L83*$E$4) | O83: =IF($A83="","",$A83&" - "&$B83) | P83: =IF($A83="",0,IF(OR($F83<>0,$G83<>0),1,0)) | Q83: =IF($P83=1,SUM($P$8:$P83),"") | R83: =IF($A83="","",$A83&"#"&COUNTIF($A$8:$A83,$A83)) | S83: =IF(OR($A83="",$D83=""),0,$E83*$D83) | T83: =IF(OR($A83="",$D83=""),0,$F83*$D83) | U83: =IF(OR($A83="",$D83=""),0,$G83*$D83) | V83: =IF(OR($A83="",$D83=""),0,$H83*$D83) | W83: =IF(OR($A83="",$D83=""),0,$I83*$D83) | X83: =IF(AND($A83<>"",$D83=""),1,0) | Y83: =IF($A83="",0,IF(COUNTIF($O$8:$O$101,$O83)>1,1,0))
A84: White Squid | B84: SQW 20/40 10% | C84: Slab | D84: 2 | E84: 0 | F84: =IF($A84="","",SUMIFS('Daily Entry'!$C$7:$C$5003,'Daily Entry'!$B$7:$B$5003,$O84,'Daily Entry'!$A$7:$A$5003,$E$3)) | G84: =IF($A84="","",SUMIFS('Daily Entry'!$D$7:$D$5003,'Daily Entry'!$B$7:$B$5003,$O84,'Daily Entry'!$A$7:$A$5003,$E$3)) | H84: =IF($A84="","",SUMIFS('Daily Entry'!$C$7:$C$5003,'Daily Entry'!$B$7:$B$5003,$O84)) | I84: =IF($A84="","",SUMIFS('Daily Entry'!$D$7:$D$5003,'Daily Entry'!$B$7:$B$5003,$O84)) | J84: =IF($A84="","",$E84+$H84-$I84) | K84: =IF(OR($A84="",$D84=""),"",$J84*$D84) | M84: =IF(OR($A84="",$D84="",$L84="",$E$4=""),"",$K84*$L84*$E$4) | O84: =IF($A84="","",$A84&" - "&$B84) | P84: =IF($A84="",0,IF(OR($F84<>0,$G84<>0),1,0)) | Q84: =IF($P84=1,SUM($P$8:$P84),"") | R84: =IF($A84="","",$A84&"#"&COUNTIF($A$8:$A84,$A84)) | S84: =IF(OR($A84="",$D84=""),0,$E84*$D84) | T84: =IF(OR($A84="",$D84=""),0,$F84*$D84) | U84: =IF(OR($A84="",$D84=""),0,$G84*$D84) | V84: =IF(OR($A84="",$D84=""),0,$H84*$D84) | W84: =IF(OR($A84="",$D84=""),0,$I84*$D84) | X84: =IF(AND($A84<>"",$D84=""),1,0) | Y84: =IF($A84="",0,IF(COUNTIF($O$8:$O$101,$O84)>1,1,0))
A85: White Squid | B85: SQWC U/5 25% | C85: Slab | D85: 2 | E85: 0 | F85: =IF($A85="","",SUMIFS('Daily Entry'!$C$7:$C$5003,'Daily Entry'!$B$7:$B$5003,$O85,'Daily Entry'!$A$7:$A$5003,$E$3)) | G85: =IF($A85="","",SUMIFS('Daily Entry'!$D$7:$D$5003,'Daily Entry'!$B$7:$B$5003,$O85,'Daily Entry'!$A$7:$A$5003,$E$3)) | H85: =IF($A85="","",SUMIFS('Daily Entry'!$C$7:$C$5003,'Daily Entry'!$B$7:$B$5003,$O85)) | I85: =IF($A85="","",SUMIFS('Daily Entry'!$D$7:$D$5003,'Daily Entry'!$B$7:$B$5003,$O85)) | J85: =IF($A85="","",$E85+$H85-$I85) | K85: =IF(OR($A85="",$D85=""),"",$J85*$D85) | M85: =IF(OR($A85="",$D85="",$L85="",$E$4=""),"",$K85*$L85*$E$4) | O85: =IF($A85="","",$A85&" - "&$B85) | P85: =IF($A85="",0,IF(OR($F85<>0,$G85<>0),1,0)) | Q85: =IF($P85=1,SUM($P$8:$P85),"") | R85: =IF($A85="","",$A85&"#"&COUNTIF($A$8:$A85,$A85)) | S85: =IF(OR($A85="",$D85=""),0,$E85*$D85) | T85: =IF(OR($A85="",$D85=""),0,$F85*$D85) | U85: =IF(OR($A85="",$D85=""),0,$G85*$D85) | V85: =IF(OR($A85="",$D85=""),0,$H85*$D85) | W85: =IF(OR($A85="",$D85=""),0,$I85*$D85) | X85: =IF(AND($A85<>"",$D85=""),1,0) | Y85: =IF($A85="",0,IF(COUNTIF($O$8:$O$101,$O85)>1,1,0))
A86: White Squid | B86: SQWC U/10 25% | C86: Slab | D86: 2 | E86: 0 | F86: =IF($A86="","",SUMIFS('Daily Entry'!$C$7:$C$5003,'Daily Entry'!$B$7:$B$5003,$O86,'Daily Entry'!$A$7:$A$5003,$E$3)) | G86: =IF($A86="","",SUMIFS('Daily Entry'!$D$7:$D$5003,'Daily Entry'!$B$7:$B$5003,$O86,'Daily Entry'!$A$7:$A$5003,$E$3)) | H86: =IF($A86="","",SUMIFS('Daily Entry'!$C$7:$C$5003,'Daily Entry'!$B$7:$B$5003,$O86)) | I86: =IF($A86="","",SUMIFS('Daily Entry'!$D$7:$D$5003,'Daily Entry'!$B$7:$B$5003,$O86)) | J86: =IF($A86="","",$E86+$H86-$I86) | K86: =IF(OR($A86="",$D86=""),"",$J86*$D86) | M86: =IF(OR($A86="",$D86="",$L86="",$E$4=""),"",$K86*$L86*$E$4) | O86: =IF($A86="","",$A86&" - "&$B86) | P86: =IF($A86="",0,IF(OR($F86<>0,$G86<>0),1,0)) | Q86: =IF($P86=1,SUM($P$8:$P86),"") | R86: =IF($A86="","",$A86&"#"&COUNTIF($A$8:$A86,$A86)) | S86: =IF(OR($A86="",$D86=""),0,$E86*$D86) | T86: =IF(OR($A86="",$D86=""),0,$F86*$D86) | U86: =IF(OR($A86="",$D86=""),0,$G86*$D86) | V86: =IF(OR($A86="",$D86=""),0,$H86*$D86) | W86: =IF(OR($A86="",$D86=""),0,$I86*$D86) | X86: =IF(AND($A86<>"",$D86=""),1,0) | Y86: =IF($A86="",0,IF(COUNTIF($O$8:$O$101,$O86)>1,1,0))
A87: White Squid | B87: SQWC 10/20 25% | C87: Slab | D87: 2 | E87: 0 | F87: =IF($A87="","",SUMIFS('Daily Entry'!$C$7:$C$5003,'Daily Entry'!$B$7:$B$5003,$O87,'Daily Entry'!$A$7:$A$5003,$E$3)) | G87: =IF($A87="","",SUMIFS('Daily Entry'!$D$7:$D$5003,'Daily Entry'!$B$7:$B$5003,$O87,'Daily Entry'!$A$7:$A$5003,$E$3)) | H87: =IF($A87="","",SUMIFS('Daily Entry'!$C$7:$C$5003,'Daily Entry'!$B$7:$B$5003,$O87)) | I87: =IF($A87="","",SUMIFS('Daily Entry'!$D$7:$D$5003,'Daily Entry'!$B$7:$B$5003,$O87)) | J87: =IF($A87="","",$E87+$H87-$I87) | K87: =IF(OR($A87="",$D87=""),"",$J87*$D87) | M87: =IF(OR($A87="",$D87="",$L87="",$E$4=""),"",$K87*$L87*$E$4) | O87: =IF($A87="","",$A87&" - "&$B87) | P87: =IF($A87="",0,IF(OR($F87<>0,$G87<>0),1,0)) | Q87: =IF($P87=1,SUM($P$8:$P87),"") | R87: =IF($A87="","",$A87&"#"&COUNTIF($A$8:$A87,$A87)) | S87: =IF(OR($A87="",$D87=""),0,$E87*$D87) | T87: =IF(OR($A87="",$D87=""),0,$F87*$D87) | U87: =IF(OR($A87="",$D87=""),0,$G87*$D87) | V87: =IF(OR($A87="",$D87=""),0,$H87*$D87) | W87: =IF(OR($A87="",$D87=""),0,$I87*$D87) | X87: =IF(AND($A87<>"",$D87=""),1,0) | Y87: =IF($A87="",0,IF(COUNTIF($O$8:$O$101,$O87)>1,1,0))
A88: Semi Needle Squid | B88: SKIN-ON RINGS 3/6 25% | C88: Kg | D88: 1 | E88: 0 | F88: =IF($A88="","",SUMIFS('Daily Entry'!$C$7:$C$5003,'Daily Entry'!$B$7:$B$5003,$O88,'Daily Entry'!$A$7:$A$5003,$E$3)) | G88: =IF($A88="","",SUMIFS('Daily Entry'!$D$7:$D$5003,'Daily Entry'!$B$7:$B$5003,$O88,'Daily Entry'!$A$7:$A$5003,$E$3)) | H88: =IF($A88="","",SUMIFS('Daily Entry'!$C$7:$C$5003,'Daily Entry'!$B$7:$B$5003,$O88)) | I88: =IF($A88="","",SUMIFS('Daily Entry'!$D$7:$D$5003,'Daily Entry'!$B$7:$B$5003,$O88)) | J88: =IF($A88="","",$E88+$H88-$I88) | K88: =IF(OR($A88="",$D88=""),"",$J88*$D88) | M88: =IF(OR($A88="",$D88="",$L88="",$E$4=""),"",$K88*$L88*$E$4) | O88: =IF($A88="","",$A88&" - "&$B88) | P88: =IF($A88="",0,IF(OR($F88<>0,$G88<>0),1,0)) | Q88: =IF($P88=1,SUM($P$8:$P88),"") | R88: =IF($A88="","",$A88&"#"&COUNTIF($A$8:$A88,$A88)) | S88: =IF(OR($A88="",$D88=""),0,$E88*$D88) | T88: =IF(OR($A88="",$D88=""),0,$F88*$D88) | U88: =IF(OR($A88="",$D88=""),0,$G88*$D88) | V88: =IF(OR($A88="",$D88=""),0,$H88*$D88) | W88: =IF(OR($A88="",$D88=""),0,$I88*$D88) | X88: =IF(AND($A88<>"",$D88=""),1,0) | Y88: =IF($A88="",0,IF(COUNTIF($O$8:$O$101,$O88)>1,1,0))
A89: Semi Needle Squid | B89: SKIN-ON RINGS 6/10 25% | C89: Kg | D89: 1 | E89: 11500 | F89: =IF($A89="","",SUMIFS('Daily Entry'!$C$7:$C$5003,'Daily Entry'!$B$7:$B$5003,$O89,'Daily Entry'!$A$7:$A$5003,$E$3)) | G89: =IF($A89="","",SUMIFS('Daily Entry'!$D$7:$D$5003,'Daily Entry'!$B$7:$B$5003,$O89,'Daily Entry'!$A$7:$A$5003,$E$3)) | H89: =IF($A89="","",SUMIFS('Daily Entry'!$C$7:$C$5003,'Daily Entry'!$B$7:$B$5003,$O89)) | I89: =IF($A89="","",SUMIFS('Daily Entry'!$D$7:$D$5003,'Daily Entry'!$B$7:$B$5003,$O89)) | J89: =IF($A89="","",$E89+$H89-$I89) | K89: =IF(OR($A89="",$D89=""),"",$J89*$D89) | L89: 4.15 | M89: =IF(OR($A89="",$D89="",$L89="",$E$4=""),"",$K89*$L89*$E$4) | O89: =IF($A89="","",$A89&" - "&$B89) | P89: =IF($A89="",0,IF(OR($F89<>0,$G89<>0),1,0)) | Q89: =IF($P89=1,SUM($P$8:$P89),"") | R89: =IF($A89="","",$A89&"#"&COUNTIF($A$8:$A89,$A89)) | S89: =IF(OR($A89="",$D89=""),0,$E89*$D89) | T89: =IF(OR($A89="",$D89=""),0,$F89*$D89) | U89: =IF(OR($A89="",$D89=""),0,$G89*$D89) | V89: =IF(OR($A89="",$D89=""),0,$H89*$D89) | W89: =IF(OR($A89="",$D89=""),0,$I89*$D89) | X89: =IF(AND($A89<>"",$D89=""),1,0) | Y89: =IF($A89="",0,IF(COUNTIF($O$8:$O$101,$O89)>1,1,0))
A90: Semi Needle Squid | B90: SKIN-ON RINGS 10/20 25% | C90: Kg | D90: 1 | E90: 8500 | F90: =IF($A90="","",SUMIFS('Daily Entry'!$C$7:$C$5003,'Daily Entry'!$B$7:$B$5003,$O90,'Daily Entry'!$A$7:$A$5003,$E$3)) | G90: =IF($A90="","",SUMIFS('Daily Entry'!$D$7:$D$5003,'Daily Entry'!$B$7:$B$5003,$O90,'Daily Entry'!$A$7:$A$5003,$E$3)) | H90: =IF($A90="","",SUMIFS('Daily Entry'!$C$7:$C$5003,'Daily Entry'!$B$7:$B$5003,$O90)) | I90: =IF($A90="","",SUMIFS('Daily Entry'!$D$7:$D$5003,'Daily Entry'!$B$7:$B$5003,$O90)) | J90: =IF($A90="","",$E90+$H90-$I90) | K90: =IF(OR($A90="",$D90=""),"",$J90*$D90) | L90: 3.7 | M90: =IF(OR($A90="",$D90="",$L90="",$E$4=""),"",$K90*$L90*$E$4) | O90: =IF($A90="","",$A90&" - "&$B90) | P90: =IF($A90="",0,IF(OR($F90<>0,$G90<>0),1,0)) | Q90: =IF($P90=1,SUM($P$8:$P90),"") | R90: =IF($A90="","",$A90&"#"&COUNTIF($A$8:$A90,$A90)) | S90: =IF(OR($A90="",$D90=""),0,$E90*$D90) | T90: =IF(OR($A90="",$D90=""),0,$F90*$D90) | U90: =IF(OR($A90="",$D90=""),0,$G90*$D90) | V90: =IF(OR($A90="",$D90=""),0,$H90*$D90) | W90: =IF(OR($A90="",$D90=""),0,$I90*$D90) | X90: =IF(AND($A90<>"",$D90=""),1,0) | Y90: =IF($A90="",0,IF(COUNTIF($O$8:$O$101,$O90)>1,1,0))
A91: Semi Needle Squid | B91: SKIN-ON TENTACLES 25% | C91: Kg | D91: 1 | E91: 0 | F91: =IF($A91="","",SUMIFS('Daily Entry'!$C$7:$C$5003,'Daily Entry'!$B$7:$B$5003,$O91,'Daily Entry'!$A$7:$A$5003,$E$3)) | G91: =IF($A91="","",SUMIFS('Daily Entry'!$D$7:$D$5003,'Daily Entry'!$B$7:$B$5003,$O91,'Daily Entry'!$A$7:$A$5003,$E$3)) | H91: =IF($A91="","",SUMIFS('Daily Entry'!$C$7:$C$5003,'Daily Entry'!$B$7:$B$5003,$O91)) | I91: =IF($A91="","",SUMIFS('Daily Entry'!$D$7:$D$5003,'Daily Entry'!$B$7:$B$5003,$O91)) | J91: =IF($A91="","",$E91+$H91-$I91) | K91: =IF(OR($A91="",$D91=""),"",$J91*$D91) | M91: =IF(OR($A91="",$D91="",$L91="",$E$4=""),"",$K91*$L91*$E$4) | O91: =IF($A91="","",$A91&" - "&$B91) | P91: =IF($A91="",0,IF(OR($F91<>0,$G91<>0),1,0)) | Q91: =IF($P91=1,SUM($P$8:$P91),"") | R91: =IF($A91="","",$A91&"#"&COUNTIF($A$8:$A91,$A91)) | S91: =IF(OR($A91="",$D91=""),0,$E91*$D91) | T91: =IF(OR($A91="",$D91=""),0,$F91*$D91) | U91: =IF(OR($A91="",$D91=""),0,$G91*$D91) | V91: =IF(OR($A91="",$D91=""),0,$H91*$D91) | W91: =IF(OR($A91="",$D91=""),0,$I91*$D91) | X91: =IF(AND($A91<>"",$D91=""),1,0) | Y91: =IF($A91="",0,IF(COUNTIF($O$8:$O$101,$O91)>1,1,0))
A92: Semi Needle Squid | B92: SQW 10/20 | C92: Slab | D92: 4 | E92: 0 | F92: =IF($A92="","",SUMIFS('Daily Entry'!$C$7:$C$5003,'Daily Entry'!$B$7:$B$5003,$O92,'Daily Entry'!$A$7:$A$5003,$E$3)) | G92: =IF($A92="","",SUMIFS('Daily Entry'!$D$7:$D$5003,'Daily Entry'!$B$7:$B$5003,$O92,'Daily Entry'!$A$7:$A$5003,$E$3)) | H92: =IF($A92="","",SUMIFS('Daily Entry'!$C$7:$C$5003,'Daily Entry'!$B$7:$B$5003,$O92)) | I92: =IF($A92="","",SUMIFS('Daily Entry'!$D$7:$D$5003,'Daily Entry'!$B$7:$B$5003,$O92)) | J92: =IF($A92="","",$E92+$H92-$I92) | K92: =IF(OR($A92="",$D92=""),"",$J92*$D92) | L92: 1.8 | M92: =IF(OR($A92="",$D92="",$L92="",$E$4=""),"",$K92*$L92*$E$4) | O92: =IF($A92="","",$A92&" - "&$B92) | P92: =IF($A92="",0,IF(OR($F92<>0,$G92<>0),1,0)) | Q92: =IF($P92=1,SUM($P$8:$P92),"") | R92: =IF($A92="","",$A92&"#"&COUNTIF($A$8:$A92,$A92)) | S92: =IF(OR($A92="",$D92=""),0,$E92*$D92) | T92: =IF(OR($A92="",$D92=""),0,$F92*$D92) | U92: =IF(OR($A92="",$D92=""),0,$G92*$D92) | V92: =IF(OR($A92="",$D92=""),0,$H92*$D92) | W92: =IF(OR($A92="",$D92=""),0,$I92*$D92) | X92: =IF(AND($A92<>"",$D92=""),1,0) | Y92: =IF($A92="",0,IF(COUNTIF($O$8:$O$101,$O92)>1,1,0))
A93: Semi Needle Squid | B93: SQW 20/40 | C93: Slab | D93: 4 | E93: 0 | F93: =IF($A93="","",SUMIFS('Daily Entry'!$C$7:$C$5003,'Daily Entry'!$B$7:$B$5003,$O93,'Daily Entry'!$A$7:$A$5003,$E$3)) | G93: =IF($A93="","",SUMIFS('Daily Entry'!$D$7:$D$5003,'Daily Entry'!$B$7:$B$5003,$O93,'Daily Entry'!$A$7:$A$5003,$E$3)) | H93: =IF($A93="","",SUMIFS('Daily Entry'!$C$7:$C$5003,'Daily Entry'!$B$7:$B$5003,$O93)) | I93: =IF($A93="","",SUMIFS('Daily Entry'!$D$7:$D$5003,'Daily Entry'!$B$7:$B$5003,$O93)) | J93: =IF($A93="","",$E93+$H93-$I93) | K93: =IF(OR($A93="",$D93=""),"",$J93*$D93) | L93: 1.8 | M93: =IF(OR($A93="",$D93="",$L93="",$E$4=""),"",$K93*$L93*$E$4) | O93: =IF($A93="","",$A93&" - "&$B93) | P93: =IF($A93="",0,IF(OR($F93<>0,$G93<>0),1,0)) | Q93: =IF($P93=1,SUM($P$8:$P93),"") | R93: =IF($A93="","",$A93&"#"&COUNTIF($A$8:$A93,$A93)) | S93: =IF(OR($A93="",$D93=""),0,$E93*$D93) | T93: =IF(OR($A93="",$D93=""),0,$F93*$D93) | U93: =IF(OR($A93="",$D93=""),0,$G93*$D93) | V93: =IF(OR($A93="",$D93=""),0,$H93*$D93) | W93: =IF(OR($A93="",$D93=""),0,$I93*$D93) | X93: =IF(AND($A93<>"",$D93=""),1,0) | Y93: =IF($A93="",0,IF(COUNTIF($O$8:$O$101,$O93)>1,1,0))
A94: Semi Needle Squid | B94: SQW 40/60 | C94: Slab | D94: 4 | E94: 0 | F94: =IF($A94="","",SUMIFS('Daily Entry'!$C$7:$C$5003,'Daily Entry'!$B$7:$B$5003,$O94,'Daily Entry'!$A$7:$A$5003,$E$3)) | G94: =IF($A94="","",SUMIFS('Daily Entry'!$D$7:$D$5003,'Daily Entry'!$B$7:$B$5003,$O94,'Daily Entry'!$A$7:$A$5003,$E$3)) | H94: =IF($A94="","",SUMIFS('Daily Entry'!$C$7:$C$5003,'Daily Entry'!$B$7:$B$5003,$O94)) | I94: =IF($A94="","",SUMIFS('Daily Entry'!$D$7:$D$5003,'Daily Entry'!$B$7:$B$5003,$O94)) | J94: =IF($A94="","",$E94+$H94-$I94) | K94: =IF(OR($A94="",$D94=""),"",$J94*$D94) | L94: 1.65 | M94: =IF(OR($A94="",$D94="",$L94="",$E$4=""),"",$K94*$L94*$E$4) | O94: =IF($A94="","",$A94&" - "&$B94) | P94: =IF($A94="",0,IF(OR($F94<>0,$G94<>0),1,0)) | Q94: =IF($P94=1,SUM($P$8:$P94),"") | R94: =IF($A94="","",$A94&"#"&COUNTIF($A$8:$A94,$A94)) | S94: =IF(OR($A94="",$D94=""),0,$E94*$D94) | T94: =IF(OR($A94="",$D94=""),0,$F94*$D94) | U94: =IF(OR($A94="",$D94=""),0,$G94*$D94) | V94: =IF(OR($A94="",$D94=""),0,$H94*$D94) | W94: =IF(OR($A94="",$D94=""),0,$I94*$D94) | X94: =IF(AND($A94<>"",$D94=""),1,0) | Y94: =IF($A94="",0,IF(COUNTIF($O$8:$O$101,$O94)>1,1,0))
A95: Semi Needle Squid | B95: SQW 60/80 | C95: Slab | D95: 4 | E95: 0 | F95: =IF($A95="","",SUMIFS('Daily Entry'!$C$7:$C$5003,'Daily Entry'!$B$7:$B$5003,$O95,'Daily Entry'!$A$7:$A$5003,$E$3)) | G95: =IF($A95="","",SUMIFS('Daily Entry'!$D$7:$D$5003,'Daily Entry'!$B$7:$B$5003,$O95,'Daily Entry'!$A$7:$A$5003,$E$3)) | H95: =IF($A95="","",SUMIFS('Daily Entry'!$C$7:$C$5003,'Daily Entry'!$B$7:$B$5003,$O95)) | I95: =IF($A95="","",SUMIFS('Daily Entry'!$D$7:$D$5003,'Daily Entry'!$B$7:$B$5003,$O95)) | J95: =IF($A95="","",$E95+$H95-$I95) | K95: =IF(OR($A95="",$D95=""),"",$J95*$D95) | L95: 1.3 | M95: =IF(OR($A95="",$D95="",$L95="",$E$4=""),"",$K95*$L95*$E$4) | O95: =IF($A95="","",$A95&" - "&$B95) | P95: =IF($A95="",0,IF(OR($F95<>0,$G95<>0),1,0)) | Q95: =IF($P95=1,SUM($P$8:$P95),"") | R95: =IF($A95="","",$A95&"#"&COUNTIF($A$8:$A95,$A95)) | S95: =IF(OR($A95="",$D95=""),0,$E95*$D95) | T95: =IF(OR($A95="",$D95=""),0,$F95*$D95) | U95: =IF(OR($A95="",$D95=""),0,$G95*$D95) | V95: =IF(OR($A95="",$D95=""),0,$H95*$D95) | W95: =IF(OR($A95="",$D95=""),0,$I95*$D95) | X95: =IF(AND($A95<>"",$D95=""),1,0) | Y95: =IF($A95="",0,IF(COUNTIF($O$8:$O$101,$O95)>1,1,0))
F96: =IF($A96="","",SUMIFS('Daily Entry'!$C$7:$C$5003,'Daily Entry'!$B$7:$B$5003,$O96,'Daily Entry'!$A$7:$A$5003,$E$3)) | G96: =IF($A96="","",SUMIFS('Daily Entry'!$D$7:$D$5003,'Daily Entry'!$B$7:$B$5003,$O96,'Daily Entry'!$A$7:$A$5003,$E$3)) | H96: =IF($A96="","",SUMIFS('Daily Entry'!$C$7:$C$5003,'Daily Entry'!$B$7:$B$5003,$O96)) | I96: =IF($A96="","",SUMIFS('Daily Entry'!$D$7:$D$5003,'Daily Entry'!$B$7:$B$5003,$O96)) | J96: =IF($A96="","",$E96+$H96-$I96) | K96: =IF(OR($A96="",$D96=""),"",$J96*$D96) | M96: =IF(OR($A96="",$D96="",$L96="",$E$4=""),"",$K96*$L96*$E$4) | O96: =IF($A96="","",$A96&" - "&$B96) | P96: =IF($A96="",0,IF(OR($F96<>0,$G96<>0),1,0)) | Q96: =IF($P96=1,SUM($P$8:$P96),"") | R96: =IF($A96="","",$A96&"#"&COUNTIF($A$8:$A96,$A96)) | S96: =IF(OR($A96="",$D96=""),0,$E96*$D96) | T96: =IF(OR($A96="",$D96=""),0,$F96*$D96) | U96: =IF(OR($A96="",$D96=""),0,$G96*$D96) | V96: =IF(OR($A96="",$D96=""),0,$H96*$D96) | W96: =IF(OR($A96="",$D96=""),0,$I96*$D96) | X96: =IF(AND($A96<>"",$D96=""),1,0) | Y96: =IF($A96="",0,IF(COUNTIF($O$8:$O$101,$O96)>1,1,0))
F97: =IF($A97="","",SUMIFS('Daily Entry'!$C$7:$C$5003,'Daily Entry'!$B$7:$B$5003,$O97,'Daily Entry'!$A$7:$A$5003,$E$3)) | G97: =IF($A97="","",SUMIFS('Daily Entry'!$D$7:$D$5003,'Daily Entry'!$B$7:$B$5003,$O97,'Daily Entry'!$A$7:$A$5003,$E$3)) | H97: =IF($A97="","",SUMIFS('Daily Entry'!$C$7:$C$5003,'Daily Entry'!$B$7:$B$5003,$O97)) | I97: =IF($A97="","",SUMIFS('Daily Entry'!$D$7:$D$5003,'Daily Entry'!$B$7:$B$5003,$O97)) | J97: =IF($A97="","",$E97+$H97-$I97) | K97: =IF(OR($A97="",$D97=""),"",$J97*$D97) | M97: =IF(OR($A97="",$D97="",$L97="",$E$4=""),"",$K97*$L97*$E$4) | O97: =IF($A97="","",$A97&" - "&$B97) | P97: =IF($A97="",0,IF(OR($F97<>0,$G97<>0),1,0)) | Q97: =IF($P97=1,SUM($P$8:$P97),"") | R97: =IF($A97="","",$A97&"#"&COUNTIF($A$8:$A97,$A97)) | S97: =IF(OR($A97="",$D97=""),0,$E97*$D97) | T97: =IF(OR($A97="",$D97=""),0,$F97*$D97) | U97: =IF(OR($A97="",$D97=""),0,$G97*$D97) | V97: =IF(OR($A97="",$D97=""),0,$H97*$D97) | W97: =IF(OR($A97="",$D97=""),0,$I97*$D97) | X97: =IF(AND($A97<>"",$D97=""),1,0) | Y97: =IF($A97="",0,IF(COUNTIF($O$8:$O$101,$O97)>1,1,0))
F98: =IF($A98="","",SUMIFS('Daily Entry'!$C$7:$C$5003,'Daily Entry'!$B$7:$B$5003,$O98,'Daily Entry'!$A$7:$A$5003,$E$3)) | G98: =IF($A98="","",SUMIFS('Daily Entry'!$D$7:$D$5003,'Daily Entry'!$B$7:$B$5003,$O98,'Daily Entry'!$A$7:$A$5003,$E$3)) | H98: =IF($A98="","",SUMIFS('Daily Entry'!$C$7:$C$5003,'Daily Entry'!$B$7:$B$5003,$O98)) | I98: =IF($A98="","",SUMIFS('Daily Entry'!$D$7:$D$5003,'Daily Entry'!$B$7:$B$5003,$O98)) | J98: =IF($A98="","",$E98+$H98-$I98) | K98: =IF(OR($A98="",$D98=""),"",$J98*$D98) | M98: =IF(OR($A98="",$D98="",$L98="",$E$4=""),"",$K98*$L98*$E$4) | O98: =IF($A98="","",$A98&" - "&$B98) | P98: =IF($A98="",0,IF(OR($F98<>0,$G98<>0),1,0)) | Q98: =IF($P98=1,SUM($P$8:$P98),"") | R98: =IF($A98="","",$A98&"#"&COUNTIF($A$8:$A98,$A98)) | S98: =IF(OR($A98="",$D98=""),0,$E98*$D98) | T98: =IF(OR($A98="",$D98=""),0,$F98*$D98) | U98: =IF(OR($A98="",$D98=""),0,$G98*$D98) | V98: =IF(OR($A98="",$D98=""),0,$H98*$D98) | W98: =IF(OR($A98="",$D98=""),0,$I98*$D98) | X98: =IF(AND($A98<>"",$D98=""),1,0) | Y98: =IF($A98="",0,IF(COUNTIF($O$8:$O$101,$O98)>1,1,0))
F99: =IF($A99="","",SUMIFS('Daily Entry'!$C$7:$C$5003,'Daily Entry'!$B$7:$B$5003,$O99,'Daily Entry'!$A$7:$A$5003,$E$3)) | G99: =IF($A99="","",SUMIFS('Daily Entry'!$D$7:$D$5003,'Daily Entry'!$B$7:$B$5003,$O99,'Daily Entry'!$A$7:$A$5003,$E$3)) | H99: =IF($A99="","",SUMIFS('Daily Entry'!$C$7:$C$5003,'Daily Entry'!$B$7:$B$5003,$O99)) | I99: =IF($A99="","",SUMIFS('Daily Entry'!$D$7:$D$5003,'Daily Entry'!$B$7:$B$5003,$O99)) | J99: =IF($A99="","",$E99+$H99-$I99) | K99: =IF(OR($A99="",$D99=""),"",$J99*$D99) | M99: =IF(OR($A99="",$D99="",$L99="",$E$4=""),"",$K99*$L99*$E$4) | O99: =IF($A99="","",$A99&" - "&$B99) | P99: =IF($A99="",0,IF(OR($F99<>0,$G99<>0),1,0)) | Q99: =IF($P99=1,SUM($P$8:$P99),"") | R99: =IF($A99="","",$A99&"#"&COUNTIF($A$8:$A99,$A99)) | S99: =IF(OR($A99="",$D99=""),0,$E99*$D99) | T99: =IF(OR($A99="",$D99=""),0,$F99*$D99) | U99: =IF(OR($A99="",$D99=""),0,$G99*$D99) | V99: =IF(OR($A99="",$D99=""),0,$H99*$D99) | W99: =IF(OR($A99="",$D99=""),0,$I99*$D99) | X99: =IF(AND($A99<>"",$D99=""),1,0) | Y99: =IF($A99="",0,IF(COUNTIF($O$8:$O$101,$O99)>1,1,0))
F100: =IF($A100="","",SUMIFS('Daily Entry'!$C$7:$C$5003,'Daily Entry'!$B$7:$B$5003,$O100,'Daily Entry'!$A$7:$A$5003,$E$3)) | G100: =IF($A100="","",SUMIFS('Daily Entry'!$D$7:$D$5003,'Daily Entry'!$B$7:$B$5003,$O100,'Daily Entry'!$A$7:$A$5003,$E$3)) | H100: =IF($A100="","",SUMIFS('Daily Entry'!$C$7:$C$5003,'Daily Entry'!$B$7:$B$5003,$O100)) | I100: =IF($A100="","",SUMIFS('Daily Entry'!$D$7:$D$5003,'Daily Entry'!$B$7:$B$5003,$O100)) | J100: =IF($A100="","",$E100+$H100-$I100) | K100: =IF(OR($A100="",$D100=""),"",$J100*$D100) | M100: =IF(OR($A100="",$D100="",$L100="",$E$4=""),"",$K100*$L100*$E$4) | O100: =IF($A100="","",$A100&" - "&$B100) | P100: =IF($A100="",0,IF(OR($F100<>0,$G100<>0),1,0)) | Q100: =IF($P100=1,SUM($P$8:$P100),"") | R100: =IF($A100="","",$A100&"#"&COUNTIF($A$8:$A100,$A100)) | S100: =IF(OR($A100="",$D100=""),0,$E100*$D100) | T100: =IF(OR($A100="",$D100=""),0,$F100*$D100) | U100: =IF(OR($A100="",$D100=""),0,$G100*$D100) | V100: =IF(OR($A100="",$D100=""),0,$H100*$D100) | W100: =IF(OR($A100="",$D100=""),0,$I100*$D100) | X100: =IF(AND($A100<>"",$D100=""),1,0) | Y100: =IF($A100="",0,IF(COUNTIF($O$8:$O$101,$O100)>1,1,0))
F101: =IF($A101="","",SUMIFS('Daily Entry'!$C$7:$C$5003,'Daily Entry'!$B$7:$B$5003,$O101,'Daily Entry'!$A$7:$A$5003,$E$3)) | G101: =IF($A101="","",SUMIFS('Daily Entry'!$D$7:$D$5003,'Daily Entry'!$B$7:$B$5003,$O101,'Daily Entry'!$A$7:$A$5003,$E$3)) | H101: =IF($A101="","",SUMIFS('Daily Entry'!$C$7:$C$5003,'Daily Entry'!$B$7:$B$5003,$O101)) | I101: =IF($A101="","",SUMIFS('Daily Entry'!$D$7:$D$5003,'Daily Entry'!$B$7:$B$5003,$O101)) | J101: =IF($A101="","",$E101+$H101-$I101) | K101: =IF(OR($A101="",$D101=""),"",$J101*$D101) | M101: =IF(OR($A101="",$D101="",$L101="",$E$4=""),"",$K101*$L101*$E$4) | O101: =IF($A101="","",$A101&" - "&$B101) | P101: =IF($A101="",0,IF(OR($F101<>0,$G101<>0),1,0)) | Q101: =IF($P101=1,SUM($P$8:$P101),"") | R101: =IF($A101="","",$A101&"#"&COUNTIF($A$8:$A101,$A101)) | S101: =IF(OR($A101="",$D101=""),0,$E101*$D101) | T101: =IF(OR($A101="",$D101=""),0,$F101*$D101) | U101: =IF(OR($A101="",$D101=""),0,$G101*$D101) | V101: =IF(OR($A101="",$D101=""),0,$H101*$D101) | W101: =IF(OR($A101="",$D101=""),0,$I101*$D101) | X101: =IF(AND($A101<>"",$D101=""),1,0) | Y101: =IF($A101="",0,IF(COUNTIF($O$8:$O$101,$O101)>1,1,0))
A102: GRAND TOTAL (Kg) | K102: =SUM($K$8:$K$101) | M102: =IF(SUM($M$8:$M$101)=0,"",SUM($M$8:$M$101))
A103: Balances are in each product's own unit, so only the kilo column totals. Stock Value (₹) = Closing Kg × Rate / Kg (US$) × the exchange rate.
A104: =IF(SUM($X$8:$X$101)=0,"",SUM($X$8:$X$101)&" product(s) have no Kg / Unit — they are not valued. Fill column D.")
A105: =IF(SUM($Y$8:$Y$101)=0,"","Two rows share a Brand + Product — production would be counted twice. Rename one.")

Sheet Daily Entry
A1: PREMIER EXPORTS INTERNATIONAL
A2: DAILY ENTRY — ADD ONE ROW PER PRODUCT THAT MOVED
A4: After production, add a row below: date, product from the dropdown, and the quantity in that product's own unit — slabs for the shrimp brands, kilos for tuna and mackerel. Never delete past rows. | G4: Rows that will not reach Stock: | J4: =SUMPRODUCT((B7:B5003<>"")*(COUNTIF(Stock!$O$8:$O$101,B7:B5003)=0)) | K4: ← must stay at 0; anything else is a mistyped product
A6: Date | B6: Item (pick from list) | C6: Production (in product unit) | D6: Shipment (in product unit) | E6: Note
A7: 46254 | B7: Blue Dolphin - PD PVN 100/200 | C7: 1068
A8: 46254 | B8: Blue Dolphin - PD KKD 100/200 | C8: 65
A9: 46254 | B9: Blue Dolphin - PUD PVN 200/300 | C9: 267
A10: 46254 | B10: Primus Japan - PUD KZN 40/60 | C10: 29
A11: 46254 | B11: Primus Japan - PUD KZN 60/80 | C11: 39
A12: 46254 | B12: Primus Japan - PUD KZN 80/120 | C12: 50
A13: 46254 | B13: Primus Japan - PUD NRN 80/120 | C13: 3
A14: 46254 | B14: Primus Japan - PUD KZN 100/200 | C14: 50
A15: 46254 | B15: Primus Japan - PUD KZN 200/300 | C15: 33
A16: 46254 | B16: Primus Japan - PUD PVN 300/500 | C16: 156
A17: 46254 | B17: Primus Japan - PUD KKD 300/500 | C17: 596
A18: 46254 | B18: Primus EU - BKN | C18: 52
... A31: 46255 | B31: Primus EU - BKN | C31: 31
A32: 46255 | B32: Blue Dolphin - PD PVN 100/200 | C32: 0 | D32: 5770
A33: 46255 | B33: Blue Dolphin - PUD PVN 200/300 | C33: 0 | D33: 1200
A34: 46255 | B34: Blue Dolphin - PUD KKD 200/300 | C34: 0 | D34: 1200
A35: 46255 | B35: Blue Dolphin - PUD PVN 300/500 | C35: 0 | D35: 660
A36: 46255 | B36: Blue Dolphin - PUD KKD 300/500 | C36: 0 | D36: 1170
A37: 46256 | B37: Blue Dolphin - PD PVN 100/200 | C37: 588
A38: 46256 | B38: Blue Dolphin - PD KKD 100/200 | C38: 52
A39: 46256 | B39: Blue Dolphin - PUD PVN 200/300 | C39: 419
A40: 46256 | B40: THT Brand - PUD PVN 80/120 | C40: 413
A41: 46256 | B41: THT Brand - PUD PVN 100/200 | C41: 556
A42: 46256 | B42: Primus Japan - PUD KKD 200/300 | C42: 22
A43: 46256 | B43: Primus Japan - PUD KKD 300/500 | C43: 374
A44: 46256 | B44: Primus Japan - PUD PVN 300/500 | C44: 12
A45: 46256 | B45: Primus Japan - PUD KZN 80/120 | C45: 2
A46: 46256 | B46: Primus Japan - PUD KZN 100/200 | C46: 37
A47: 46256 | B47: Primus Japan - PUD KZN 200/300 | C47: 12
A48: 46256 | B48: Primus EU - BKN | C48: 16
A49: 46256 | B49: Primus Japan - PUD PVN 80/120 | C49: 0 | D49: 10000
A50: 46256 | B50: Semi Needle Squid - SQW 20/40 | C50: 165
A51: 46256 | B51: Semi Needle Squid - SQW 40/60 | C51: 801
A52: 46256 | B52: Semi Needle Squid - SQW 60/80 | C52: 137
A53: 46257 | B53: Blue Dolphin - PD PVN 100/200 | C53: 52
A54: 46257 | B54: Blue Dolphin - PUD PVN 200/300 | C54: 62
A55: 46257 | B55: Blue Dolphin - PUD PVN 300/500 | C55: 15
A56: 46257 | B56: THT Brand - PUD PVN 80/120 | C56: 58
A57: 46257 | B57: Primus Japan - PUD KKD 300/500 | C57: 83
A58: 46257 | B58: Primus EU - BKN | C58: 3
A59: 46257 | B59: Semi Needle Squid - SQW 10/20 | C59: 3
A60: 46257 | B60: Semi Needle Squid - SQW 20/40 | C60: 50
A61: 46257 | B61: Semi Needle Squid - SQW 40/60 | C61: 495
... A78: 46260 | B78: Tuna - SKIPJACK 4/10 | C78: 408.6
A79: 46260 | B79: Primus Japan - PUD PVN 80/120 | C79: 0 | D79: 6849
A80: 46260 | B80: Primus Japan - PUD PVN 100/200 | C80: 0 | D80: 2617
A81: 46260 | B81: THT Brand - PUD PVN 100/200 | C81: 0 | D81: 383
A82: 46260 | B82: THT Brand - PUD PVN 80/120 | C82: 0 | D82: 151
A83: 46261 | B83: Semi Needle Squid - SQW 10/20 | C83: 20
A84: 46261 | B84: Semi Needle Squid - SQW 20/40 | C84: 120
A85: 46261 | B85: Semi Needle Squid - SQW 40/60 | C85: 94
A86: 46261 | B86: Semi Needle Squid - SQW 60/80 | C86: 692
A87: 46261 | B87: Tuna - SKIPJACK 2/4 | C87: 7665.5
A88: 46261 | B88: Tuna - SKIPJACK 4/10 | C88: 3525
A89: 46262 | B89: Blue Dolphin - PUD PVN 200/300 | C89: 43
A90: 46262 | B90: Primus Japan - PUD KKD 200/300 | C90: 7
A91: 46262 | B91: Primus Japan - PUD KKD 300/500 | C91: 97
A92: 46262 | B92: Primus Japan - PUD PVN 300/500 | C92: 63
A93: 46262 | B93: THT Brand - PUD PVN 80/120 | C93: 17
A94: 46262 | B94: THT Brand - PUD PVN 100/200 | C94: 26
... A99: 46262 | B99: Tuna - SKIPJACK 4/10 | C99: 4148.7
A100: 46262 | B100: Blue Dolphin - PD PVN 100/200 | C100: 0 | D100: 1520
A101: 46262 | B101: Blue Dolphin - PD KKD 100/200 | C101: 0 | D101: 400
A102: 46262 | B102: Blue Dolphin - PUD KKD 200/300 | C102: 0 | D102: 1200
A103: 46262 | B103: Blue Dolphin - PUD PVN 300/500 | C103: 0 | D103: 420
A104: 46262 | B104: Blue Dolphin - PUD KKD 300/500 | C104: 0 | D104: 6372
A105: 46262 | B105: Primus Japan - PUD KKD 300/500 | C105: 0 | D105: 88
A106: 46263 | B106: Blue Dolphin - PUD PVN 200/300 | C106: 92
A107: 46263 | B107: THT Brand - PUD PVN 100/200 | C107: 96
A108: 46263 | B108: Primus Japan - PUD KKD 200/300 | C108: 40
A109: 46263 | B109: Primus Japan - PUD KKD 300/500 | C109: 892
A110: 46263 | B110: Semi Needle Squid - SQW 20/40 | C110: 90
A111: 46263 | B111: Semi Needle Squid - SQW 40/60 | C111: 124
A112: 46263 | B112: Semi Needle Squid - SQW 60/80 | C112: 949
A113: 46263 | B113: Tuna - SKIPJACK 2/4 | C113: 1243
A114: 46263 | B114: Tuna - SKIPJACK 4/10 | C114: 525
A115: 46263 | B115: Tuna - YELLOW FIN 2/4 | C115: 476
A116: 46263 | B116: Tuna - YELLOW FIN 4/10 | C116: 562
A117: 46263 | B117: Tuna - SKIPJACK 2/4 | C117: 0 | D117: 25884
A118: 46263 | B118: Tuna - SKIPJACK 4/10 | C118: 0 | D118: 3116
A119: 46264 | B119: Primus Japan - PUD KKD 300/500 | C119: 247
A120: 46264 | B120: Semi Needle Squid - SQW 20/40 | C120: 95
A121: 46264 | B121: Semi Needle Squid - SQW 40/60 | C121: 151
A122: 46264 | B122: Semi Needle Squid - SQW 60/80 | C122: 394
A123: 46265 | B123: Blue Dolphin - PD PVN 100/200 | C123: 512
A124: 46265 | B124: Blue Dolphin - PD KKD 100/200 | C124: 8
A125: 46265 | B125: Blue Dolphin - PUD PVN 200/300 | C125: 34
A126: 46265 | B126: THT Brand - PUD PVN 80/120 | C126: 458
A127: 46265 | B127: Primus Japan - PUD KKD 300/500 | C127: 1808
A128: 46265 | B128: Primus EU - PUD 20/40 | C128: 2
A129: 46265 | B129: Primus Japan - PUD KZN 40/60 | C129: 2
A130: 46265 | B130: Primus Japan - PUD KZN 60/80 | C130: 5
... A216: 46271 | B216: Mackerel - WHOLE 12/15 | C216: 6670
A217: 46270 | B217: Primus Japan - PUD KKD 200/300 | C217: 0 | D217: 2849
A218: 46270 | B218: Primus Japan - PUD PVN 300/500 | C218: 0 | D218: 300
A219: 46270 | B219: Primus Japan - PUD KKD 300/500 | C219: 0 | D219: 6700
...

Sheet Summary
A1: PREMIER EXPORTS INTERNATIONAL
A2: VALUATION BY BRAND
A4: Closing Stock | C4: Stock Value (₹) | G4: Stock Value ($)
A5: =Stock!$K$102 | C5: =IF(Stock!$M$102="","—",Stock!$M$102) | G5: =IF(OR(Stock!$E$4="",Stock!$M$102=""),"—",Stock!$M$102/Stock!$E$4)
A6: kilos, across every product | C6: at the per-kilo export prices | G6: the same stock in dollars
A7: =IF(SUM(Stock!$X$8:$X$101)=0,"",SUM(Stock!$X$8:$X$101)&" product(s) have no Kg / Unit on Stock — they are counted in kilos as zero and are not valued.")
A9: Blue Dolphin
A10: Product | B10: Unit | C10: Kg / Unit | D10: Closing Balance | E10: Closing Stock (Kg) | F10: No. of Cases | G10: Rate / Kg ($) | H10: Stock Value (₹)
A11: =IF($J11="","",INDEX(Stock!$B$8:$B$101,$J11)) | B11: =IF($J11="","",IF(INDEX(Stock!$C$8:$C$101,$J11)=0,"",INDEX(Stock!$C$8:$C$101,$J11))) | C11: =IF($J11="","",IF(INDEX(Stock!$D$8:$D$101,$J11)=0,"",INDEX(Stock!$D$8:$D$101,$J11))) | D11: =IF($J11="","",INDEX(Stock!$J$8:$J$101,$J11)) | E11: =IF($J11="","",INDEX(Stock!$K$8:$K$101,$J11)) | F11: =+$D11/10 | G11: =IF($J11="","",IF(INDEX(Stock!$L$8:$L$101,$J11)=0,"",INDEX(Stock!$L$8:$L$101,$J11))) | H11: =IF($J11="","",INDEX(Stock!$M$8:$M$101,$J11)) | J11: =IFERROR(MATCH($A$9&"#"&1,Stock!$R$8:$R$101,0),"")
A12: =IF($J12="","",INDEX(Stock!$B$8:$B$101,$J12)) | B12: =IF($J12="","",IF(INDEX(Stock!$C$8:$C$101,$J12)=0,"",INDEX(Stock!$C$8:$C$101,$J12))) | C12: =IF($J12="","",IF(INDEX(Stock!$D$8:$D$101,$J12)=0,"",INDEX(Stock!$D$8:$D$101,$J12))) | D12: =IF($J12="","",INDEX(Stock!$J$8:$J$101,$J12)) | E12: =IF($J12="","",INDEX(Stock!$K$8:$K$101,$J12)) | F12: =+$D12/10 | G12: =IF($J12="","",IF(INDEX(Stock!$L$8:$L$101,$J12)=0,"",INDEX(Stock!$L$8:$L$101,$J12))) | H12: =IF($J12="","",INDEX(Stock!$M$8:$M$101,$J12)) | J12: =IFERROR(MATCH($A$9&"#"&2,Stock!$R$8:$R$101,0),"")
A13: =IF($J13="","",INDEX(Stock!$B$8:$B$101,$J13)) | B13: =IF($J13="","",IF(INDEX(Stock!$C$8:$C$101,$J13)=0,"",INDEX(Stock!$C$8:$C$101,$J13))) | C13: =IF($J13="","",IF(INDEX(Stock!$D$8:$D$101,$J13)=0,"",INDEX(Stock!$D$8:$D$101,$J13))) | D13: =IF($J13="","",INDEX(Stock!$J$8:$J$101,$J13)) | E13: =IF($J13="","",INDEX(Stock!$K$8:$K$101,$J13)) | F13: =+$D13/10 | G13: =IF($J13="","",IF(INDEX(Stock!$L$8:$L$101,$J13)=0,"",INDEX(Stock!$L$8:$L$101,$J13))) | H13: =IF($J13="","",INDEX(Stock!$M$8:$M$101,$J13)) | J13: =IFERROR(MATCH($A$9&"#"&3,Stock!$R$8:$R$101,0),"")
A14: =IF($J14="","",INDEX(Stock!$B$8:$B$101,$J14)) | B14: =IF($J14="","",IF(INDEX(Stock!$C$8:$C$101,$J14)=0,"",INDEX(Stock!$C$8:$C$101,$J14))) | C14: =IF($J14="","",IF(INDEX(Stock!$D$8:$D$101,$J14)=0,"",INDEX(Stock!$D$8:$D$101,$J14))) | D14: =IF($J14="","",INDEX(Stock!$J$8:$J$101,$J14)) | E14: =IF($J14="","",INDEX(Stock!$K$8:$K$101,$J14)) | F14: =+$D14/10 | G14: =IF($J14="","",IF(INDEX(Stock!$L$8:$L$101,$J14)=0,"",INDEX(Stock!$L$8:$L$101,$J14))) | H14: =IF($J14="","",INDEX(Stock!$M$8:$M$101,$J14)) | J14: =IFERROR(MATCH($A$9&"#"&4,Stock!$R$8:$R$101,0),"")
A15: =IF($J15="","",INDEX(Stock!$B$8:$B$101,$J15)) | B15: =IF($J15="","",IF(INDEX(Stock!$C$8:$C$101,$J15)=0,"",INDEX(Stock!$C$8:$C$101,$J15))) | C15: =IF($J15="","",IF(INDEX(Stock!$D$8:$D$101,$J15)=0,"",INDEX(Stock!$D$8:$D$101,$J15))) | D15: =IF($J15="","",INDEX(Stock!$J$8:$J$101,$J15)) | E15: =IF($J15="","",INDEX(Stock!$K$8:$K$101,$J15)) | F15: =+$D15/10 | G15: =IF($J15="","",IF(INDEX(Stock!$L$8:$L$101,$J15)=0,"",INDEX(Stock!$L$8:$L$101,$J15))) | H15: =IF($J15="","",INDEX(Stock!$M$8:$M$101,$J15)) | J15: =IFERROR(MATCH($A$9&"#"&5,Stock!$R$8:$R$101,0),"")
A16: =IF($J16="","",INDEX(Stock!$B$8:$B$101,$J16)) | B16: =IF($J16="","",IF(INDEX(Stock!$C$8:$C$101,$J16)=0,"",INDEX(Stock!$C$8:$C$101,$J16))) | C16: =IF($J16="","",IF(INDEX(Stock!$D$8:$D$101,$J16)=0,"",INDEX(Stock!$D$8:$D$101,$J16))) | D16: =IF($J16="","",INDEX(Stock!$J$8:$J$101,$J16)) | E16: =IF($J16="","",INDEX(Stock!$K$8:$K$101,$J16)) | F16: =+$D16/10 | G16: =IF($J16="","",IF(INDEX(Stock!$L$8:$L$101,$J16)=0,"",INDEX(Stock!$L$8:$L$101,$J16))) | H16: =IF($J16="","",INDEX(Stock!$M$8:$M$101,$J16)) | J16: =IFERROR(MATCH($A$9&"#"&6,Stock!$R$8:$R$101,0),"")
A17: =IF($J17="","",INDEX(Stock!$B$8:$B$101,$J17)) | B17: =IF($J17="","",IF(INDEX(Stock!$C$8:$C$101,$J17)=0,"",INDEX(Stock!$C$8:$C$101,$J17))) | C17: =IF($J17="","",IF(INDEX(Stock!$D$8:$D$101,$J17)=0,"",INDEX(Stock!$D$8:$D$101,$J17))) | D17: =IF($J17="","",INDEX(Stock!$J$8:$J$101,$J17)) | E17: =IF($J17="","",INDEX(Stock!$K$8:$K$101,$J17)) | F17: =+$D17/10 | G17: =IF($J17="","",IF(INDEX(Stock!$L$8:$L$101,$J17)=0,"",INDEX(Stock!$L$8:$L$101,$J17))) | H17: =IF($J17="","",INDEX(Stock!$M$8:$M$101,$J17)) | J17: =IFERROR(MATCH($A$9&"#"&7,Stock!$R$8:$R$101,0),"")
A18: =IF($J18="","",INDEX(Stock!$B$8:$B$101,$J18)) | B18: =IF($J18="","",IF(INDEX(Stock!$C$8:$C$101,$J18)=0,"",INDEX(Stock!$C$8:$C$101,$J18))) | C18: =IF($J18="","",IF(INDEX(Stock!$D$8:$D$101,$J18)=0,"",INDEX(Stock!$D$8:$D$101,$J18))) | D18: =IF($J18="","",INDEX(Stock!$J$8:$J$101,$J18)) | E18: =IF($J18="","",INDEX(Stock!$K$8:$K$101,$J18)) | F18: =+$D18/10 | G18: =IF($J18="","",IF(INDEX(Stock!$L$8:$L$101,$J18)=0,"",INDEX(Stock!$L$8:$L$101,$J18))) | H18: =IF($J18="","",INDEX(Stock!$M$8:$M$101,$J18)) | J18: =IFERROR(MATCH($A$9&"#"&8,Stock!$R$8:$R$101,0),"")
A19: =IF($J19="","",INDEX(Stock!$B$8:$B$101,$J19)) | B19: =IF($J19="","",IF(INDEX(Stock!$C$8:$C$101,$J19)=0,"",INDEX(Stock!$C$8:$C$101,$J19))) | C19: =IF($J19="","",IF(INDEX(Stock!$D$8:$D$101,$J19)=0,"",INDEX(Stock!$D$8:$D$101,$J19))) | D19: =IF($J19="","",INDEX(Stock!$J$8:$J$101,$J19)) | E19: =IF($J19="","",INDEX(Stock!$K$8:$K$101,$J19)) | G19: =IF($J19="","",IF(INDEX(Stock!$L$8:$L$101,$J19)=0,"",INDEX(Stock!$L$8:$L$101,$J19))) | H19: =IF($J19="","",INDEX(Stock!$M$8:$M$101,$J19)) | J19: =IFERROR(MATCH($A$9&"#"&9,Stock!$R$8:$R$101,0),"")
A20: =IF($J20="","",INDEX(Stock!$B$8:$B$101,$J20)) | B20: =IF($J20="","",IF(INDEX(Stock!$C$8:$C$101,$J20)=0,"",INDEX(Stock!$C$8:$C$101,$J20))) | C20: =IF($J20="","",IF(INDEX(Stock!$D$8:$D$101,$J20)=0,"",INDEX(Stock!$D$8:$D$101,$J20))) | D20: =IF($J20="","",INDEX(Stock!$J$8:$J$101,$J20)) | E20: =IF($J20="","",INDEX(Stock!$K$8:$K$101,$J20)) | G20: =IF($J20="","",IF(INDEX(Stock!$L$8:$L$101,$J20)=0,"",INDEX(Stock!$L$8:$L$101,$J20))) | H20: =IF($J20="","",INDEX(Stock!$M$8:$M$101,$J20)) | J20: =IFERROR(MATCH($A$9&"#"&10,Stock!$R$8:$R$101,0),"")
A21: =IF($J21="","",INDEX(Stock!$B$8:$B$101,$J21)) | B21: =IF($J21="","",IF(INDEX(Stock!$C$8:$C$101,$J21)=0,"",INDEX(Stock!$C$8:$C$101,$J21))) | C21: =IF($J21="","",IF(INDEX(Stock!$D$8:$D$101,$J21)=0,"",INDEX(Stock!$D$8:$D$101,$J21))) | D21: =IF($J21="","",INDEX(Stock!$J$8:$J$101,$J21)) | E21: =IF($J21="","",INDEX(Stock!$K$8:$K$101,$J21)) | G21: =IF($J21="","",IF(INDEX(Stock!$L$8:$L$101,$J21)=0,"",INDEX(Stock!$L$8:$L$101,$J21))) | H21: =IF($J21="","",INDEX(Stock!$M$8:$M$101,$J21)) | J21: =IFERROR(MATCH($A$9&"#"&11,Stock!$R$8:$R$101,0),"")
A22: =IF($A$9="","",$A$9&" total") | D22: =SUM(D11:D21) | E22: =SUM(E11:E21) | F22: =SUM(F11:F21) | H22: =SUM(H11:H21)
A24: Primus Japan
A25: Product | B25: Unit | C25: Kg / Unit | D25: Closing Balance | E25: Closing Stock (Kg) | F25: No. of Cases | G25: Rate / Kg ($) | H25: Stock Value (₹)
A26: =IF($J26="","",INDEX(Stock!$B$8:$B$101,$J26)) | B26: =IF($J26="","",IF(INDEX(Stock!$C$8:$C$101,$J26)=0,"",INDEX(Stock!$C$8:$C$101,$J26))) | C26: =IF($J26="","",IF(INDEX(Stock!$D$8:$D$101,$J26)=0,"",INDEX(Stock!$D$8:$D$101,$J26))) | D26: =IF($J26="","",INDEX(Stock!$J$8:$J$101,$J26)) | E26: =IF($J26="","",INDEX(Stock!$K$8:$K$101,$J26)) | F26: =+$D26/10 | G26: =IF($J26="","",IF(INDEX(Stock!$L$8:$L$101,$J26)=0,"",INDEX(Stock!$L$8:$L$101,$J26))) | H26: =IF($J26="","",INDEX(Stock!$M$8:$M$101,$J26)) | J26: =IFERROR(MATCH($A$24&"#"&1,Stock!$R$8:$R$101,0),"")
A27: =IF($J27="","",INDEX(Stock!$B$8:$B$101,$J27)) | B27: =IF($J27="","",IF(INDEX(Stock!$C$8:$C$101,$J27)=0,"",INDEX(Stock!$C$8:$C$101,$J27))) | C27: =IF($J27="","",IF(INDEX(Stock!$D$8:$D$101,$J27)=0,"",INDEX(Stock!$D$8:$D$101,$J27))) | D27: =IF($J27="","",INDEX(Stock!$J$8:$J$101,$J27)) | E27: =IF($J27="","",INDEX(Stock!$K$8:$K$101,$J27)) | F27: =+$D27/10 | G27: =IF($J27="","",IF(INDEX(Stock!$L$8:$L$101,$J27)=0,"",INDEX(Stock!$L$8:$L$101,$J27))) | H27: =IF($J27="","",INDEX(Stock!$M$8:$M$101,$J27)) | J27: =IFERROR(MATCH($A$24&"#"&2,Stock!$R$8:$R$101,0),"")
A28: =IF($J28="","",INDEX(Stock!$B$8:$B$101,$J28)) | B28: =IF($J28="","",IF(INDEX(Stock!$C$8:$C$101,$J28)=0,"",INDEX(Stock!$C$8:$C$101,$J28))) | C28: =IF($J28="","",IF(INDEX(Stock!$D$8:$D$101,$J28)=0,"",INDEX(Stock!$D$8:$D$101,$J28))) | D28: =IF($J28="","",INDEX(Stock!$J$8:$J$101,$J28)) | E28: =IF($J28="","",INDEX(Stock!$K$8:$K$101,$J28)) | F28: =+$D28/10 | G28: =IF($J28="","",IF(INDEX(Stock!$L$8:$L$101,$J28)=0,"",INDEX(Stock!$L$8:$L$101,$J28))) | H28: =IF($J28="","",INDEX(Stock!$M$8:$M$101,$J28)) | J28: =IFERROR(MATCH($A$24&"#"&3,Stock!$R$8:$R$101,0),"")
A29: =IF($J29="","",INDEX(Stock!$B$8:$B$101,$J29)) | B29: =IF($J29="","",IF(INDEX(Stock!$C$8:$C$101,$J29)=0,"",INDEX(Stock!$C$8:$C$101,$J29))) | C29: =IF($J29="","",IF(INDEX(Stock!$D$8:$D$101,$J29)=0,"",INDEX(Stock!$D$8:$D$101,$J29))) | D29: =IF($J29="","",INDEX(Stock!$J$8:$J$101,$J29)) | E29: =IF($J29="","",INDEX(Stock!$K$8:$K$101,$J29)) | F29: =+$D29/10 | G29: =IF($J29="","",IF(INDEX(Stock!$L$8:$L$101,$J29)=0,"",INDEX(Stock!$L$8:$L$101,$J29))) | H29: =IF($J29="","",INDEX(Stock!$M$8:$M$101,$J29)) | J29: =IFERROR(MATCH($A$24&"#"&4,Stock!$R$8:$R$101,0),"")
A30: =IF($J30="","",INDEX(Stock!$B$8:$B$101,$J30)) | B30: =IF($J30="","",IF(INDEX(Stock!$C$8:$C$101,$J30)=0,"",INDEX(Stock!$C$8:$C$101,$J30))) | C30: =IF($J30="","",IF(INDEX(Stock!$D$8:$D$101,$J30)=0,"",INDEX(Stock!$D$8:$D$101,$J30))) | D30: =IF($J30="","",INDEX(Stock!$J$8:$J$101,$J30)) | E30: =IF($J30="","",INDEX(Stock!$K$8:$K$101,$J30)) | F30: =+$D30/10 | G30: =IF($J30="","",IF(INDEX(Stock!$L$8:$L$101,$J30)=0,"",INDEX(Stock!$L$8:$L$101,$J30))) | H30: =IF($J30="","",INDEX(Stock!$M$8:$M$101,$J30)) | J30: =IFERROR(MATCH($A$24&"#"&5,Stock!$R$8:$R$101,0),"")
A31: =IF($J31="","",INDEX(Stock!$B$8:$B$101,$J31)) | B31: =IF($J31="","",IF(INDEX(Stock!$C$8:$C$101,$J31)=0,"",INDEX(Stock!$C$8:$C$101,$J31))) | C31: =IF($J31="","",IF(INDEX(Stock!$D$8:$D$101,$J31)=0,"",INDEX(Stock!$D$8:$D$101,$J31))) | D31: =IF($J31="","",INDEX(Stock!$J$8:$J$101,$J31)) | E31: =IF($J31="","",INDEX(Stock!$K$8:$K$101,$J31)) | F31: =+$D31/10 | G31: =IF($J31="","",IF(INDEX(Stock!$L$8:$L$101,$J31)=0,"",INDEX(Stock!$L$8:$L$101,$J31))) | H31: =IF($J31="","",INDEX(Stock!$M$8:$M$101,$J31)) | J31: =IFERROR(MATCH($A$24&"#"&6,Stock!$R$8:$R$101,0),"")
A32: =IF($J32="","",INDEX(Stock!$B$8:$B$101,$J32)) | B32: =IF($J32="","",IF(INDEX(Stock!$C$8:$C$101,$J32)=0,"",INDEX(Stock!$C$8:$C$101,$J32))) | C32: =IF($J32="","",IF(INDEX(Stock!$D$8:$D$101,$J32)=0,"",INDEX(Stock!$D$8:$D$101,$J32))) | D32: =IF($J32="","",INDEX(Stock!$J$8:$J$101,$J32)) | E32: =IF($J32="","",INDEX(Stock!$K$8:$K$101,$J32)) | F32: =+$D32/10 | G32: =IF($J32="","",IF(INDEX(Stock!$L$8:$L$101,$J32)=0,"",INDEX(Stock!$L$8:$L$101,$J32))) | H32: =IF($J32="","",INDEX(Stock!$M$8:$M$101,$J32)) | J32: =IFERROR(MATCH($A$24&"#"&7,Stock!$R$8:$R$101,0),"")
A33: =IF($J33="","",INDEX(Stock!$B$8:$B$101,$J33)) | B33: =IF($J33="","",IF(INDEX(Stock!$C$8:$C$101,$J33)=0,"",INDEX(Stock!$C$8:$C$101,$J33))) | C33: =IF($J33="","",IF(INDEX(Stock!$D$8:$D$101,$J33)=0,"",INDEX(Stock!$D$8:$D$101,$J33))) | D33: =IF($J33="","",INDEX(Stock!$J$8:$J$101,$J33)) | E33: =IF($J33="","",INDEX(Stock!$K$8:$K$101,$J33)) | F33: =+$D33/10 | G33: =IF($J33="","",IF(INDEX(Stock!$L$8:$L$101,$J33)=0,"",INDEX(Stock!$L$8:$L$101,$J33))) | H33: =IF($J33="","",INDEX(Stock!$M$8:$M$101,$J33)) | J33: =IFERROR(MATCH($A$24&"#"&8,Stock!$R$8:$R$101,0),"")
A34: =IF($J34="","",INDEX(Stock!$B$8:$B$101,$J34)) | B34: =IF($J34="","",IF(INDEX(Stock!$C$8:$C$101,$J34)=0,"",INDEX(Stock!$C$8:$C$101,$J34))) | C34: =IF($J34="","",IF(INDEX(Stock!$D$8:$D$101,$J34)=0,"",INDEX(Stock!$D$8:$D$101,$J34))) | D34: =IF($J34="","",INDEX(Stock!$J$8:$J$101,$J34)) | E34: =IF($J34="","",INDEX(Stock!$K$8:$K$101,$J34)) | F34: =+$D34/10 | G34: =IF($J34="","",IF(INDEX(Stock!$L$8:$L$101,$J34)=0,"",INDEX(Stock!$L$8:$L$101,$J34))) | H34: =IF($J34="","",INDEX(Stock!$M$8:$M$101,$J34)) | J34: =IFERROR(MATCH($A$24&"#"&9,Stock!$R$8:$R$101,0),"")
A35: =IF($J35="","",INDEX(Stock!$B$8:$B$101,$J35)) | B35: =IF($J35="","",IF(INDEX(Stock!$C$8:$C$101,$J35)=0,"",INDEX(Stock!$C$8:$C$101,$J35))) | C35: =IF($J35="","",IF(INDEX(Stock!$D$8:$D$101,$J35)=0,"",INDEX(Stock!$D$8:$D$101,$J35))) | D35: =IF($J35="","",INDEX(Stock!$J$8:$J$101,$J35)) | E35: =IF($J35="","",INDEX(Stock!$K$8:$K$101,$J35)) | F35: =+$D35/10 | G35: =IF($J35="","",IF(INDEX(Stock!$L$8:$L$101,$J35)=0,"",INDEX(Stock!$L$8:$L$101,$J35))) | H35: =IF($J35="","",INDEX(Stock!$M$8:$M$101,$J35)) | J35: =IFERROR(MATCH($A$24&"#"&10,Stock!$R$8:$R$101,0),"")
A36: =IF($J36="","",INDEX(Stock!$B$8:$B$101,$J36)) | B36: =IF($J36="","",IF(INDEX(Stock!$C$8:$C$101,$J36)=0,"",INDEX(Stock!$C$8:$C$101,$J36))) | C36: =IF($J36="","",IF(INDEX(Stock!$D$8:$D$101,$J36)=0,"",INDEX(Stock!$D$8:$D$101,$J36))) | D36: =IF($J36="","",INDEX(Stock!$J$8:$J$101,$J36)) | E36: =IF($J36="","",INDEX(Stock!$K$8:$K$101,$J36)) | F36: =+$D36/10 | G36: =IF($J36="","",IF(INDEX(Stock!$L$8:$L$101,$J36)=0,"",INDEX(Stock!$L$8:$L$101,$J36))) | H36: =IF($J36="","",INDEX(Stock!$M$8:$M$101,$J36)) | J36: =IFERROR(MATCH($A$24&"#"&11,Stock!$R$8:$R$101,0),"")
A37: =IF($J37="","",INDEX(Stock!$B$8:$B$101,$J37)) | B37: =IF($J37="","",IF(INDEX(Stock!$C$8:$C$101,$J37)=0,"",INDEX(Stock!$C$8:$C$101,$J37))) | C37: =IF($J37="","",IF(INDEX(Stock!$D$8:$D$101,$J37)=0,"",INDEX(Stock!$D$8:$D$101,$J37))) | D37: =IF($J37="","",INDEX(Stock!$J$8:$J$101,$J37)) | E37: =IF($J37="","",INDEX(Stock!$K$8:$K$101,$J37)) | F37: =+$D37/10 | G37: =IF($J37="","",IF(INDEX(Stock!$L$8:$L$101,$J37)=0,"",INDEX(Stock!$L$8:$L$101,$J37))) | H37: =IF($J37="","",INDEX(Stock!$M$8:$M$101,$J37)) | J37: =IFERROR(MATCH($A$24&"#"&12,Stock!$R$8:$R$101,0),"")
A38: =IF($J38="","",INDEX(Stock!$B$8:$B$101,$J38)) | B38: =IF($J38="","",IF(INDEX(Stock!$C$8:$C$101,$J38)=0,"",INDEX(Stock!$C$8:$C$101,$J38))) | C38: =IF($J38="","",IF(INDEX(Stock!$D$8:$D$101,$J38)=0,"",INDEX(Stock!$D$8:$D$101,$J38))) | D38: =IF($J38="","",INDEX(Stock!$J$8:$J$101,$J38)) | E38: =IF($J38="","",INDEX(Stock!$K$8:$K$101,$J38)) | F38: =+$D38/10 | G38: =IF($J38="","",IF(INDEX(Stock!$L$8:$L$101,$J38)=0,"",INDEX(Stock!$L$8:$L$101,$J38))) | H38: =IF($J38="","",INDEX(Stock!$M$8:$M$101,$J38)) | J38: =IFERROR(MATCH($A$24&"#"&13,Stock!$R$8:$R$101,0),"")
A39: =IF($J39="","",INDEX(Stock!$B$8:$B$101,$J39)) | B39: =IF($J39="","",IF(INDEX(Stock!$C$8:$C$101,$J39)=0,"",INDEX(Stock!$C$8:$C$101,$J39))) | C39: =IF($J39="","",IF(INDEX(Stock!$D$8:$D$101,$J39)=0,"",INDEX(Stock!$D$8:$D$101,$J39))) | D39: =IF($J39="","",INDEX(Stock!$J$8:$J$101,$J39)) | E39: =IF($J39="","",INDEX(Stock!$K$8:$K$101,$J39)) | F39: =+$D39/10 | G39: =IF($J39="","",IF(INDEX(Stock!$L$8:$L$101,$J39)=0,"",INDEX(Stock!$L$8:$L$101,$J39))) | H39: =IF($J39="","",INDEX(Stock!$M$8:$M$101,$J39)) | J39: =IFERROR(MATCH($A$24&"#"&14,Stock!$R$8:$R$101,0),"")
A40: =IF($J40="","",INDEX(Stock!$B$8:$B$101,$J40)) | B40: =IF($J40="","",IF(INDEX(Stock!$C$8:$C$101,$J40)=0,"",INDEX(Stock!$C$8:$C$101,$J40))) | C40: =IF($J40="","",IF(INDEX(Stock!$D$8:$D$101,$J40)=0,"",INDEX(Stock!$D$8:$D$101,$J40))) | D40: =IF($J40="","",INDEX(Stock!$J$8:$J$101,$J40)) | E40: =IF($J40="","",INDEX(Stock!$K$8:$K$101,$J40)) | F40: =+$D40/10 | G40: =IF($J40="","",IF(INDEX(Stock!$L$8:$L$101,$J40)=0,"",INDEX(Stock!$L$8:$L$101,$J40))) | H40: =IF($J40="","",INDEX(Stock!$M$8:$M$101,$J40)) | J40: =IFERROR(MATCH($A$24&"#"&15,Stock!$R$8:$R$101,0),"")
A41: =IF($J41="","",INDEX(Stock!$B$8:$B$101,$J41)) | B41: =IF($J41="","",IF(INDEX(Stock!$C$8:$C$101,$J41)=0,"",INDEX(Stock!$C$8:$C$101,$J41))) | C41: =IF($J41="","",IF(INDEX(Stock!$D$8:$D$101,$J41)=0,"",INDEX(Stock!$D$8:$D$101,$J41))) | D41: =IF($J41="","",INDEX(Stock!$J$8:$J$101,$J41)) | E41: =IF($J41="","",INDEX(Stock!$K$8:$K$101,$J41)) | F41: =+$D41/10 | G41: =IF($J41="","",IF(INDEX(Stock!$L$8:$L$101,$J41)=0,"",INDEX(Stock!$L$8:$L$101,$J41))) | H41: =IF($J41="","",INDEX(Stock!$M$8:$M$101,$J41)) | J41: =IFERROR(MATCH($A$24&"#"&16,Stock!$R$8:$R$101,0),"")
A42: =IF($J42="","",INDEX(Stock!$B$8:$B$101,$J42)) | B42: =IF($J42="","",IF(INDEX(Stock!$C$8:$C$101,$J42)=0,"",INDEX(Stock!$C$8:$C$101,$J42))) | C42: =IF($J42="","",IF(INDEX(Stock!$D$8:$D$101,$J42)=0,"",INDEX(Stock!$D$8:$D$101,$J42))) | D42: =IF($J42="","",INDEX(Stock!$J$8:$J$101,$J42)) | E42: =IF($J42="","",INDEX(Stock!$K$8:$K$101,$J42)) | F42: =+$D42/10 | G42: =IF($J42="","",IF(INDEX(Stock!$L$8:$L$101,$J42)=0,"",INDEX(Stock!$L$8:$L$101,$J42))) | H42: =IF($J42="","",INDEX(Stock!$M$8:$M$101,$J42)) | J42: =IFERROR(MATCH($A$24&"#"&17,Stock!$R$8:$R$101,0),"")
A43: =IF($J43="","",INDEX(Stock!$B$8:$B$101,$J43)) | B43: =IF($J43="","",IF(INDEX(Stock!$C$8:$C$101,$J43)=0,"",INDEX(Stock!$C$8:$C$101,$J43))) | C43: =IF($J43="","",IF(INDEX(Stock!$D$8:$D$101,$J43)=0,"",INDEX(Stock!$D$8:$D$101,$J43))) | D43: =IF($J43="","",INDEX(Stock!$J$8:$J$101,$J43)) | E43: =IF($J43="","",INDEX(Stock!$K$8:$K$101,$J43)) | F43: =+$D43/10 | G43: =IF($J43="","",IF(INDEX(Stock!$L$8:$L$101,$J43)=0,"",INDEX(Stock!$L$8:$L$101,$J43))) | H43: =IF($J43="","",INDEX(Stock!$M$8:$M$101,$J43)) | J43: =IFERROR(MATCH($A$24&"#"&18,Stock!$R$8:$R$101,0),"")
A44: =IF($J44="","",INDEX(Stock!$B$8:$B$101,$J44)) | B44: =IF($J44="","",IF(INDEX(Stock!$C$8:$C$101,$J44)=0,"",INDEX(Stock!$C$8:$C$101,$J44))) | C44: =IF($J44="","",IF(INDEX(Stock!$D$8:$D$101,$J44)=0,"",INDEX(Stock!$D$8:$D$101,$J44))) | D44: =IF($J44="","",INDEX(Stock!$J$8:$J$101,$J44)) | E44: =IF($J44="","",INDEX(Stock!$K$8:$K$101,$J44)) | F44: =+$D44/10 | G44: =IF($J44="","",IF(INDEX(Stock!$L$8:$L$101,$J44)=0,"",INDEX(Stock!$L$8:$L$101,$J44))) | H44: =IF($J44="","",INDEX(Stock!$M$8:$M$101,$J44)) | J44: =IFERROR(MATCH($A$24&"#"&19,Stock!$R$8:$R$101,0),"")
A45: =IF($J45="","",INDEX(Stock!$B$8:$B$101,$J45)) | B45: =IF($J45="","",IF(INDEX(Stock!$C$8:$C$101,$J45)=0,"",INDEX(Stock!$C$8:$C$101,$J45))) | C45: =IF($J45="","",IF(INDEX(Stock!$D$8:$D$101,$J45)=0,"",INDEX(Stock!$D$8:$D$101,$J45))) | D45: =IF($J45="","",INDEX(Stock!$J$8:$J$101,$J45)) | E45: =IF($J45="","",INDEX(Stock!$K$8:$K$101,$J45)) | G45: =IF($J45="","",IF(INDEX(Stock!$L$8:$L$101,$J45)=0,"",INDEX(Stock!$L$8:$L$101,$J45))) | H45: =IF($J45="","",INDEX(Stock!$M$8:$M$101,$J45)) | J45: =IFERROR(MATCH($A$24&"#"&20,Stock!$R$8:$R$101,0),"")
A46: =IF($J46="","",INDEX(Stock!$B$8:$B$101,$J46)) | B46: =IF($J46="","",IF(INDEX(Stock!$C$8:$C$101,$J46)=0,"",INDEX(Stock!$C$8:$C$101,$J46))) | C46: =IF($J46="","",IF(INDEX(Stock!$D$8:$D$101,$J46)=0,"",INDEX(Stock!$D$8:$D$101,$J46))) | D46: =IF($J46="","",INDEX(Stock!$J$8:$J$101,$J46)) | E46: =IF($J46="","",INDEX(Stock!$K$8:$K$101,$J46)) | G46: =IF($J46="","",IF(INDEX(Stock!$L$8:$L$101,$J46)=0,"",INDEX(Stock!$L$8:$L$101,$J46))) | H46: =IF($J46="","",INDEX(Stock!$M$8:$M$101,$J46)) | J46: =IFERROR(MATCH($A$24&"#"&21,Stock!$R$8:$R$101,0),"")
A47: =IF($J47="","",INDEX(Stock!$B$8:$B$101,$J47)) | B47: =IF($J47="","",IF(INDEX(Stock!$C$8:$C$101,$J47)=0,"",INDEX(Stock!$C$8:$C$101,$J47))) | C47: =IF($J47="","",IF(INDEX(Stock!$D$8:$D$101,$J47)=0,"",INDEX(Stock!$D$8:$D$101,$J47))) | D47: =IF($J47="","",INDEX(Stock!$J$8:$J$101,$J47)) | E47: =IF($J47="","",INDEX(Stock!$K$8:$K$101,$J47)) | G47: =IF($J47="","",IF(INDEX(Stock!$L$8:$L$101,$J47)=0,"",INDEX(Stock!$L$8:$L$101,$J47))) | H47: =IF($J47="","",INDEX(Stock!$M$8:$M$101,$J47)) | J47: =IFERROR(MATCH($A$24&"#"&22,Stock!$R$8:$R$101,0),"")
A48: =IF($A$24="","",$A$24&" total") | D48: =SUM(D26:D47) | E48: =SUM(E26:E47) | F48: =SUM(F26:F47) | H48: =SUM(H26:H47)
A50: Primus EU
A51: Product | B51: Unit | C51: Kg / Unit | D51: Closing Balance | E51: Closing Stock (Kg) | F51: No. of Cases | G51: Rate / Kg ($) | H51: Stock Value (₹)
A52: =IF($J52="","",INDEX(Stock!$B$8:$B$101,$J52)) | B52: =IF($J52="","",IF(INDEX(Stock!$C$8:$C$101,$J52)=0,"",INDEX(Stock!$C$8:$C$101,$J52))) | C52: =IF($J52="","",IF(INDEX(Stock!$D$8:$D$101,$J52)=0,"",INDEX(Stock!$D$8:$D$101,$J52))) | D52: =IF($J52="","",INDEX(Stock!$J$8:$J$101,$J52)) | E52: =IF($J52="","",INDEX(Stock!$K$8:$K$101,$J52)) | F52: =+$D52/10 | G52: =IF($J52="","",IF(INDEX(Stock!$L$8:$L$101,$J52)=0,"",INDEX(Stock!$L$8:$L$101,$J52))) | H52: =IF($J52="","",INDEX(Stock!$M$8:$M$101,$J52)) | J52: =IFERROR(MATCH($A$50&"#"&1,Stock!$R$8:$R$101,0),"")
A53: =IF($J53="","",INDEX(Stock!$B$8:$B$101,$J53)) | B53: =IF($J53="","",IF(INDEX(Stock!$C$8:$C$101,$J53)=0,"",INDEX(Stock!$C$8:$C$101,$J53))) | C53: =IF($J53="","",IF(INDEX(Stock!$D$8:$D$101,$J53)=0,"",INDEX(Stock!$D$8:$D$101,$J53))) | D53: =IF($J53="","",INDEX(Stock!$J$8:$J$101,$J53)) | E53: =IF($J53="","",INDEX(Stock!$K$8:$K$101,$J53)) | F53: =+$D53/10 | G53: =IF($J53="","",IF(INDEX(Stock!$L$8:$L$101,$J53)=0,"",INDEX(Stock!$L$8:$L$101,$J53))) | H53: =IF($J53="","",INDEX(Stock!$M$8:$M$101,$J53)) | J53: =IFERROR(MATCH($A$50&"#"&2,Stock!$R$8:$R$101,0),"")
A54: =IF($J54="","",INDEX(Stock!$B$8:$B$101,$J54)) | B54: =IF($J54="","",IF(INDEX(Stock!$C$8:$C$101,$J54)=0,"",INDEX(Stock!$C$8:$C$101,$J54))) | C54: =IF($J54="","",IF(INDEX(Stock!$D$8:$D$101,$J54)=0,"",INDEX(Stock!$D$8:$D$101,$J54))) | D54: =IF($J54="","",INDEX(Stock!$J$8:$J$101,$J54)) | E54: =IF($J54="","",INDEX(Stock!$K$8:$K$101,$J54)) | F54: =+$D54/10 | G54: =IF($J54="","",IF(INDEX(Stock!$L$8:$L$101,$J54)=0,"",INDEX(Stock!$L$8:$L$101,$J54))) | H54: =IF($J54="","",INDEX(Stock!$M$8:$M$101,$J54)) | J54: =IFERROR(MATCH($A$50&"#"&3,Stock!$R$8:$R$101,0),"")
A55: =IF($J55="","",INDEX(Stock!$B$8:$B$101,$J55)) | B55: =IF($J55="","",IF(INDEX(Stock!$C$8:$C$101,$J55)=0,"",INDEX(Stock!$C$8:$C$101,$J55))) | C55: =IF($J55="","",IF(INDEX(Stock!$D$8:$D$101,$J55)=0,"",INDEX(Stock!$D$8:$D$101,$J55))) | D55: =IF($J55="","",INDEX(Stock!$J$8:$J$101,$J55)) | E55: =IF($J55="","",INDEX(Stock!$K$8:$K$101,$J55)) | F55: =+$D55/10 | G55: =IF($J55="","",IF(INDEX(Stock!$L$8:$L$101,$J55)=0,"",INDEX(Stock!$L$8:$L$101,$J55))) | H55: =IF($J55="","",INDEX(Stock!$M$8:$M$101,$J55)) | J55: =IFERROR(MATCH($A$50&"#"&4,Stock!$R$8:$R$101,0),"")
A56: =IF($J56="","",INDEX(Stock!$B$8:$B$101,$J56)) | B56: =IF($J56="","",IF(INDEX(Stock!$C$8:$C$101,$J56)=0,"",INDEX(Stock!$C$8:$C$101,$J56))) | C56: =IF($J56="","",IF(INDEX(Stock!$D$8:$D$101,$J56)=0,"",INDEX(Stock!$D$8:$D$101,$J56))) | D56: =IF($J56="","",INDEX(Stock!$J$8:$J$101,$J56)) | E56: =IF($J56="","",INDEX(Stock!$K$8:$K$101,$J56)) | F56: =+$D56/10 | G56: =IF($J56="","",IF(INDEX(Stock!$L$8:$L$101,$J56)=0,"",INDEX(Stock!$L$8:$L$101,$J56))) | H56: =IF($J56="","",INDEX(Stock!$M$8:$M$101,$J56)) | J56: =IFERROR(MATCH($A$50&"#"&5,Stock!$R$8:$R$101,0),"")
A57: =IF($J57="","",INDEX(Stock!$B$8:$B$101,$J57)) | B57: =IF($J57="","",IF(INDEX(Stock!$C$8:$C$101,$J57)=0,"",INDEX(Stock!$C$8:$C$101,$J57))) | C57: =IF($J57="","",IF(INDEX(Stock!$D$8:$D$101,$J57)=0,"",INDEX(Stock!$D$8:$D$101,$J57))) | D57: =IF($J57="","",INDEX(Stock!$J$8:$J$101,$J57)) | E57: =IF($J57="","",INDEX(Stock!$K$8:$K$101,$J57)) | F57: =+$D57/10 | G57: =IF($J57="","",IF(INDEX(Stock!$L$8:$L$101,$J57)=0,"",INDEX(Stock!$L$8:$L$101,$J57))) | H57: =IF($J57="","",INDEX(Stock!$M$8:$M$101,$J57)) | J57: =IFERROR(MATCH($A$50&"#"&6,Stock!$R$8:$R$101,0),"")
A58: =IF($J58="","",INDEX(Stock!$B$8:$B$101,$J58)) | B58: =IF($J58="","",IF(INDEX(Stock!$C$8:$C$101,$J58)=0,"",INDEX(Stock!$C$8:$C$101,$J58))) | C58: =IF($J58="","",IF(INDEX(Stock!$D$8:$D$101,$J58)=0,"",INDEX(Stock!$D$8:$D$101,$J58))) | D58: =IF($J58="","",INDEX(Stock!$J$8:$J$101,$J58)) | E58: =IF($J58="","",INDEX(Stock!$K$8:$K$101,$J58)) | F58: =+$D58/10 | G58: =IF($J58="","",IF(INDEX(Stock!$L$8:$L$101,$J58)=0,"",INDEX(Stock!$L$8:$L$101,$J58))) | H58: =IF($J58="","",INDEX(Stock!$M$8:$M$101,$J58)) | J58: =IFERROR(MATCH($A$50&"#"&7,Stock!$R$8:$R$101,0),"")
A59: =IF($J59="","",INDEX(Stock!$B$8:$B$101,$J59)) | B59: =IF($J59="","",IF(INDEX(Stock!$C$8:$C$101,$J59)=0,"",INDEX(Stock!$C$8:$C$101,$J59))) | C59: =IF($J59="","",IF(INDEX(Stock!$D$8:$D$101,$J59)=0,"",INDEX(Stock!$D$8:$D$101,$J59))) | D59: =IF($J59="","",INDEX(Stock!$J$8:$J$101,$J59)) | E59: =IF($J59="","",INDEX(Stock!$K$8:$K$101,$J59)) | F59: =+$D59/10 | G59: =IF($J59="","",IF(INDEX(Stock!$L$8:$L$101,$J59)=0,"",INDEX(Stock!$L$8:$L$101,$J59))) | H59: =IF($J59="","",INDEX(Stock!$M$8:$M$101,$J59)) | J59: =IFERROR(MATCH($A$50&"#"&8,Stock!$R$8:$R$101,0),"")
A60: =IF($J60="","",INDEX(Stock!$B$8:$B$101,$J60)) | B60: =IF($J60="","",IF(INDEX(Stock!$C$8:$C$101,$J60)=0,"",INDEX(Stock!$C$8:$C$101,$J60))) | C60: =IF($J60="","",IF(INDEX(Stock!$D$8:$D$101,$J60)=0,"",INDEX(Stock!$D$8:$D$101,$J60))) | D60: =IF($J60="","",INDEX(Stock!$J$8:$J$101,$J60)) | E60: =IF($J60="","",INDEX(Stock!$K$8:$K$101,$J60)) | G60: =IF($J60="","",IF(INDEX(Stock!$L$8:$L$101,$J60)=0,"",INDEX(Stock!$L$8:$L$101,$J60))) | H60: =IF($J60="","",INDEX(Stock!$M$8:$M$101,$J60)) | J60: =IFERROR(MATCH($A$50&"#"&9,Stock!$R$8:$R$101,0),"")
A61: =IF($J61="","",INDEX(Stock!$B$8:$B$101,$J61)) | B61: =IF($J61="","",IF(INDEX(Stock!$C$8:$C$101,$J61)=0,"",INDEX(Stock!$C$8:$C$101,$J61))) | C61: =IF($J61="","",IF(INDEX(Stock!$D$8:$D$101,$J61)=0,"",INDEX(Stock!$D$8:$D$101,$J61))) | D61: =IF($J61="","",INDEX(Stock!$J$8:$J$101,$J61)) | E61: =IF($J61="","",INDEX(Stock!$K$8:$K$101,$J61)) | G61: =IF($J61="","",IF(INDEX(Stock!$L$8:$L$101,$J61)=0,"",INDEX(Stock!$L$8:$L$101,$J61))) | H61: =IF($J61="","",INDEX(Stock!$M$8:$M$101,$J61)) | J61: =IFERROR(MATCH($A$50&"#"&10,Stock!$R$8:$R$101,0),"")
A62: =IF($J62="","",INDEX(Stock!$B$8:$B$101,$J62)) | B62: =IF($J62="","",IF(INDEX(Stock!$C$8:$C$101,$J62)=0,"",INDEX(Stock!$C$8:$C$101,$J62))) | C62: =IF($J62="","",IF(INDEX(Stock!$D$8:$D$101,$J62)=0,"",INDEX(Stock!$D$8:$D$101,$J62))) | D62: =IF($J62="","",INDEX(Stock!$J$8:$J$101,$J62)) | E62: =IF($J62="","",INDEX(Stock!$K$8:$K$101,$J62)) | G62: =IF($J62="","",IF(INDEX(Stock!$L$8:$L$101,$J62)=0,"",INDEX(Stock!$L$8:$L$101,$J62))) | H62: =IF($J62="","",INDEX(Stock!$M$8:$M$101,$J62)) | J62: =IFERROR(MATCH($A$50&"#"&11,Stock!$R$8:$R$101,0),"")
A63: =IF($A$50="","",$A$50&" total") | D63: =SUM(D52:D62) | E63: =SUM(E52:E62) | F63: =SUM(F52:F62) | H63: =SUM(H52:H62)
A65: AMF Brand
A66: Product | B66: Unit | C66: Kg / Unit | D66: Closing Balance | E66: Closing Stock (Kg) | F66: No. of Cases | G66: Rate / Kg ($) | H66: Stock Value (₹)
A67: =IF($J67="","",INDEX(Stock!$B$8:$B$101,$J67)) | B67: =IF($J67="","",IF(INDEX(Stock!$C$8:$C$101,$J67)=0,"",INDEX(Stock!$C$8:$C$101,$J67))) | C67: =IF($J67="","",IF(INDEX(Stock!$D$8:$D$101,$J67)=0,"",INDEX(Stock!$D$8:$D$101,$J67))) | D67: =IF($J67="","",INDEX(Stock!$J$8:$J$101,$J67)) | E67: =IF($J67="","",INDEX(Stock!$K$8:$K$101,$J67)) | F67: =+$D67/10 | G67: =IF($J67="","",IF(INDEX(Stock!$L$8:$L$101,$J67)=0,"",INDEX(Stock!$L$8:$L$101,$J67))) | H67: =IF($J67="","",INDEX(Stock!$M$8:$M$101,$J67)) | J67: =IFERROR(MATCH($A$65&"#"&1,Stock!$R$8:$R$101,0),"")
A68: =IF($J68="","",INDEX(Stock!$B$8:$B$101,$J68)) | B68: =IF($J68="","",IF(INDEX(Stock!$C$8:$C$101,$J68)=0,"",INDEX(Stock!$C$8:$C$101,$J68))) | C68: =IF($J68="","",IF(INDEX(Stock!$D$8:$D$101,$J68)=0,"",INDEX(Stock!$D$8:$D$101,$J68))) | D68: =IF($J68="","",INDEX(Stock!$J$8:$J$101,$J68)) | E68: =IF($J68="","",INDEX(Stock!$K$8:$K$101,$J68)) | F68: =+$D68/10 | G68: =IF($J68="","",IF(INDEX(Stock!$L$8:$L$101,$J68)=0,"",INDEX(Stock!$L$8:$L$101,$J68))) | H68: =IF($J68="","",INDEX(Stock!$M$8:$M$101,$J68)) | J68: =IFERROR(MATCH($A$65&"#"&2,Stock!$R$8:$R$101,0),"")
A69: =IF($J69="","",INDEX(Stock!$B$8:$B$101,$J69)) | B69: =IF($J69="","",IF(INDEX(Stock!$C$8:$C$101,$J69)=0,"",INDEX(Stock!$C$8:$C$101,$J69))) | C69: =IF($J69="","",IF(INDEX(Stock!$D$8:$D$101,$J69)=0,"",INDEX(Stock!$D$8:$D$101,$J69))) | D69: =IF($J69="","",INDEX(Stock!$J$8:$J$101,$J69)) | E69: =IF($J69="","",INDEX(Stock!$K$8:$K$101,$J69)) | F69: =+$D69/10 | G69: =IF($J69="","",IF(INDEX(Stock!$L$8:$L$101,$J69)=0,"",INDEX(Stock!$L$8:$L$101,$J69))) | H69: =IF($J69="","",INDEX(Stock!$M$8:$M$101,$J69)) | J69: =IFERROR(MATCH($A$65&"#"&3,Stock!$R$8:$R$101,0),"")
A70: =IF($J70="","",INDEX(Stock!$B$8:$B$101,$J70)) | B70: =IF($J70="","",IF(INDEX(Stock!$C$8:$C$101,$J70)=0,"",INDEX(Stock!$C$8:$C$101,$J70))) | C70: =IF($J70="","",IF(INDEX(Stock!$D$8:$D$101,$J70)=0,"",INDEX(Stock!$D$8:$D$101,$J70))) | D70: =IF($J70="","",INDEX(Stock!$J$8:$J$101,$J70)) | E70: =IF($J70="","",INDEX(Stock!$K$8:$K$101,$J70)) | F70: =+$D70/10 | G70: =IF($J70="","",IF(INDEX(Stock!$L$8:$L$101,$J70)=0,"",INDEX(Stock!$L$8:$L$101,$J70))) | H70: =IF($J70="","",INDEX(Stock!$M$8:$M$101,$J70)) | J70: =IFERROR(MATCH($A$65&"#"&4,Stock!$R$8:$R$101,0),"")
A71: =IF($J71="","",INDEX(Stock!$B$8:$B$101,$J71)) | B71: =IF($J71="","",IF(INDEX(Stock!$C$8:$C$101,$J71)=0,"",INDEX(Stock!$C$8:$C$101,$J71))) | C71: =IF($J71="","",IF(INDEX(Stock!$D$8:$D$101,$J71)=0,"",INDEX(Stock!$D$8:$D$101,$J71))) | D71: =IF($J71="","",INDEX(Stock!$J$8:$J$101,$J71)) | E71: =IF($J71="","",INDEX(Stock!$K$8:$K$101,$J71)) | F71: =+$D71/10 | G71: =IF($J71="","",IF(INDEX(Stock!$L$8:$L$101,$J71)=0,"",INDEX(Stock!$L$8:$L$101,$J71))) | H71: =IF($J71="","",INDEX(Stock!$M$8:$M$101,$J71)) | J71: =IFERROR(MATCH($A$65&"#"&5,Stock!$R$8:$R$101,0),"")
A72: =IF($J72="","",INDEX(Stock!$B$8:$B$101,$J72)) | B72: =IF($J72="","",IF(INDEX(Stock!$C$8:$C$101,$J72)=0,"",INDEX(Stock!$C$8:$C$101,$J72))) | C72: =IF($J72="","",IF(INDEX(Stock!$D$8:$D$101,$J72)=0,"",INDEX(Stock!$D$8:$D$101,$J72))) | D72: =IF($J72="","",INDEX(Stock!$J$8:$J$101,$J72)) | E72: =IF($J72="","",INDEX(Stock!$K$8:$K$101,$J72)) | F72: =+$D72/10 | G72: =IF($J72="","",IF(INDEX(Stock!$L$8:$L$101,$J72)=0,"",INDEX(Stock!$L$8:$L$101,$J72))) | H72: =IF($J72="","",INDEX(Stock!$M$8:$M$101,$J72)) | J72: =IFERROR(MATCH($A$65&"#"&6,Stock!$R$8:$R$101,0),"")
A73: =IF($J73="","",INDEX(Stock!$B$8:$B$101,$J73)) | B73: =IF($J73="","",IF(INDEX(Stock!$C$8:$C$101,$J73)=0,"",INDEX(Stock!$C$8:$C$101,$J73))) | C73: =IF($J73="","",IF(INDEX(Stock!$D$8:$D$101,$J73)=0,"",INDEX(Stock!$D$8:$D$101,$J73))) | D73: =IF($J73="","",INDEX(Stock!$J$8:$J$101,$J73)) | E73: =IF($J73="","",INDEX(Stock!$K$8:$K$101,$J73)) | F73: =+$D73/10 | G73: =IF($J73="","",IF(INDEX(Stock!$L$8:$L$101,$J73)=0,"",INDEX(Stock!$L$8:$L$101,$J73))) | H73: =IF($J73="","",INDEX(Stock!$M$8:$M$101,$J73)) | J73: =IFERROR(MATCH($A$65&"#"&7,Stock!$R$8:$R$101,0),"")
A74: =IF($J74="","",INDEX(Stock!$B$8:$B$101,$J74)) | B74: =IF($J74="","",IF(INDEX(Stock!$C$8:$C$101,$J74)=0,"",INDEX(Stock!$C$8:$C$101,$J74))) | C74: =IF($J74="","",IF(INDEX(Stock!$D$8:$D$101,$J74)=0,"",INDEX(Stock!$D$8:$D$101,$J74))) | D74: =IF($J74="","",INDEX(Stock!$J$8:$J$101,$J74)) | E74: =IF($J74="","",INDEX(Stock!$K$8:$K$101,$J74)) | F74: =+$D74/10 | G74: =IF($J74="","",IF(INDEX(Stock!$L$8:$L$101,$J74)=0,"",INDEX(Stock!$L$8:$L$101,$J74))) | H74: =IF($J74="","",INDEX(Stock!$M$8:$M$101,$J74)) | J74: =IFERROR(MATCH($A$65&"#"&8,Stock!$R$8:$R$101,0),"")
A75: =IF($J75="","",INDEX(Stock!$B$8:$B$101,$J75)) | B75: =IF($J75="","",IF(INDEX(Stock!$C$8:$C$101,$J75)=0,"",INDEX(Stock!$C$8:$C$101,$J75))) | C75: =IF($J75="","",IF(INDEX(Stock!$D$8:$D$101,$J75)=0,"",INDEX(Stock!$D$8:$D$101,$J75))) | D75: =IF($J75="","",INDEX(Stock!$J$8:$J$101,$J75)) | E75: =IF($J75="","",INDEX(Stock!$K$8:$K$101,$J75)) | G75: =IF($J75="","",IF(INDEX(Stock!$L$8:$L$101,$J75)=0,"",INDEX(Stock!$L$8:$L$101,$J75))) | H75: =IF($J75="","",INDEX(Stock!$M$8:$M$101,$J75)) | J75: =IFERROR(MATCH($A$65&"#"&9,Stock!$R$8:$R$101,0),"")
A76: =IF($J76="","",INDEX(Stock!$B$8:$B$101,$J76)) | B76: =IF($J76="","",IF(INDEX(Stock!$C$8:$C$101,$J76)=0,"",INDEX(Stock!$C$8:$C$101,$J76))) | C76: =IF($J76="","",IF(INDEX(Stock!$D$8:$D$101,$J76)=0,"",INDEX(Stock!$D$8:$D$101,$J76))) | D76: =IF($J76="","",INDEX(Stock!$J$8:$J$101,$J76)) | E76: =IF($J76="","",INDEX(Stock!$K$8:$K$101,$J76)) | G76: =IF($J76="","",IF(INDEX(Stock!$L$8:$L$101,$J76)=0,"",INDEX(Stock!$L$8:$L$101,$J76))) | H76: =IF($J76="","",INDEX(Stock!$M$8:$M$101,$J76)) | J76: =IFERROR(MATCH($A$65&"#"&10,Stock!$R$8:$R$101,0),"")
A77: =IF($A$65="","",$A$65&" total") | D77: =SUM(D67:D76) | E77: =SUM(E67:E76) | F77: =SUM(F67:F76) | H77: =SUM(H67:H76)
A79: THT Brand
A80: Product | B80: Unit | C80: Kg / Unit | D80: Closing Balance | E80: Closing Stock (Kg) | F80: No. of Cases | G80: Rate / Kg ($) | H80: Stock Value (₹)
A81: =IF($J81="","",INDEX(Stock!$B$8:$B$101,$J81)) | B81: =IF($J81="","",IF(INDEX(Stock!$C$8:$C$101,$J81)=0,"",INDEX(Stock!$C$8:$C$101,$J81))) | C81: =IF($J81="","",IF(INDEX(Stock!$D$8:$D$101,$J81)=0,"",INDEX(Stock!$D$8:$D$101,$J81))) | D81: =IF($J81="","",INDEX(Stock!$J$8:$J$101,$J81)) | E81: =IF($J81="","",INDEX(Stock!$K$8:$K$101,$J81)) | F81: =+$D81/10 | G81: =IF($J81="","",IF(INDEX(Stock!$L$8:$L$101,$J81)=0,"",INDEX(Stock!$L$8:$L$101,$J81))) | H81: =IF($J81="","",INDEX(Stock!$M$8:$M$101,$J81)) | J81: =IFERROR(MATCH($A$79&"#"&1,Stock!$R$8:$R$101,0),"")
A82: =IF($J82="","",INDEX(Stock!$B$8:$B$101,$J82)) | B82: =IF($J82="","",IF(INDEX(Stock!$C$8:$C$101,$J82)=0,"",INDEX(Stock!$C$8:$C$101,$J82))) | C82: =IF($J82="","",IF(INDEX(Stock!$D$8:$D$101,$J82)=0,"",INDEX(Stock!$D$8:$D$101,$J82))) | D82: =IF($J82="","",INDEX(Stock!$J$8:$J$101,$J82)) | E82: =IF($J82="","",INDEX(Stock!$K$8:$K$101,$J82)) | F82: =+$D82/10 | G82: =IF($J82="","",IF(INDEX(Stock!$L$8:$L$101,$J82)=0,"",INDEX(Stock!$L$8:$L$101,$J82))) | H82: =IF($J82="","",INDEX(Stock!$M$8:$M$101,$J82)) | J82: =IFERROR(MATCH($A$79&"#"&2,Stock!$R$8:$R$101,0),"")
A83: =IF($J83="","",INDEX(Stock!$B$8:$B$101,$J83)) | B83: =IF($J83="","",IF(INDEX(Stock!$C$8:$C$101,$J83)=0,"",INDEX(Stock!$C$8:$C$101,$J83))) | C83: =IF($J83="","",IF(INDEX(Stock!$D$8:$D$101,$J83)=0,"",INDEX(Stock!$D$8:$D$101,$J83))) | D83: =IF($J83="","",INDEX(Stock!$J$8:$J$101,$J83)) | E83: =IF($J83="","",INDEX(Stock!$K$8:$K$101,$J83)) | F83: =+$D83/10 | G83: =IF($J83="","",IF(INDEX(Stock!$L$8:$L$101,$J83)=0,"",INDEX(Stock!$L$8:$L$101,$J83))) | H83: =IF($J83="","",INDEX(Stock!$M$8:$M$101,$J83)) | J83: =IFERROR(MATCH($A$79&"#"&3,Stock!$R$8:$R$101,0),"")
A84: =IF($J84="","",INDEX(Stock!$B$8:$B$101,$J84)) | B84: =IF($J84="","",IF(INDEX(Stock!$C$8:$C$101,$J84)=0,"",INDEX(Stock!$C$8:$C$101,$J84))) | C84: =IF($J84="","",IF(INDEX(Stock!$D$8:$D$101,$J84)=0,"",INDEX(Stock!$D$8:$D$101,$J84))) | D84: =IF($J84="","",INDEX(Stock!$J$8:$J$101,$J84)) | E84: =IF($J84="","",INDEX(Stock!$K$8:$K$101,$J84)) | G84: =IF($J84="","",IF(INDEX(Stock!$L$8:$L$101,$J84)=0,"",INDEX(Stock!$L$8:$L$101,$J84))) | H84: =IF($J84="","",INDEX(Stock!$M$8:$M$101,$J84)) | J84: =IFERROR(MATCH($A$79&"#"&4,Stock!$R$8:$R$101,0),"")
A85: =IF($J85="","",INDEX(Stock!$B$8:$B$101,$J85)) | B85: =IF($J85="","",IF(INDEX(Stock!$C$8:$C$101,$J85)=0,"",INDEX(Stock!$C$8:$C$101,$J85))) | C85: =IF($J85="","",IF(INDEX(Stock!$D$8:$D$101,$J85)=0,"",INDEX(Stock!$D$8:$D$101,$J85))) | D85: =IF($J85="","",INDEX(Stock!$J$8:$J$101,$J85)) | E85: =IF($J85="","",INDEX(Stock!$K$8:$K$101,$J85)) | G85: =IF($J85="","",IF(INDEX(Stock!$L$8:$L$101,$J85)=0,"",INDEX(Stock!$L$8:$L$101,$J85))) | H85: =IF($J85="","",INDEX(Stock!$M$8:$M$101,$J85)) | J85: =IFERROR(MATCH($A$79&"#"&5,Stock!$R$8:$R$101,0),"")
A86: =IF($J86="","",INDEX(Stock!$B$8:$B$101,$J86)) | B86: =IF($J86="","",IF(INDEX(Stock!$C$8:$C$101,$J86)=0,"",INDEX(Stock!$C$8:$C$101,$J86))) | C86: =IF($J86="","",IF(INDEX(Stock!$D$8:$D$101,$J86)=0,"",INDEX(Stock!$D$8:$D$101,$J86))) | D86: =IF($J86="","",INDEX(Stock!$J$8:$J$101,$J86)) | E86: =IF($J86="","",INDEX(Stock!$K$8:$K$101,$J86)) | G86: =IF($J86="","",IF(INDEX(Stock!$L$8:$L$101,$J86)=0,"",INDEX(Stock!$L$8:$L$101,$J86))) | H86: =IF($J86="","",INDEX(Stock!$M$8:$M$101,$J86)) | J86: =IFERROR(MATCH($A$79&"#"&6,Stock!$R$8:$R$101,0),"")
A87: =IF($A$79="","",$A$79&" total") | D87: =SUM(D81:D86) | E87: =SUM(E81:E86) | F87: =SUM(F81:F86) | H87: =SUM(H81:H86)
A89: China
A90: Product | B90: Unit | C90: Kg / Unit | D90: Closing Balance | E90: Closing Stock (Kg) | F90: No. of Cases | G90: Rate / Kg ($) | H90: Stock Value (₹)
A91: =IF($J91="","",INDEX(Stock!$B$8:$B$101,$J91)) | B91: =IF($J91="","",IF(INDEX(Stock!$C$8:$C$101,$J91)=0,"",INDEX(Stock!$C$8:$C$101,$J91))) | C91: =IF($J91="","",IF(INDEX(Stock!$D$8:$D$101,$J91)=0,"",INDEX(Stock!$D$8:$D$101,$J91))) | D91: =IF($J91="","",INDEX(Stock!$J$8:$J$101,$J91)) | E91: =IF($J91="","",INDEX(Stock!$K$8:$K$101,$J91)) | F91: =+$D91/10 | G91: =IF($J91="","",IF(INDEX(Stock!$L$8:$L$101,$J91)=0,"",INDEX(Stock!$L$8:$L$101,$J91))) | H91: =IF($J91="","",INDEX(Stock!$M$8:$M$101,$J91)) | J91: =IFERROR(MATCH($A$89&"#"&1,Stock!$R$8:$R$101,0),"")
A92: =IF($J92="","",INDEX(Stock!$B$8:$B$101,$J92)) | B92: =IF($J92="","",IF(INDEX(Stock!$C$8:$C$101,$J92)=0,"",INDEX(Stock!$C$8:$C$101,$J92))) | C92: =IF($J92="","",IF(INDEX(Stock!$D$8:$D$101,$J92)=0,"",INDEX(Stock!$D$8:$D$101,$J92))) | D92: =IF($J92="","",INDEX(Stock!$J$8:$J$101,$J92)) | E92: =IF($J92="","",INDEX(Stock!$K$8:$K$101,$J92)) | F92: =+$D92/10 | G92: =IF($J92="","",IF(INDEX(Stock!$L$8:$L$101,$J92)=0,"",INDEX(Stock!$L$8:$L$101,$J92))) | H92: =IF($J92="","",INDEX(Stock!$M$8:$M$101,$J92)) | J92: =IFERROR(MATCH($A$89&"#"&2,Stock!$R$8:$R$101,0),"")
A93: =IF($J93="","",INDEX(Stock!$B$8:$B$101,$J93)) | B93: =IF($J93="","",IF(INDEX(Stock!$C$8:$C$101,$J93)=0,"",INDEX(Stock!$C$8:$C$101,$J93))) | C93: =IF($J93="","",IF(INDEX(Stock!$D$8:$D$101,$J93)=0,"",INDEX(Stock!$D$8:$D$101,$J93))) | D93: =IF($J93="","",INDEX(Stock!$J$8:$J$101,$J93)) | E93: =IF($J93="","",INDEX(Stock!$K$8:$K$101,$J93)) | F93: =+$D93/10 | G93: =IF($J93="","",IF(INDEX(Stock!$L$8:$L$101,$J93)=0,"",INDEX(Stock!$L$8:$L$101,$J93))) | H93: =IF($J93="","",INDEX(Stock!$M$8:$M$101,$J93)) | J93: =IFERROR(MATCH($A$89&"#"&3,Stock!$R$8:$R$101,0),"")
A94: =IF($J94="","",INDEX(Stock!$B$8:$B$101,$J94)) | B94: =IF($J94="","",IF(INDEX(Stock!$C$8:$C$101,$J94)=0,"",INDEX(Stock!$C$8:$C$101,$J94))) | C94: =IF($J94="","",IF(INDEX(Stock!$D$8:$D$101,$J94)=0,"",INDEX(Stock!$D$8:$D$101,$J94))) | D94: =IF($J94="","",INDEX(Stock!$J$8:$J$101,$J94)) | E94: =IF($J94="","",INDEX(Stock!$K$8:$K$101,$J94)) | F94: =+$D94/10 | G94: =IF($J94="","",IF(INDEX(Stock!$L$8:$L$101,$J94)=0,"",INDEX(Stock!$L$8:$L$101,$J94))) | H94: =IF($J94="","",INDEX(Stock!$M$8:$M$101,$J94)) | J94: =IFERROR(MATCH($A$89&"#"&4,Stock!$R$8:$R$101,0),"")
A95: =IF($J95="","",INDEX(Stock!$B$8:$B$101,$J95)) | B95: =IF($J95="","",IF(INDEX(Stock!$C$8:$C$101,$J95)=0,"",INDEX(Stock!$C$8:$C$101,$J95))) | C95: =IF($J95="","",IF(INDEX(Stock!$D$8:$D$101,$J95)=0,"",INDEX(Stock!$D$8:$D$101,$J95))) | D95: =IF($J95="","",INDEX(Stock!$J$8:$J$101,$J95)) | E95: =IF($J95="","",INDEX(Stock!$K$8:$K$101,$J95)) | G95: =IF($J95="","",IF(INDEX(Stock!$L$8:$L$101,$J95)=0,"",INDEX(Stock!$L$8:$L$101,$J95))) | H95: =IF($J95="","",INDEX(Stock!$M$8:$M$101,$J95)) | J95: =IFERROR(MATCH($A$89&"#"&5,Stock!$R$8:$R$101,0),"")
A96: =IF($J96="","",INDEX(Stock!$B$8:$B$101,$J96)) | B96: =IF($J96="","",IF(INDEX(Stock!$C$8:$C$101,$J96)=0,"",INDEX(Stock!$C$8:$C$101,$J96))) | C96: =IF($J96="","",IF(INDEX(Stock!$D$8:$D$101,$J96)=0,"",INDEX(Stock!$D$8:$D$101,$J96))) | D96: =IF($J96="","",INDEX(Stock!$J$8:$J$101,$J96)) | E96: =IF($J96="","",INDEX(Stock!$K$8:$K$101,$J96)) | G96: =IF($J96="","",IF(INDEX(Stock!$L$8:$L$101,$J96)=0,"",INDEX(Stock!$L$8:$L$101,$J96))) | H96: =IF($J96="","",INDEX(Stock!$M$8:$M$101,$J96)) | J96: =IFERROR(MATCH($A$89&"#"&6,Stock!$R$8:$R$101,0),"")
A97: =IF($J97="","",INDEX(Stock!$B$8:$B$101,$J97)) | B97: =IF($J97="","",IF(INDEX(Stock!$C$8:$C$101,$J97)=0,"",INDEX(Stock!$C$8:$C$101,$J97))) | C97: =IF($J97="","",IF(INDEX(Stock!$D$8:$D$101,$J97)=0,"",INDEX(Stock!$D$8:$D$101,$J97))) | D97: =IF($J97="","",INDEX(Stock!$J$8:$J$101,$J97)) | E97: =IF($J97="","",INDEX(Stock!$K$8:$K$101,$J97)) | G97: =IF($J97="","",IF(INDEX(Stock!$L$8:$L$101,$J97)=0,"",INDEX(Stock!$L$8:$L$101,$J97))) | H97: =IF($J97="","",INDEX(Stock!$M$8:$M$101,$J97)) | J97: =IFERROR(MATCH($A$89&"#"&7,Stock!$R$8:$R$101,0),"")
A98: =IF($A$89="","",$A$89&" total") | D98: =SUM(D91:D97) | E98: =SUM(E91:E97) | F98: =SUM(F91:F97) | H98: =SUM(H91:H97)
A100: Deep Sea
A101: Product | B101: Unit | C101: Kg / Unit | D101: Closing Balance | E101: Closing Stock (Kg) | F101: No. of Cases | G101: Rate / Kg ($) | H101: Stock Value (₹)
A102: =IF($J102="","",INDEX(Stock!$B$8:$B$101,$J102)) | B102: =IF($J102="","",IF(INDEX(Stock!$C$8:$C$101,$J102)=0,"",INDEX(Stock!$C$8:$C$101,$J102))) | C102: =IF($J102="","",IF(INDEX(Stock!$D$8:$D$101,$J102)=0,"",INDEX(Stock!$D$8:$D$101,$J102))) | D102: =IF($J102="","",INDEX(Stock!$J$8:$J$101,$J102)) | E102: =IF($J102="","",INDEX(Stock!$K$8:$K$101,$J102)) | F102: =+$D102/10 | G102: =IF($J102="","",IF(INDEX(Stock!$L$8:$L$101,$J102)=0,"",INDEX(Stock!$L$8:$L$101,$J102))) | H102: =IF($J102="","",INDEX(Stock!$M$8:$M$101,$J102)) | J102: =IFERROR(MATCH($A$100&"#"&1,Stock!$R$8:$R$101,0),"")
A103: =IF($J103="","",INDEX(Stock!$B$8:$B$101,$J103)) | B103: =IF($J103="","",IF(INDEX(Stock!$C$8:$C$101,$J103)=0,"",INDEX(Stock!$C$8:$C$101,$J103))) | C103: =IF($J103="","",IF(INDEX(Stock!$D$8:$D$101,$J103)=0,"",INDEX(Stock!$D$8:$D$101,$J103))) | D103: =IF($J103="","",INDEX(Stock!$J$8:$J$101,$J103)) | E103: =IF($J103="","",INDEX(Stock!$K$8:$K$101,$J103)) | G103: =IF($J103="","",IF(INDEX(Stock!$L$8:$L$101,$J103)=0,"",INDEX(Stock!$L$8:$L$101,$J103))) | H103: =IF($J103="","",INDEX(Stock!$M$8:$M$101,$J103)) | J103: =IFERROR(MATCH($A$100&"#"&2,Stock!$R$8:$R$101,0),"")
A104: =IF($J104="","",INDEX(Stock!$B$8:$B$101,$J104)) | B104: =IF($J104="","",IF(INDEX(Stock!$C$8:$C$101,$J104)=0,"",INDEX(Stock!$C$8:$C$101,$J104))) | C104: =IF($J104="","",IF(INDEX(Stock!$D$8:$D$101,$J104)=0,"",INDEX(Stock!$D$8:$D$101,$J104))) | D104: =IF($J104="","",INDEX(Stock!$J$8:$J$101,$J104)) | E104: =IF($J104="","",INDEX(Stock!$K$8:$K$101,$J104)) | G104: =IF($J104="","",IF(INDEX(Stock!$L$8:$L$101,$J104)=0,"",INDEX(Stock!$L$8:$L$101,$J104))) | H104: =IF($J104="","",INDEX(Stock!$M$8:$M$101,$J104)) | J104: =IFERROR(MATCH($A$100&"#"&3,Stock!$R$8:$R$101,0),"")
A105: =IF($J105="","",INDEX(Stock!$B$8:$B$101,$J105)) | B105: =IF($J105="","",IF(INDEX(Stock!$C$8:$C$101,$J105)=0,"",INDEX(Stock!$C$8:$C$101,$J105))) | C105: =IF($J105="","",IF(INDEX(Stock!$D$8:$D$101,$J105)=0,"",INDEX(Stock!$D$8:$D$101,$J105))) | D105: =IF($J105="","",INDEX(Stock!$J$8:$J$101,$J105)) | E105: =IF($J105="","",INDEX(Stock!$K$8:$K$101,$J105)) | G105: =IF($J105="","",IF(INDEX(Stock!$L$8:$L$101,$J105)=0,"",INDEX(Stock!$L$8:$L$101,$J105))) | H105: =IF($J105="","",INDEX(Stock!$M$8:$M$101,$J105)) | J105: =IFERROR(MATCH($A$100&"#"&4,Stock!$R$8:$R$101,0),"")
A106: =IF($A$100="","",$A$100&" total") | D106: =SUM(D102:D105) | E106: =SUM(E102:E105) | F106: =SUM(F102:F105) | H106: =SUM(H102:H105)
A108: Shrimp Whole
A109: Product | B109: Unit | C109: Kg / Unit | D109: Closing Balance | E109: Closing Stock (Kg) | F109: No. of Cases | G109: Rate / Kg ($) | H109: Stock Value (₹)
...

Sheet Daily Report
B1: Premier Exports International | E1: AP X/453, NH-66 Highway, Chandiroor P.O.,
E2: Aroor, Alappuzha, Kerala - 688 537, India
E3: GSTIN 32AADFP3158P1ZZ
A5: DAILY STOCK REPORT | E5: =Stock!$E$3
A6: PURCHASE & PROCESSING · PRODUCTION | E6: STATEMENT DATE
A8: OPENING STOCK (KG) | B8: PRODUCED TODAY (KG) | C8: SHIPPED TODAY (KG) | D8: CLOSING STOCK (KG) | E8: =IF(Stock!$E$4="","STOCK VALUE (₹)","STOCK VALUE (₹) AT "&TEXT(Stock!$E$4,"0.00")&" / US$")
A9: =+($D$9-$B$9)+$C$9 | B9: =SUM(Stock!$T$8:$T$101) | C9: =SUM(Stock!$U$8:$U$101) | D9: =Stock!$K$102 | E9: =IF(Stock!$E$4="","Exchange rate not set",IF(Stock!$M$102="","Export rates not entered",Stock!$M$102))
A10: =IF(SUM(Stock!$X$8:$X$101)=0,"",SUM(Stock!$X$8:$X$101)&" product(s) have no Kg / Unit set — their stock is not counted in these totals.")
A12: POSITION BY BRAND
A13: Brand | B13: Closing Stock (Kg) | C13: Today's Production (Kg) | D13: Today's Shipment (Kg) | E13: Products | F13: Stock Value (₹)
A14: Blue Dolphin | B14: =IF($A14="","",SUMIF(Stock!$A$8:$A$101,$A14,Stock!$K$8:$K$101)) | C14: =IF($A14="","",SUMIF(Stock!$A$8:$A$101,$A14,Stock!$T$8:$T$101)) | D14: =IF($A14="","",SUMIF(Stock!$A$8:$A$101,$A14,Stock!$U$8:$U$101)) | E14: =IF($A14="","",COUNTIF(Stock!$A$8:$A$101,$A14)) | F14: =IF($A14="","",IF(SUMIF(Stock!$A$8:$A$101,$A14,Stock!$M$8:$M$101)=0,"",SUMIF(Stock!$A$8:$A$101,$A14,Stock!$M$8:$M$101)))
A15: Primus Japan | B15: =IF($A15="","",SUMIF(Stock!$A$8:$A$101,$A15,Stock!$K$8:$K$101)) | C15: =IF($A15="","",SUMIF(Stock!$A$8:$A$101,$A15,Stock!$T$8:$T$101)) | D15: =IF($A15="","",SUMIF(Stock!$A$8:$A$101,$A15,Stock!$U$8:$U$101)) | E15: =IF($A15="","",COUNTIF(Stock!$A$8:$A$101,$A15)) | F15: =IF($A15="","",IF(SUMIF(Stock!$A$8:$A$101,$A15,Stock!$M$8:$M$101)=0,"",SUMIF(Stock!$A$8:$A$101,$A15,Stock!$M$8:$M$101)))
A16: Primus EU | B16: =IF($A16="","",SUMIF(Stock!$A$8:$A$101,$A16,Stock!$K$8:$K$101)) | C16: =IF($A16="","",SUMIF(Stock!$A$8:$A$101,$A16,Stock!$T$8:$T$101)) | D16: =IF($A16="","",SUMIF(Stock!$A$8:$A$101,$A16,Stock!$U$8:$U$101)) | E16: =IF($A16="","",COUNTIF(Stock!$A$8:$A$101,$A16)) | F16: =IF($A16="","",IF(SUMIF(Stock!$A$8:$A$101,$A16,Stock!$M$8:$M$101)=0,"",SUMIF(Stock!$A$8:$A$101,$A16,Stock!$M$8:$M$101)))
A17: AMF Brand | B17: =IF($A17="","",SUMIF(Stock!$A$8:$A$101,$A17,Stock!$K$8:$K$101)) | C17: =IF($A17="","",SUMIF(Stock!$A$8:$A$101,$A17,Stock!$T$8:$T$101)) | D17: =IF($A17="","",SUMIF(Stock!$A$8:$A$101,$A17,Stock!$U$8:$U$101)) | E17: =IF($A17="","",COUNTIF(Stock!$A$8:$A$101,$A17)) | F17: =IF($A17="","",IF(SUMIF(Stock!$A$8:$A$101,$A17,Stock!$M$8:$M$101)=0,"",SUMIF(Stock!$A$8:$A$101,$A17,Stock!$M$8:$M$101)))
A18: THT Brand | B18: =IF($A18="","",SUMIF(Stock!$A$8:$A$101,$A18,Stock!$K$8:$K$101)) | C18: =IF($A18="","",SUMIF(Stock!$A$8:$A$101,$A18,Stock!$T$8:$T$101)) | D18: =IF($A18="","",SUMIF(Stock!$A$8:$A$101,$A18,Stock!$U$8:$U$101)) | E18: =IF($A18="","",COUNTIF(Stock!$A$8:$A$101,$A18)) | F18: =IF($A18="","",IF(SUMIF(Stock!$A$8:$A$101,$A18,Stock!$M$8:$M$101)=0,"",SUMIF(Stock!$A$8:$A$101,$A18,Stock!$M$8:$M$101)))
A19: China | B19: =IF($A19="","",SUMIF(Stock!$A$8:$A$101,$A19,Stock!$K$8:$K$101)) | C19: =IF($A19="","",SUMIF(Stock!$A$8:$A$101,$A19,Stock!$T$8:$T$101)) | D19: =IF($A19="","",SUMIF(Stock!$A$8:$A$101,$A19,Stock!$U$8:$U$101)) | E19: =IF($A19="","",COUNTIF(Stock!$A$8:$A$101,$A19)) | F19: =IF($A19="","",IF(SUMIF(Stock!$A$8:$A$101,$A19,Stock!$M$8:$M$101)=0,"",SUMIF(Stock!$A$8:$A$101,$A19,Stock!$M$8:$M$101)))
A20: Deep Sea | B20: =IF($A20="","",SUMIF(Stock!$A$8:$A$101,$A20,Stock!$K$8:$K$101)) | C20: =IF($A20="","",SUMIF(Stock!$A$8:$A$101,$A20,Stock!$T$8:$T$101)) | D20: =IF($A20="","",SUMIF(Stock!$A$8:$A$101,$A20,Stock!$U$8:$U$101)) | E20: =IF($A20="","",COUNTIF(Stock!$A$8:$A$101,$A20)) | F20: =IF($A20="","",IF(SUMIF(Stock!$A$8:$A$101,$A20,Stock!$M$8:$M$101)=0,"",SUMIF(Stock!$A$8:$A$101,$A20,Stock!$M$8:$M$101)))
A21: Shrimp Whole | B21: =IF($A21="","",SUMIF(Stock!$A$8:$A$101,$A21,Stock!$K$8:$K$101)) | C21: =IF($A21="","",SUMIF(Stock!$A$8:$A$101,$A21,Stock!$T$8:$T$101)) | D21: =IF($A21="","",SUMIF(Stock!$A$8:$A$101,$A21,Stock!$U$8:$U$101)) | E21: =IF($A21="","",COUNTIF(Stock!$A$8:$A$101,$A21)) | F21: =IF($A21="","",IF(SUMIF(Stock!$A$8:$A$101,$A21,Stock!$M$8:$M$101)=0,"",SUMIF(Stock!$A$8:$A$101,$A21,Stock!$M$8:$M$101)))
A22: Tuna | B22: =IF($A22="","",SUMIF(Stock!$A$8:$A$101,$A22,Stock!$K$8:$K$101)) | C22: =IF($A22="","",SUMIF(Stock!$A$8:$A$101,$A22,Stock!$T$8:$T$101)) | D22: =IF($A22="","",SUMIF(Stock!$A$8:$A$101,$A22,Stock!$U$8:$U$101)) | E22: =IF($A22="","",COUNTIF(Stock!$A$8:$A$101,$A22)) | F22: =IF($A22="","",IF(SUMIF(Stock!$A$8:$A$101,$A22,Stock!$M$8:$M$101)=0,"",SUMIF(Stock!$A$8:$A$101,$A22,Stock!$M$8:$M$101)))
A23: Mackerel | B23: =IF($A23="","",SUMIF(Stock!$A$8:$A$101,$A23,Stock!$K$8:$K$101)) | C23: =IF($A23="","",SUMIF(Stock!$A$8:$A$101,$A23,Stock!$T$8:$T$101)) | D23: =IF($A23="","",SUMIF(Stock!$A$8:$A$101,$A23,Stock!$U$8:$U$101)) | E23: =IF($A23="","",COUNTIF(Stock!$A$8:$A$101,$A23)) | F23: =IF($A23="","",IF(SUMIF(Stock!$A$8:$A$101,$A23,Stock!$M$8:$M$101)=0,"",SUMIF(Stock!$A$8:$A$101,$A23,Stock!$M$8:$M$101)))
A24: Cuttlefish | B24: =IF($A24="","",SUMIF(Stock!$A$8:$A$101,$A24,Stock!$K$8:$K$101)) | C24: =IF($A24="","",SUMIF(Stock!$A$8:$A$101,$A24,Stock!$T$8:$T$101)) | D24: =IF($A24="","",SUMIF(Stock!$A$8:$A$101,$A24,Stock!$U$8:$U$101)) | E24: =IF($A24="","",COUNTIF(Stock!$A$8:$A$101,$A24)) | F24: =IF($A24="","",IF(SUMIF(Stock!$A$8:$A$101,$A24,Stock!$M$8:$M$101)=0,"",SUMIF(Stock!$A$8:$A$101,$A24,Stock!$M$8:$M$101)))
A25: White Squid | B25: =IF($A25="","",SUMIF(Stock!$A$8:$A$101,$A25,Stock!$K$8:$K$101)) | C25: =IF($A25="","",SUMIF(Stock!$A$8:$A$101,$A25,Stock!$T$8:$T$101)) | D25: =IF($A25="","",SUMIF(Stock!$A$8:$A$101,$A25,Stock!$U$8:$U$101)) | E25: =IF($A25="","",COUNTIF(Stock!$A$8:$A$101,$A25)) | F25: =IF($A25="","",IF(SUMIF(Stock!$A$8:$A$101,$A25,Stock!$M$8:$M$101)=0,"",SUMIF(Stock!$A$8:$A$101,$A25,Stock!$M$8:$M$101)))
A26: Semi Needle Squid | B26: =IF($A26="","",SUMIF(Stock!$A$8:$A$101,$A26,Stock!$K$8:$K$101)) | C26: =IF($A26="","",SUMIF(Stock!$A$8:$A$101,$A26,Stock!$T$8:$T$101)) | D26: =IF($A26="","",SUMIF(Stock!$A$8:$A$101,$A26,Stock!$U$8:$U$101)) | E26: =IF($A26="","",COUNTIF(Stock!$A$8:$A$101,$A26)) | F26: =IF($A26="","",IF(SUMIF(Stock!$A$8:$A$101,$A26,Stock!$M$8:$M$101)=0,"",SUMIF(Stock!$A$8:$A$101,$A26,Stock!$M$8:$M$101)))
B27: =IF($A27="","",SUMIF(Stock!$A$8:$A$101,$A27,Stock!$K$8:$K$101)) | C27: =IF($A27="","",SUMIF(Stock!$A$8:$A$101,$A27,Stock!$T$8:$T$101)) | D27: =IF($A27="","",SUMIF(Stock!$A$8:$A$101,$A27,Stock!$U$8:$U$101)) | E27: =IF($A27="","",COUNTIF(Stock!$A$8:$A$101,$A27)) | F27: =IF($A27="","",IF(SUMIF(Stock!$A$8:$A$101,$A27,Stock!$M$8:$M$101)=0,"",SUMIF(Stock!$A$8:$A$101,$A27,Stock!$M$8:$M$101)))
B28: =IF($A28="","",SUMIF(Stock!$A$8:$A$101,$A28,Stock!$K$8:$K$101)) | C28: =IF($A28="","",SUMIF(Stock!$A$8:$A$101,$A28,Stock!$T$8:$T$101)) | D28: =IF($A28="","",SUMIF(Stock!$A$8:$A$101,$A28,Stock!$U$8:$U$101)) | E28: =IF($A28="","",COUNTIF(Stock!$A$8:$A$101,$A28)) | F28: =IF($A28="","",IF(SUMIF(Stock!$A$8:$A$101,$A28,Stock!$M$8:$M$101)=0,"",SUMIF(Stock!$A$8:$A$101,$A28,Stock!$M$8:$M$101)))
A29: GRAND TOTAL | B29: =SUM(B14:B28) | C29: =SUM(C14:C28) | D29: =SUM(D14:D28) | F29: =IF(SUM(F14:F28)=0,"",SUM(F14:F28))
A31: TODAY'S MOVEMENTS
A32: Brand | B32: Product | C32: Production | D32: Shipment | E32: Closing Stock Balance | F32: Unit
A33: =IF($H33="","",INDEX(Stock!$A$8:$A$101,$H33)) | B33: =IF($H33="","",INDEX(Stock!$B$8:$B$101,$H33)) | C33: =IF($H33="","",INDEX(Stock!$F$8:$F$101,$H33)) | D33: =IF($H33="","",INDEX(Stock!$G$8:$G$101,$H33)) | E33: =IF($H33="","",INDEX(Stock!$J$8:$J$101,$H33)) | F33: =IF($H33="","",IF(INDEX(Stock!$C$8:$C$101,$H33)=0,"",INDEX(Stock!$C$8:$C$101,$H33))) | H33: =IFERROR(MATCH(1,Stock!$Q$8:$Q$101,0),"")
A34: =IF($H34="","",INDEX(Stock!$A$8:$A$101,$H34)) | B34: =IF($H34="","",INDEX(Stock!$B$8:$B$101,$H34)) | C34: =IF($H34="","",INDEX(Stock!$F$8:$F$101,$H34)) | D34: =IF($H34="","",INDEX(Stock!$G$8:$G$101,$H34)) | E34: =IF($H34="","",INDEX(Stock!$J$8:$J$101,$H34)) | F34: =IF($H34="","",IF(INDEX(Stock!$C$8:$C$101,$H34)=0,"",INDEX(Stock!$C$8:$C$101,$H34))) | H34: =IFERROR(MATCH(2,Stock!$Q$8:$Q$101,0),"")
A35: =IF($H35="","",INDEX(Stock!$A$8:$A$101,$H35)) | B35: =IF($H35="","",INDEX(Stock!$B$8:$B$101,$H35)) | C35: =IF($H35="","",INDEX(Stock!$F$8:$F$101,$H35)) | D35: =IF($H35="","",INDEX(Stock!$G$8:$G$101,$H35)) | E35: =IF($H35="","",INDEX(Stock!$J$8:$J$101,$H35)) | F35: =IF($H35="","",IF(INDEX(Stock!$C$8:$C$101,$H35)=0,"",INDEX(Stock!$C$8:$C$101,$H35))) | H35: =IFERROR(MATCH(3,Stock!$Q$8:$Q$101,0),"")
A36: =IF($H36="","",INDEX(Stock!$A$8:$A$101,$H36)) | B36: =IF($H36="","",INDEX(Stock!$B$8:$B$101,$H36)) | C36: =IF($H36="","",INDEX(Stock!$F$8:$F$101,$H36)) | D36: =IF($H36="","",INDEX(Stock!$G$8:$G$101,$H36)) | E36: =IF($H36="","",INDEX(Stock!$J$8:$J$101,$H36)) | F36: =IF($H36="","",IF(INDEX(Stock!$C$8:$C$101,$H36)=0,"",INDEX(Stock!$C$8:$C$101,$H36))) | H36: =IFERROR(MATCH(4,Stock!$Q$8:$Q$101,0),"")
A37: =IF($H37="","",INDEX(Stock!$A$8:$A$101,$H37)) | B37: =IF($H37="","",INDEX(Stock!$B$8:$B$101,$H37)) | C37: =IF($H37="","",INDEX(Stock!$F$8:$F$101,$H37)) | D37: =IF($H37="","",INDEX(Stock!$G$8:$G$101,$H37)) | E37: =IF($H37="","",INDEX(Stock!$J$8:$J$101,$H37)) | F37: =IF($H37="","",IF(INDEX(Stock!$C$8:$C$101,$H37)=0,"",INDEX(Stock!$C$8:$C$101,$H37))) | H37: =IFERROR(MATCH(5,Stock!$Q$8:$Q$101,0),"")
A38: =IF($H38="","",INDEX(Stock!$A$8:$A$101,$H38)) | B38: =IF($H38="","",INDEX(Stock!$B$8:$B$101,$H38)) | C38: =IF($H38="","",INDEX(Stock!$F$8:$F$101,$H38)) | D38: =IF($H38="","",INDEX(Stock!$G$8:$G$101,$H38)) | E38: =IF($H38="","",INDEX(Stock!$J$8:$J$101,$H38)) | F38: =IF($H38="","",IF(INDEX(Stock!$C$8:$C$101,$H38)=0,"",INDEX(Stock!$C$8:$C$101,$H38))) | H38: =IFERROR(MATCH(6,Stock!$Q$8:$Q$101,0),"")
A39: =IF($H39="","",INDEX(Stock!$A$8:$A$101,$H39)) | B39: =IF($H39="","",INDEX(Stock!$B$8:$B$101,$H39)) | C39: =IF($H39="","",INDEX(Stock!$F$8:$F$101,$H39)) | D39: =IF($H39="","",INDEX(Stock!$G$8:$G$101,$H39)) | E39: =IF($H39="","",INDEX(Stock!$J$8:$J$101,$H39)) | F39: =IF($H39="","",IF(INDEX(Stock!$C$8:$C$101,$H39)=0,"",INDEX(Stock!$C$8:$C$101,$H39))) | H39: =IFERROR(MATCH(7,Stock!$Q$8:$Q$101,0),"")
A40: =IF($H40="","",INDEX(Stock!$A$8:$A$101,$H40)) | B40: =IF($H40="","",INDEX(Stock!$B$8:$B$101,$H40)) | C40: =IF($H40="","",INDEX(Stock!$F$8:$F$101,$H40)) | D40: =IF($H40="","",INDEX(Stock!$G$8:$G$101,$H40)) | E40: =IF($H40="","",INDEX(Stock!$J$8:$J$101,$H40)) | F40: =IF($H40="","",IF(INDEX(Stock!$C$8:$C$101,$H40)=0,"",INDEX(Stock!$C$8:$C$101,$H40))) | H40: =IFERROR(MATCH(8,Stock!$Q$8:$Q$101,0),"")
A41: =IF($H41="","",INDEX(Stock!$A$8:$A$101,$H41)) | B41: =IF($H41="","",INDEX(Stock!$B$8:$B$101,$H41)) | C41: =IF($H41="","",INDEX(Stock!$F$8:$F$101,$H41)) | D41: =IF($H41="","",INDEX(Stock!$G$8:$G$101,$H41)) | E41: =IF($H41="","",INDEX(Stock!$J$8:$J$101,$H41)) | F41: =IF($H41="","",IF(INDEX(Stock!$C$8:$C$101,$H41)=0,"",INDEX(Stock!$C$8:$C$101,$H41))) | H41: =IFERROR(MATCH(9,Stock!$Q$8:$Q$101,0),"")
A42: =IF($H42="","",INDEX(Stock!$A$8:$A$101,$H42)) | B42: =IF($H42="","",INDEX(Stock!$B$8:$B$101,$H42)) | C42: =IF($H42="","",INDEX(Stock!$F$8:$F$101,$H42)) | D42: =IF($H42="","",INDEX(Stock!$G$8:$G$101,$H42)) | E42: =IF($H42="","",INDEX(Stock!$J$8:$J$101,$H42)) | F42: =IF($H42="","",IF(INDEX(Stock!$C$8:$C$101,$H42)=0,"",INDEX(Stock!$C$8:$C$101,$H42))) | H42: =IFERROR(MATCH(10,Stock!$Q$8:$Q$101,0),"")
A43: =IF($H43="","",INDEX(Stock!$A$8:$A$101,$H43)) | B43: =IF($H43="","",INDEX(Stock!$B$8:$B$101,$H43)) | C43: =IF($H43="","",INDEX(Stock!$F$8:$F$101,$H43)) | D43: =IF($H43="","",INDEX(Stock!$G$8:$G$101,$H43)) | E43: =IF($H43="","",INDEX(Stock!$J$8:$J$101,$H43)) | F43: =IF($H43="","",IF(INDEX(Stock!$C$8:$C$101,$H43)=0,"",INDEX(Stock!$C$8:$C$101,$H43))) | H43: =IFERROR(MATCH(11,Stock!$Q$8:$Q$101,0),"")
A44: =IF($H44="","",INDEX(Stock!$A$8:$A$101,$H44)) | B44: =IF($H44="","",INDEX(Stock!$B$8:$B$101,$H44)) | C44: =IF($H44="","",INDEX(Stock!$F$8:$F$101,$H44)) | D44: =IF($H44="","",INDEX(Stock!$G$8:$G$101,$H44)) | E44: =IF($H44="","",INDEX(Stock!$J$8:$J$101,$H44)) | F44: =IF($H44="","",IF(INDEX(Stock!$C$8:$C$101,$H44)=0,"",INDEX(Stock!$C$8:$C$101,$H44))) | H44: =IFERROR(MATCH(12,Stock!$Q$8:$Q$101,0),"")
A45: =IF($H45="","",INDEX(Stock!$A$8:$A$101,$H45)) | B45: =IF($H45="","",INDEX(Stock!$B$8:$B$101,$H45)) | C45: =IF($H45="","",INDEX(Stock!$F$8:$F$101,$H45)) | D45: =IF($H45="","",INDEX(Stock!$G$8:$G$101,$H45)) | E45: =IF($H45="","",INDEX(Stock!$J$8:$J$101,$H45)) | F45: =IF($H45="","",IF(INDEX(Stock!$C$8:$C$101,$H45)=0,"",INDEX(Stock!$C$8:$C$101,$H45))) | H45: =IFERROR(MATCH(13,Stock!$Q$8:$Q$101,0),"")
A46: =IF($H46="","",INDEX(Stock!$A$8:$A$101,$H46)) | B46: =IF($H46="","",INDEX(Stock!$B$8:$B$101,$H46)) | C46: =IF($H46="","",INDEX(Stock!$F$8:$F$101,$H46)) | D46: =IF($H46="","",INDEX(Stock!$G$8:$G$101,$H46)) | E46: =IF($H46="","",INDEX(Stock!$J$8:$J$101,$H46)) | F46: =IF($H46="","",IF(INDEX(Stock!$C$8:$C$101,$H46)=0,"",INDEX(Stock!$C$8:$C$101,$H46))) | H46: =IFERROR(MATCH(14,Stock!$Q$8:$Q$101,0),"")
A47: =IF($H47="","",INDEX(Stock!$A$8:$A$101,$H47)) | B47: =IF($H47="","",INDEX(Stock!$B$8:$B$101,$H47)) | C47: =IF($H47="","",INDEX(Stock!$F$8:$F$101,$H47)) | D47: =IF($H47="","",INDEX(Stock!$G$8:$G$101,$H47)) | E47: =IF($H47="","",INDEX(Stock!$J$8:$J$101,$H47)) | F47: =IF($H47="","",IF(INDEX(Stock!$C$8:$C$101,$H47)=0,"",INDEX(Stock!$C$8:$C$101,$H47))) | H47: =IFERROR(MATCH(15,Stock!$Q$8:$Q$101,0),"")
A48: =IF($H48="","",INDEX(Stock!$A$8:$A$101,$H48)) | B48: =IF($H48="","",INDEX(Stock!$B$8:$B$101,$H48)) | C48: =IF($H48="","",INDEX(Stock!$F$8:$F$101,$H48)) | D48: =IF($H48="","",INDEX(Stock!$G$8:$G$101,$H48)) | E48: =IF($H48="","",INDEX(Stock!$J$8:$J$101,$H48)) | F48: =IF($H48="","",IF(INDEX(Stock!$C$8:$C$101,$H48)=0,"",INDEX(Stock!$C$8:$C$101,$H48))) | H48: =IFERROR(MATCH(16,Stock!$Q$8:$Q$101,0),"")
A49: =IF($H49="","",INDEX(Stock!$A$8:$A$101,$H49)) | B49: =IF($H49="","",INDEX(Stock!$B$8:$B$101,$H49)) | C49: =IF($H49="","",INDEX(Stock!$F$8:$F$101,$H49)) | D49: =IF($H49="","",INDEX(Stock!$G$8:$G$101,$H49)) | E49: =IF($H49="","",INDEX(Stock!$J$8:$J$101,$H49)) | F49: =IF($H49="","",IF(INDEX(Stock!$C$8:$C$101,$H49)=0,"",INDEX(Stock!$C$8:$C$101,$H49))) | H49: =IFERROR(MATCH(17,Stock!$Q$8:$Q$101,0),"")
A50: =IF($H50="","",INDEX(Stock!$A$8:$A$101,$H50)) | B50: =IF($H50="","",INDEX(Stock!$B$8:$B$101,$H50)) | C50: =IF($H50="","",INDEX(Stock!$F$8:$F$101,$H50)) | D50: =IF($H50="","",INDEX(Stock!$G$8:$G$101,$H50)) | E50: =IF($H50="","",INDEX(Stock!$J$8:$J$101,$H50)) | F50: =IF($H50="","",IF(INDEX(Stock!$C$8:$C$101,$H50)=0,"",INDEX(Stock!$C$8:$C$101,$H50))) | H50: =IFERROR(MATCH(18,Stock!$Q$8:$Q$101,0),"")
A51: =IF($H51="","",INDEX(Stock!$A$8:$A$101,$H51)) | B51: =IF($H51="","",INDEX(Stock!$B$8:$B$101,$H51)) | C51: =IF($H51="","",INDEX(Stock!$F$8:$F$101,$H51)) | D51: =IF($H51="","",INDEX(Stock!$G$8:$G$101,$H51)) | E51: =IF($H51="","",INDEX(Stock!$J$8:$J$101,$H51)) | F51: =IF($H51="","",IF(INDEX(Stock!$C$8:$C$101,$H51)=0,"",INDEX(Stock!$C$8:$C$101,$H51))) | H51: =IFERROR(MATCH(19,Stock!$Q$8:$Q$101,0),"")
A52: =IF($H52="","",INDEX(Stock!$A$8:$A$101,$H52)) | B52: =IF($H52="","",INDEX(Stock!$B$8:$B$101,$H52)) | C52: =IF($H52="","",INDEX(Stock!$F$8:$F$101,$H52)) | D52: =IF($H52="","",INDEX(Stock!$G$8:$G$101,$H52)) | E52: =IF($H52="","",INDEX(Stock!$J$8:$J$101,$H52)) | F52: =IF($H52="","",IF(INDEX(Stock!$C$8:$C$101,$H52)=0,"",INDEX(Stock!$C$8:$C$101,$H52))) | H52: =IFERROR(MATCH(20,Stock!$Q$8:$Q$101,0),"")
A53: TOTAL MOVED TODAY | B53: =COUNTIF(Stock!$P$8:$P$101,1)&" product(s)" | C53: =SUM(Stock!$T$8:$T$101) | D53: =SUM(Stock!$U$8:$U$101) | E53: Kg
A54: =IF(COUNTIF(Stock!$P$8:$P$101,1)>20,"Note: "&(COUNTIF(Stock!$P$8:$P$101,1)-20)&" further product(s) moved today — see the Stock sheet.","")
A56: Prepared from the stock register. Balances are in each product's own unit; totals are in kilos. Value = Closing Kg × Rate / Kg ($) × Exchange Rate.

Sheet Carton Stock
A1: PREMIER EXPORTS INTERNATIONAL
A2: CARTON STOCK — LIVE POSITION
A3: Statement Date | E3: =Stock!$E$3 | F3: ← from Stock; change it there
A4: Count Date | E4: 46325 | F4: ← the day the opening cartons were counted, before that day's packing | O4: Days averaged | P4: =MAX(1,MIN(30,Stock!$E$3-'Carton Stock'!$E$4+1))
A5: Cartons used come from production on Daily Entry and the carton sizes on Packing, rounded up per product. Closing = Opening + Received − Used ± Adjusted.
A7: Brand | B7: Carton | C7: Opening Stock | D7: Received Today | E7: Used Today | F7: Received to Date | G7: Used to Date | H7: Adjusted to Date | I7: Closing Stock | J7: Reorder Level | K7: Status | L7: Days Left | O7: Used / day (last 30 days) | P7: Duplicate name
A8: Blue Dolphin | B8: Blue Dolphin carton | D8: =IF($B8="","",IF(Stock!$E$3<'Carton Stock'!$E$4,0,SUMIFS('Carton Entry'!$C$7:$C$5006,'Carton Entry'!$B$7:$B$5006,$B8,'Carton Entry'!$A$7:$A$5006,Stock!$E$3))) | E8: =IF($B8="","",SUMIF(Packing!$D$8:$D$101,$B8,Packing!$I$8:$I$101)) | F8: =IF($B8="","",IF(Stock!$E$3<'Carton Stock'!$E$4,0,SUMIFS('Carton Entry'!$C$7:$C$5006,'Carton Entry'!$B$7:$B$5006,$B8,'Carton Entry'!$A$7:$A$5006,">="&'Carton Stock'!$E$4,'Carton Entry'!$A$7:$A$5006,"<="&Stock!$E$3))) | G8: =IF($B8="","",SUMIF(Packing!$D$8:$D$101,$B8,Packing!$G$8:$G$101)) | H8: =IF($B8="","",IF(Stock!$E$3<'Carton Stock'!$E$4,0,SUMIFS('Carton Entry'!$D$7:$D$5006,'Carton Entry'!$B$7:$B$5006,$B8,'Carton Entry'!$A$7:$A$5006,">="&'Carton Stock'!$E$4,'Carton Entry'!$A$7:$A$5006,"<="&Stock!$E$3))) | I8: =IF(OR($B8="",$C8=""),"",$C8+$F8-$G8+$H8) | K8: =IF($B8="","",IF($C8="","Count needed",IF($I8<0,"Negative — check",IF(AND($J8<>"",$I8<=$J8),"Reorder","OK")))) | L8: =IF($I8="","",IF($I8<=0,0,IF(N($O8)<=0,"—",ROUNDDOWN($I8/$O8,0)))) | O8: =IF($B8="","",SUMIF(Packing!$D$8:$D$101,$B8,Packing!$Q$8:$Q$101)/$P$4) | P8: =IF($B8="",0,IF(COUNTIF($B$8:$B$47,$B8)>1,1,0))
A9: Primus Japan | B9: Primus Japan carton | D9: =IF($B9="","",IF(Stock!$E$3<'Carton Stock'!$E$4,0,SUMIFS('Carton Entry'!$C$7:$C$5006,'Carton Entry'!$B$7:$B$5006,$B9,'Carton Entry'!$A$7:$A$5006,Stock!$E$3))) | E9: =IF($B9="","",SUMIF(Packing!$D$8:$D$101,$B9,Packing!$I$8:$I$101)) | F9: =IF($B9="","",IF(Stock!$E$3<'Carton Stock'!$E$4,0,SUMIFS('Carton Entry'!$C$7:$C$5006,'Carton Entry'!$B$7:$B$5006,$B9,'Carton Entry'!$A$7:$A$5006,">="&'Carton Stock'!$E$4,'Carton Entry'!$A$7:$A$5006,"<="&Stock!$E$3))) | G9: =IF($B9="","",SUMIF(Packing!$D$8:$D$101,$B9,Packing!$G$8:$G$101)) | H9: =IF($B9="","",IF(Stock!$E$3<'Carton Stock'!$E$4,0,SUMIFS('Carton Entry'!$D$7:$D$5006,'Carton Entry'!$B$7:$B$5006,$B9,'Carton Entry'!$A$7:$A$5006,">="&'Carton Stock'!$E$4,'Carton Entry'!$A$7:$A$5006,"<="&Stock!$E$3))) | I9: =IF(OR($B9="",$C9=""),"",$C9+$F9-$G9+$H9) | K9: =IF($B9="","",IF($C9="","Count needed",IF($I9<0,"Negative — check",IF(AND($J9<>"",$I9<=$J9),"Reorder","OK")))) | L9: =IF($I9="","",IF($I9<=0,0,IF(N($O9)<=0,"—",ROUNDDOWN($I9/$O9,0)))) | O9: =IF($B9="","",SUMIF(Packing!$D$8:$D$101,$B9,Packing!$Q$8:$Q$101)/$P$4) | P9: =IF($B9="",0,IF(COUNTIF($B$8:$B$47,$B9)>1,1,0))
A10: Primus EU | B10: Primus EU carton | D10: =IF($B10="","",IF(Stock!$E$3<'Carton Stock'!$E$4,0,SUMIFS('Carton Entry'!$C$7:$C$5006,'Carton Entry'!$B$7:$B$5006,$B10,'Carton Entry'!$A$7:$A$5006,Stock!$E$3))) | E10: =IF($B10="","",SUMIF(Packing!$D$8:$D$101,$B10,Packing!$I$8:$I$101)) | F10: =IF($B10="","",IF(Stock!$E$3<'Carton Stock'!$E$4,0,SUMIFS('Carton Entry'!$C$7:$C$5006,'Carton Entry'!$B$7:$B$5006,$B10,'Carton Entry'!$A$7:$A$5006,">="&'Carton Stock'!$E$4,'Carton Entry'!$A$7:$A$5006,"<="&Stock!$E$3))) | G10: =IF($B10="","",SUMIF(Packing!$D$8:$D$101,$B10,Packing!$G$8:$G$101)) | H10: =IF($B10="","",IF(Stock!$E$3<'Carton Stock'!$E$4,0,SUMIFS('Carton Entry'!$D$7:$D$5006,'Carton Entry'!$B$7:$B$5006,$B10,'Carton Entry'!$A$7:$A$5006,">="&'Carton Stock'!$E$4,'Carton Entry'!$A$7:$A$5006,"<="&Stock!$E$3))) | I10: =IF(OR($B10="",$C10=""),"",$C10+$F10-$G10+$H10) | K10: =IF($B10="","",IF($C10="","Count needed",IF($I10<0,"Negative — check",IF(AND($J10<>"",$I10<=$J10),"Reorder","OK")))) | L10: =IF($I10="","",IF($I10<=0,0,IF(N($O10)<=0,"—",ROUNDDOWN($I10/$O10,0)))) | O10: =IF($B10="","",SUMIF(Packing!$D$8:$D$101,$B10,Packing!$Q$8:$Q$101)/$P$4) | P10: =IF($B10="",0,IF(COUNTIF($B$8:$B$47,$B10)>1,1,0))
A11: AMF Brand | B11: AMF Brand carton | D11: =IF($B11="","",IF(Stock!$E$3<'Carton Stock'!$E$4,0,SUMIFS('Carton Entry'!$C$7:$C$5006,'Carton Entry'!$B$7:$B$5006,$B11,'Carton Entry'!$A$7:$A$5006,Stock!$E$3))) | E11: =IF($B11="","",SUMIF(Packing!$D$8:$D$101,$B11,Packing!$I$8:$I$101)) | F11: =IF($B11="","",IF(Stock!$E$3<'Carton Stock'!$E$4,0,SUMIFS('Carton Entry'!$C$7:$C$5006,'Carton Entry'!$B$7:$B$5006,$B11,'Carton Entry'!$A$7:$A$5006,">="&'Carton Stock'!$E$4,'Carton Entry'!$A$7:$A$5006,"<="&Stock!$E$3))) | G11: =IF($B11="","",SUMIF(Packing!$D$8:$D$101,$B11,Packing!$G$8:$G$101)) | H11: =IF($B11="","",IF(Stock!$E$3<'Carton Stock'!$E$4,0,SUMIFS('Carton Entry'!$D$7:$D$5006,'Carton Entry'!$B$7:$B$5006,$B11,'Carton Entry'!$A$7:$A$5006,">="&'Carton Stock'!$E$4,'Carton Entry'!$A$7:$A$5006,"<="&Stock!$E$3))) | I11: =IF(OR($B11="",$C11=""),"",$C11+$F11-$G11+$H11) | K11: =IF($B11="","",IF($C11="","Count needed",IF($I11<0,"Negative — check",IF(AND($J11<>"",$I11<=$J11),"Reorder","OK")))) | L11: =IF($I11="","",IF($I11<=0,0,IF(N($O11)<=0,"—",ROUNDDOWN($I11/$O11,0)))) | O11: =IF($B11="","",SUMIF(Packing!$D$8:$D$101,$B11,Packing!$Q$8:$Q$101)/$P$4) | P11: =IF($B11="",0,IF(COUNTIF($B$8:$B$47,$B11)>1,1,0))
A12: THT Brand | B12: THT Brand carton | D12: =IF($B12="","",IF(Stock!$E$3<'Carton Stock'!$E$4,0,SUMIFS('Carton Entry'!$C$7:$C$5006,'Carton Entry'!$B$7:$B$5006,$B12,'Carton Entry'!$A$7:$A$5006,Stock!$E$3))) | E12: =IF($B12="","",SUMIF(Packing!$D$8:$D$101,$B12,Packing!$I$8:$I$101)) | F12: =IF($B12="","",IF(Stock!$E$3<'Carton Stock'!$E$4,0,SUMIFS('Carton Entry'!$C$7:$C$5006,'Carton Entry'!$B$7:$B$5006,$B12,'Carton Entry'!$A$7:$A$5006,">="&'Carton Stock'!$E$4,'Carton Entry'!$A$7:$A$5006,"<="&Stock!$E$3))) | G12: =IF($B12="","",SUMIF(Packing!$D$8:$D$101,$B12,Packing!$G$8:$G$101)) | H12: =IF($B12="","",IF(Stock!$E$3<'Carton Stock'!$E$4,0,SUMIFS('Carton Entry'!$D$7:$D$5006,'Carton Entry'!$B$7:$B$5006,$B12,'Carton Entry'!$A$7:$A$5006,">="&'Carton Stock'!$E$4,'Carton Entry'!$A$7:$A$5006,"<="&Stock!$E$3))) | I12: =IF(OR($B12="",$C12=""),"",$C12+$F12-$G12+$H12) | K12: =IF($B12="","",IF($C12="","Count needed",IF($I12<0,"Negative — check",IF(AND($J12<>"",$I12<=$J12),"Reorder","OK")))) | L12: =IF($I12="","",IF($I12<=0,0,IF(N($O12)<=0,"—",ROUNDDOWN($I12/$O12,0)))) | O12: =IF($B12="","",SUMIF(Packing!$D$8:$D$101,$B12,Packing!$Q$8:$Q$101)/$P$4) | P12: =IF($B12="",0,IF(COUNTIF($B$8:$B$47,$B12)>1,1,0))
A13: China | B13: China carton | D13: =IF($B13="","",IF(Stock!$E$3<'Carton Stock'!$E$4,0,SUMIFS('Carton Entry'!$C$7:$C$5006,'Carton Entry'!$B$7:$B$5006,$B13,'Carton Entry'!$A$7:$A$5006,Stock!$E$3))) | E13: =IF($B13="","",SUMIF(Packing!$D$8:$D$101,$B13,Packing!$I$8:$I$101)) | F13: =IF($B13="","",IF(Stock!$E$3<'Carton Stock'!$E$4,0,SUMIFS('Carton Entry'!$C$7:$C$5006,'Carton Entry'!$B$7:$B$5006,$B13,'Carton Entry'!$A$7:$A$5006,">="&'Carton Stock'!$E$4,'Carton Entry'!$A$7:$A$5006,"<="&Stock!$E$3))) | G13: =IF($B13="","",SUMIF(Packing!$D$8:$D$101,$B13,Packing!$G$8:$G$101)) | H13: =IF($B13="","",IF(Stock!$E$3<'Carton Stock'!$E$4,0,SUMIFS('Carton Entry'!$D$7:$D$5006,'Carton Entry'!$B$7:$B$5006,$B13,'Carton Entry'!$A$7:$A$5006,">="&'Carton Stock'!$E$4,'Carton Entry'!$A$7:$A$5006,"<="&Stock!$E$3))) | I13: =IF(OR($B13="",$C13=""),"",$C13+$F13-$G13+$H13) | K13: =IF($B13="","",IF($C13="","Count needed",IF($I13<0,"Negative — check",IF(AND($J13<>"",$I13<=$J13),"Reorder","OK")))) | L13: =IF($I13="","",IF($I13<=0,0,IF(N($O13)<=0,"—",ROUNDDOWN($I13/$O13,0)))) | O13: =IF($B13="","",SUMIF(Packing!$D$8:$D$101,$B13,Packing!$Q$8:$Q$101)/$P$4) | P13: =IF($B13="",0,IF(COUNTIF($B$8:$B$47,$B13)>1,1,0))
A14: Deep Sea | B14: Deep Sea carton | D14: =IF($B14="","",IF(Stock!$E$3<'Carton Stock'!$E$4,0,SUMIFS('Carton Entry'!$C$7:$C$5006,'Carton Entry'!$B$7:$B$5006,$B14,'Carton Entry'!$A$7:$A$5006,Stock!$E$3))) | E14: =IF($B14="","",SUMIF(Packing!$D$8:$D$101,$B14,Packing!$I$8:$I$101)) | F14: =IF($B14="","",IF(Stock!$E$3<'Carton Stock'!$E$4,0,SUMIFS('Carton Entry'!$C$7:$C$5006,'Carton Entry'!$B$7:$B$5006,$B14,'Carton Entry'!$A$7:$A$5006,">="&'Carton Stock'!$E$4,'Carton Entry'!$A$7:$A$5006,"<="&Stock!$E$3))) | G14: =IF($B14="","",SUMIF(Packing!$D$8:$D$101,$B14,Packing!$G$8:$G$101)) | H14: =IF($B14="","",IF(Stock!$E$3<'Carton Stock'!$E$4,0,SUMIFS('Carton Entry'!$D$7:$D$5006,'Carton Entry'!$B$7:$B$5006,$B14,'Carton Entry'!$A$7:$A$5006,">="&'Carton Stock'!$E$4,'Carton Entry'!$A$7:$A$5006,"<="&Stock!$E$3))) | I14: =IF(OR($B14="",$C14=""),"",$C14+$F14-$G14+$H14) | K14: =IF($B14="","",IF($C14="","Count needed",IF($I14<0,"Negative — check",IF(AND($J14<>"",$I14<=$J14),"Reorder","OK")))) | L14: =IF($I14="","",IF($I14<=0,0,IF(N($O14)<=0,"—",ROUNDDOWN($I14/$O14,0)))) | O14: =IF($B14="","",SUMIF(Packing!$D$8:$D$101,$B14,Packing!$Q$8:$Q$101)/$P$4) | P14: =IF($B14="",0,IF(COUNTIF($B$8:$B$47,$B14)>1,1,0))
A15: Shrimp Whole | B15: Shrimp Whole carton | D15: =IF($B15="","",IF(Stock!$E$3<'Carton Stock'!$E$4,0,SUMIFS('Carton Entry'!$C$7:$C$5006,'Carton Entry'!$B$7:$B$5006,$B15,'Carton Entry'!$A$7:$A$5006,Stock!$E$3))) | E15: =IF($B15="","",SUMIF(Packing!$D$8:$D$101,$B15,Packing!$I$8:$I$101)) | F15: =IF($B15="","",IF(Stock!$E$3<'Carton Stock'!$E$4,0,SUMIFS('Carton Entry'!$C$7:$C$5006,'Carton Entry'!$B$7:$B$5006,$B15,'Carton Entry'!$A$7:$A$5006,">="&'Carton Stock'!$E$4,'Carton Entry'!$A$7:$A$5006,"<="&Stock!$E$3))) | G15: =IF($B15="","",SUMIF(Packing!$D$8:$D$101,$B15,Packing!$G$8:$G$101)) | H15: =IF($B15="","",IF(Stock!$E$3<'Carton Stock'!$E$4,0,SUMIFS('Carton Entry'!$D$7:$D$5006,'Carton Entry'!$B$7:$B$5006,$B15,'Carton Entry'!$A$7:$A$5006,">="&'Carton Stock'!$E$4,'Carton Entry'!$A$7:$A$5006,"<="&Stock!$E$3))) | I15: =IF(OR($B15="",$C15=""),"",$C15+$F15-$G15+$H15) | K15: =IF($B15="","",IF($C15="","Count needed",IF($I15<0,"Negative — check",IF(AND($J15<>"",$I15<=$J15),"Reorder","OK")))) | L15: =IF($I15="","",IF($I15<=0,0,IF(N($O15)<=0,"—",ROUNDDOWN($I15/$O15,0)))) | O15: =IF($B15="","",SUMIF(Packing!$D$8:$D$101,$B15,Packing!$Q$8:$Q$101)/$P$4) | P15: =IF($B15="",0,IF(COUNTIF($B$8:$B$47,$B15)>1,1,0))
A16: Tuna | B16: Tuna carton | D16: =IF($B16="","",IF(Stock!$E$3<'Carton Stock'!$E$4,0,SUMIFS('Carton Entry'!$C$7:$C$5006,'Carton Entry'!$B$7:$B$5006,$B16,'Carton Entry'!$A$7:$A$5006,Stock!$E$3))) | E16: =IF($B16="","",SUMIF(Packing!$D$8:$D$101,$B16,Packing!$I$8:$I$101)) | F16: =IF($B16="","",IF(Stock!$E$3<'Carton Stock'!$E$4,0,SUMIFS('Carton Entry'!$C$7:$C$5006,'Carton Entry'!$B$7:$B$5006,$B16,'Carton Entry'!$A$7:$A$5006,">="&'Carton Stock'!$E$4,'Carton Entry'!$A$7:$A$5006,"<="&Stock!$E$3))) | G16: =IF($B16="","",SUMIF(Packing!$D$8:$D$101,$B16,Packing!$G$8:$G$101)) | H16: =IF($B16="","",IF(Stock!$E$3<'Carton Stock'!$E$4,0,SUMIFS('Carton Entry'!$D$7:$D$5006,'Carton Entry'!$B$7:$B$5006,$B16,'Carton Entry'!$A$7:$A$5006,">="&'Carton Stock'!$E$4,'Carton Entry'!$A$7:$A$5006,"<="&Stock!$E$3))) | I16: =IF(OR($B16="",$C16=""),"",$C16+$F16-$G16+$H16) | K16: =IF($B16="","",IF($C16="","Count needed",IF($I16<0,"Negative — check",IF(AND($J16<>"",$I16<=$J16),"Reorder","OK")))) | L16: =IF($I16="","",IF($I16<=0,0,IF(N($O16)<=0,"—",ROUNDDOWN($I16/$O16,0)))) | O16: =IF($B16="","",SUMIF(Packing!$D$8:$D$101,$B16,Packing!$Q$8:$Q$101)/$P$4) | P16: =IF($B16="",0,IF(COUNTIF($B$8:$B$47,$B16)>1,1,0))
A17: Mackerel | B17: Mackerel carton | D17: =IF($B17="","",IF(Stock!$E$3<'Carton Stock'!$E$4,0,SUMIFS('Carton Entry'!$C$7:$C$5006,'Carton Entry'!$B$7:$B$5006,$B17,'Carton Entry'!$A$7:$A$5006,Stock!$E$3))) | E17: =IF($B17="","",SUMIF(Packing!$D$8:$D$101,$B17,Packing!$I$8:$I$101)) | F17: =IF($B17="","",IF(Stock!$E$3<'Carton Stock'!$E$4,0,SUMIFS('Carton Entry'!$C$7:$C$5006,'Carton Entry'!$B$7:$B$5006,$B17,'Carton Entry'!$A$7:$A$5006,">="&'Carton Stock'!$E$4,'Carton Entry'!$A$7:$A$5006,"<="&Stock!$E$3))) | G17: =IF($B17="","",SUMIF(Packing!$D$8:$D$101,$B17,Packing!$G$8:$G$101)) | H17: =IF($B17="","",IF(Stock!$E$3<'Carton Stock'!$E$4,0,SUMIFS('Carton Entry'!$D$7:$D$5006,'Carton Entry'!$B$7:$B$5006,$B17,'Carton Entry'!$A$7:$A$5006,">="&'Carton Stock'!$E$4,'Carton Entry'!$A$7:$A$5006,"<="&Stock!$E$3))) | I17: =IF(OR($B17="",$C17=""),"",$C17+$F17-$G17+$H17) | K17: =IF($B17="","",IF($C17="","Count needed",IF($I17<0,"Negative — check",IF(AND($J17<>"",$I17<=$J17),"Reorder","OK")))) | L17: =IF($I17="","",IF($I17<=0,0,IF(N($O17)<=0,"—",ROUNDDOWN($I17/$O17,0)))) | O17: =IF($B17="","",SUMIF(Packing!$D$8:$D$101,$B17,Packing!$Q$8:$Q$101)/$P$4) | P17: =IF($B17="",0,IF(COUNTIF($B$8:$B$47,$B17)>1,1,0))
A18: Cuttlefish | B18: Cuttlefish carton | D18: =IF($B18="","",IF(Stock!$E$3<'Carton Stock'!$E$4,0,SUMIFS('Carton Entry'!$C$7:$C$5006,'Carton Entry'!$B$7:$B$5006,$B18,'Carton Entry'!$A$7:$A$5006,Stock!$E$3))) | E18: =IF($B18="","",SUMIF(Packing!$D$8:$D$101,$B18,Packing!$I$8:$I$101)) | F18: =IF($B18="","",IF(Stock!$E$3<'Carton Stock'!$E$4,0,SUMIFS('Carton Entry'!$C$7:$C$5006,'Carton Entry'!$B$7:$B$5006,$B18,'Carton Entry'!$A$7:$A$5006,">="&'Carton Stock'!$E$4,'Carton Entry'!$A$7:$A$5006,"<="&Stock!$E$3))) | G18: =IF($B18="","",SUMIF(Packing!$D$8:$D$101,$B18,Packing!$G$8:$G$101)) | H18: =IF($B18="","",IF(Stock!$E$3<'Carton Stock'!$E$4,0,SUMIFS('Carton Entry'!$D$7:$D$5006,'Carton Entry'!$B$7:$B$5006,$B18,'Carton Entry'!$A$7:$A$5006,">="&'Carton Stock'!$E$4,'Carton Entry'!$A$7:$A$5006,"<="&Stock!$E$3))) | I18: =IF(OR($B18="",$C18=""),"",$C18+$F18-$G18+$H18) | K18: =IF($B18="","",IF($C18="","Count needed",IF($I18<0,"Negative — check",IF(AND($J18<>"",$I18<=$J18),"Reorder","OK")))) | L18: =IF($I18="","",IF($I18<=0,0,IF(N($O18)<=0,"—",ROUNDDOWN($I18/$O18,0)))) | O18: =IF($B18="","",SUMIF(Packing!$D$8:$D$101,$B18,Packing!$Q$8:$Q$101)/$P$4) | P18: =IF($B18="",0,IF(COUNTIF($B$8:$B$47,$B18)>1,1,0))
A19: White Squid | B19: White Squid carton | D19: =IF($B19="","",IF(Stock!$E$3<'Carton Stock'!$E$4,0,SUMIFS('Carton Entry'!$C$7:$C$5006,'Carton Entry'!$B$7:$B$5006,$B19,'Carton Entry'!$A$7:$A$5006,Stock!$E$3))) | E19: =IF($B19="","",SUMIF(Packing!$D$8:$D$101,$B19,Packing!$I$8:$I$101)) | F19: =IF($B19="","",IF(Stock!$E$3<'Carton Stock'!$E$4,0,SUMIFS('Carton Entry'!$C$7:$C$5006,'Carton Entry'!$B$7:$B$5006,$B19,'Carton Entry'!$A$7:$A$5006,">="&'Carton Stock'!$E$4,'Carton Entry'!$A$7:$A$5006,"<="&Stock!$E$3))) | G19: =IF($B19="","",SUMIF(Packing!$D$8:$D$101,$B19,Packing!$G$8:$G$101)) | H19: =IF($B19="","",IF(Stock!$E$3<'Carton Stock'!$E$4,0,SUMIFS('Carton Entry'!$D$7:$D$5006,'Carton Entry'!$B$7:$B$5006,$B19,'Carton Entry'!$A$7:$A$5006,">="&'Carton Stock'!$E$4,'Carton Entry'!$A$7:$A$5006,"<="&Stock!$E$3))) | I19: =IF(OR($B19="",$C19=""),"",$C19+$F19-$G19+$H19) | K19: =IF($B19="","",IF($C19="","Count needed",IF($I19<0,"Negative — check",IF(AND($J19<>"",$I19<=$J19),"Reorder","OK")))) | L19: =IF($I19="","",IF($I19<=0,0,IF(N($O19)<=0,"—",ROUNDDOWN($I19/$O19,0)))) | O19: =IF($B19="","",SUMIF(Packing!$D$8:$D$101,$B19,Packing!$Q$8:$Q$101)/$P$4) | P19: =IF($B19="",0,IF(COUNTIF($B$8:$B$47,$B19)>1,1,0))
A20: Semi Needle Squid | B20: Semi Needle Squid carton | D20: =IF($B20="","",IF(Stock!$E$3<'Carton Stock'!$E$4,0,SUMIFS('Carton Entry'!$C$7:$C$5006,'Carton Entry'!$B$7:$B$5006,$B20,'Carton Entry'!$A$7:$A$5006,Stock!$E$3))) | E20: =IF($B20="","",SUMIF(Packing!$D$8:$D$101,$B20,Packing!$I$8:$I$101)) | F20: =IF($B20="","",IF(Stock!$E$3<'Carton Stock'!$E$4,0,SUMIFS('Carton Entry'!$C$7:$C$5006,'Carton Entry'!$B$7:$B$5006,$B20,'Carton Entry'!$A$7:$A$5006,">="&'Carton Stock'!$E$4,'Carton Entry'!$A$7:$A$5006,"<="&Stock!$E$3))) | G20: =IF($B20="","",SUMIF(Packing!$D$8:$D$101,$B20,Packing!$G$8:$G$101)) | H20: =IF($B20="","",IF(Stock!$E$3<'Carton Stock'!$E$4,0,SUMIFS('Carton Entry'!$D$7:$D$5006,'Carton Entry'!$B$7:$B$5006,$B20,'Carton Entry'!$A$7:$A$5006,">="&'Carton Stock'!$E$4,'Carton Entry'!$A$7:$A$5006,"<="&Stock!$E$3))) | I20: =IF(OR($B20="",$C20=""),"",$C20+$F20-$G20+$H20) | K20: =IF($B20="","",IF($C20="","Count needed",IF($I20<0,"Negative — check",IF(AND($J20<>"",$I20<=$J20),"Reorder","OK")))) | L20: =IF($I20="","",IF($I20<=0,0,IF(N($O20)<=0,"—",ROUNDDOWN($I20/$O20,0)))) | O20: =IF($B20="","",SUMIF(Packing!$D$8:$D$101,$B20,Packing!$Q$8:$Q$101)/$P$4) | P20: =IF($B20="",0,IF(COUNTIF($B$8:$B$47,$B20)>1,1,0))
D21: =IF($B21="","",IF(Stock!$E$3<'Carton Stock'!$E$4,0,SUMIFS('Carton Entry'!$C$7:$C$5006,'Carton Entry'!$B$7:$B$5006,$B21,'Carton Entry'!$A$7:$A$5006,Stock!$E$3))) | E21: =IF($B21="","",SUMIF(Packing!$D$8:$D$101,$B21,Packing!$I$8:$I$101)) | F21: =IF($B21="","",IF(Stock!$E$3<'Carton Stock'!$E$4,0,SUMIFS('Carton Entry'!$C$7:$C$5006,'Carton Entry'!$B$7:$B$5006,$B21,'Carton Entry'!$A$7:$A$5006,">="&'Carton Stock'!$E$4,'Carton Entry'!$A$7:$A$5006,"<="&Stock!$E$3))) | G21: =IF($B21="","",SUMIF(Packing!$D$8:$D$101,$B21,Packing!$G$8:$G$101)) | H21: =IF($B21="","",IF(Stock!$E$3<'Carton Stock'!$E$4,0,SUMIFS('Carton Entry'!$D$7:$D$5006,'Carton Entry'!$B$7:$B$5006,$B21,'Carton Entry'!$A$7:$A$5006,">="&'Carton Stock'!$E$4,'Carton Entry'!$A$7:$A$5006,"<="&Stock!$E$3))) | I21: =IF(OR($B21="",$C21=""),"",$C21+$F21-$G21+$H21) | K21: =IF($B21="","",IF($C21="","Count needed",IF($I21<0,"Negative — check",IF(AND($J21<>"",$I21<=$J21),"Reorder","OK")))) | L21: =IF($I21="","",IF($I21<=0,0,IF(N($O21)<=0,"—",ROUNDDOWN($I21/$O21,0)))) | O21: =IF($B21="","",SUMIF(Packing!$D$8:$D$101,$B21,Packing!$Q$8:$Q$101)/$P$4) | P21: =IF($B21="",0,IF(COUNTIF($B$8:$B$47,$B21)>1,1,0))
D22: =IF($B22="","",IF(Stock!$E$3<'Carton Stock'!$E$4,0,SUMIFS('Carton Entry'!$C$7:$C$5006,'Carton Entry'!$B$7:$B$5006,$B22,'Carton Entry'!$A$7:$A$5006,Stock!$E$3))) | E22: =IF($B22="","",SUMIF(Packing!$D$8:$D$101,$B22,Packing!$I$8:$I$101)) | F22: =IF($B22="","",IF(Stock!$E$3<'Carton Stock'!$E$4,0,SUMIFS('Carton Entry'!$C$7:$C$5006,'Carton Entry'!$B$7:$B$5006,$B22,'Carton Entry'!$A$7:$A$5006,">="&'Carton Stock'!$E$4,'Carton Entry'!$A$7:$A$5006,"<="&Stock!$E$3))) | G22: =IF($B22="","",SUMIF(Packing!$D$8:$D$101,$B22,Packing!$G$8:$G$101)) | H22: =IF($B22="","",IF(Stock!$E$3<'Carton Stock'!$E$4,0,SUMIFS('Carton Entry'!$D$7:$D$5006,'Carton Entry'!$B$7:$B$5006,$B22,'Carton Entry'!$A$7:$A$5006,">="&'Carton Stock'!$E$4,'Carton Entry'!$A$7:$A$5006,"<="&Stock!$E$3))) | I22: =IF(OR($B22="",$C22=""),"",$C22+$F22-$G22+$H22) | K22: =IF($B22="","",IF($C22="","Count needed",IF($I22<0,"Negative — check",IF(AND($J22<>"",$I22<=$J22),"Reorder","OK")))) | L22: =IF($I22="","",IF($I22<=0,0,IF(N($O22)<=0,"—",ROUNDDOWN($I22/$O22,0)))) | O22: =IF($B22="","",SUMIF(Packing!$D$8:$D$101,$B22,Packing!$Q$8:$Q$101)/$P$4) | P22: =IF($B22="",0,IF(COUNTIF($B$8:$B$47,$B22)>1,1,0))
D23: =IF($B23="","",IF(Stock!$E$3<'Carton Stock'!$E$4,0,SUMIFS('Carton Entry'!$C$7:$C$5006,'Carton Entry'!$B$7:$B$5006,$B23,'Carton Entry'!$A$7:$A$5006,Stock!$E$3))) | E23: =IF($B23="","",SUMIF(Packing!$D$8:$D$101,$B23,Packing!$I$8:$I$101)) | F23: =IF($B23="","",IF(Stock!$E$3<'Carton Stock'!$E$4,0,SUMIFS('Carton Entry'!$C$7:$C$5006,'Carton Entry'!$B$7:$B$5006,$B23,'Carton Entry'!$A$7:$A$5006,">="&'Carton Stock'!$E$4,'Carton Entry'!$A$7:$A$5006,"<="&Stock!$E$3))) | G23: =IF($B23="","",SUMIF(Packing!$D$8:$D$101,$B23,Packing!$G$8:$G$101)) | H23: =IF($B23="","",IF(Stock!$E$3<'Carton Stock'!$E$4,0,SUMIFS('Carton Entry'!$D$7:$D$5006,'Carton Entry'!$B$7:$B$5006,$B23,'Carton Entry'!$A$7:$A$5006,">="&'Carton Stock'!$E$4,'Carton Entry'!$A$7:$A$5006,"<="&Stock!$E$3))) | I23: =IF(OR($B23="",$C23=""),"",$C23+$F23-$G23+$H23) | K23: =IF($B23="","",IF($C23="","Count needed",IF($I23<0,"Negative — check",IF(AND($J23<>"",$I23<=$J23),"Reorder","OK")))) | L23: =IF($I23="","",IF($I23<=0,0,IF(N($O23)<=0,"—",ROUNDDOWN($I23/$O23,0)))) | O23: =IF($B23="","",SUMIF(Packing!$D$8:$D$101,$B23,Packing!$Q$8:$Q$101)/$P$4) | P23: =IF($B23="",0,IF(COUNTIF($B$8:$B$47,$B23)>1,1,0))
D24: =IF($B24="","",IF(Stock!$E$3<'Carton Stock'!$E$4,0,SUMIFS('Carton Entry'!$C$7:$C$5006,'Carton Entry'!$B$7:$B$5006,$B24,'Carton Entry'!$A$7:$A$5006,Stock!$E$3))) | E24: =IF($B24="","",SUMIF(Packing!$D$8:$D$101,$B24,Packing!$I$8:$I$101)) | F24: =IF($B24="","",IF(Stock!$E$3<'Carton Stock'!$E$4,0,SUMIFS('Carton Entry'!$C$7:$C$5006,'Carton Entry'!$B$7:$B$5006,$B24,'Carton Entry'!$A$7:$A$5006,">="&'Carton Stock'!$E$4,'Carton Entry'!$A$7:$A$5006,"<="&Stock!$E$3))) | G24: =IF($B24="","",SUMIF(Packing!$D$8:$D$101,$B24,Packing!$G$8:$G$101)) | H24: =IF($B24="","",IF(Stock!$E$3<'Carton Stock'!$E$4,0,SUMIFS('Carton Entry'!$D$7:$D$5006,'Carton Entry'!$B$7:$B$5006,$B24,'Carton Entry'!$A$7:$A$5006,">="&'Carton Stock'!$E$4,'Carton Entry'!$A$7:$A$5006,"<="&Stock!$E$3))) | I24: =IF(OR($B24="",$C24=""),"",$C24+$F24-$G24+$H24) | K24: =IF($B24="","",IF($C24="","Count needed",IF($I24<0,"Negative — check",IF(AND($J24<>"",$I24<=$J24),"Reorder","OK")))) | L24: =IF($I24="","",IF($I24<=0,0,IF(N($O24)<=0,"—",ROUNDDOWN($I24/$O24,0)))) | O24: =IF($B24="","",SUMIF(Packing!$D$8:$D$101,$B24,Packing!$Q$8:$Q$101)/$P$4) | P24: =IF($B24="",0,IF(COUNTIF($B$8:$B$47,$B24)>1,1,0))
D25: =IF($B25="","",IF(Stock!$E$3<'Carton Stock'!$E$4,0,SUMIFS('Carton Entry'!$C$7:$C$5006,'Carton Entry'!$B$7:$B$5006,$B25,'Carton Entry'!$A$7:$A$5006,Stock!$E$3))) | E25: =IF($B25="","",SUMIF(Packing!$D$8:$D$101,$B25,Packing!$I$8:$I$101)) | F25: =IF($B25="","",IF(Stock!$E$3<'Carton Stock'!$E$4,0,SUMIFS('Carton Entry'!$C$7:$C$5006,'Carton Entry'!$B$7:$B$5006,$B25,'Carton Entry'!$A$7:$A$5006,">="&'Carton Stock'!$E$4,'Carton Entry'!$A$7:$A$5006,"<="&Stock!$E$3))) | G25: =IF($B25="","",SUMIF(Packing!$D$8:$D$101,$B25,Packing!$G$8:$G$101)) | H25: =IF($B25="","",IF(Stock!$E$3<'Carton Stock'!$E$4,0,SUMIFS('Carton Entry'!$D$7:$D$5006,'Carton Entry'!$B$7:$B$5006,$B25,'Carton Entry'!$A$7:$A$5006,">="&'Carton Stock'!$E$4,'Carton Entry'!$A$7:$A$5006,"<="&Stock!$E$3))) | I25: =IF(OR($B25="",$C25=""),"",$C25+$F25-$G25+$H25) | K25: =IF($B25="","",IF($C25="","Count needed",IF($I25<0,"Negative — check",IF(AND($J25<>"",$I25<=$J25),"Reorder","OK")))) | L25: =IF($I25="","",IF($I25<=0,0,IF(N($O25)<=0,"—",ROUNDDOWN($I25/$O25,0)))) | O25: =IF($B25="","",SUMIF(Packing!$D$8:$D$101,$B25,Packing!$Q$8:$Q$101)/$P$4) | P25: =IF($B25="",0,IF(COUNTIF($B$8:$B$47,$B25)>1,1,0))
D26: =IF($B26="","",IF(Stock!$E$3<'Carton Stock'!$E$4,0,SUMIFS('Carton Entry'!$C$7:$C$5006,'Carton Entry'!$B$7:$B$5006,$B26,'Carton Entry'!$A$7:$A$5006,Stock!$E$3))) | E26: =IF($B26="","",SUMIF(Packing!$D$8:$D$101,$B26,Packing!$I$8:$I$101)) | F26: =IF($B26="","",IF(Stock!$E$3<'Carton Stock'!$E$4,0,SUMIFS('Carton Entry'!$C$7:$C$5006,'Carton Entry'!$B$7:$B$5006,$B26,'Carton Entry'!$A$7:$A$5006,">="&'Carton Stock'!$E$4,'Carton Entry'!$A$7:$A$5006,"<="&Stock!$E$3))) | G26: =IF($B26="","",SUMIF(Packing!$D$8:$D$101,$B26,Packing!$G$8:$G$101)) | H26: =IF($B26="","",IF(Stock!$E$3<'Carton Stock'!$E$4,0,SUMIFS('Carton Entry'!$D$7:$D$5006,'Carton Entry'!$B$7:$B$5006,$B26,'Carton Entry'!$A$7:$A$5006,">="&'Carton Stock'!$E$4,'Carton Entry'!$A$7:$A$5006,"<="&Stock!$E$3))) | I26: =IF(OR($B26="",$C26=""),"",$C26+$F26-$G26+$H26) | K26: =IF($B26="","",IF($C26="","Count needed",IF($I26<0,"Negative — check",IF(AND($J26<>"",$I26<=$J26),"Reorder","OK")))) | L26: =IF($I26="","",IF($I26<=0,0,IF(N($O26)<=0,"—",ROUNDDOWN($I26/$O26,0)))) | O26: =IF($B26="","",SUMIF(Packing!$D$8:$D$101,$B26,Packing!$Q$8:$Q$101)/$P$4) | P26: =IF($B26="",0,IF(COUNTIF($B$8:$B$47,$B26)>1,1,0))
D27: =IF($B27="","",IF(Stock!$E$3<'Carton Stock'!$E$4,0,SUMIFS('Carton Entry'!$C$7:$C$5006,'Carton Entry'!$B$7:$B$5006,$B27,'Carton Entry'!$A$7:$A$5006,Stock!$E$3))) | E27: =IF($B27="","",SUMIF(Packing!$D$8:$D$101,$B27,Packing!$I$8:$I$101)) | F27: =IF($B27="","",IF(Stock!$E$3<'Carton Stock'!$E$4,0,SUMIFS('Carton Entry'!$C$7:$C$5006,'Carton Entry'!$B$7:$B$5006,$B27,'Carton Entry'!$A$7:$A$5006,">="&'Carton Stock'!$E$4,'Carton Entry'!$A$7:$A$5006,"<="&Stock!$E$3))) | G27: =IF($B27="","",SUMIF(Packing!$D$8:$D$101,$B27,Packing!$G$8:$G$101)) | H27: =IF($B27="","",IF(Stock!$E$3<'Carton Stock'!$E$4,0,SUMIFS('Carton Entry'!$D$7:$D$5006,'Carton Entry'!$B$7:$B$5006,$B27,'Carton Entry'!$A$7:$A$5006,">="&'Carton Stock'!$E$4,'Carton Entry'!$A$7:$A$5006,"<="&Stock!$E$3))) | I27: =IF(OR($B27="",$C27=""),"",$C27+$F27-$G27+$H27) | K27: =IF($B27="","",IF($C27="","Count needed",IF($I27<0,"Negative — check",IF(AND($J27<>"",$I27<=$J27),"Reorder","OK")))) | L27: =IF($I27="","",IF($I27<=0,0,IF(N($O27)<=0,"—",ROUNDDOWN($I27/$O27,0)))) | O27: =IF($B27="","",SUMIF(Packing!$D$8:$D$101,$B27,Packing!$Q$8:$Q$101)/$P$4) | P27: =IF($B27="",0,IF(COUNTIF($B$8:$B$47,$B27)>1,1,0))
D28: =IF($B28="","",IF(Stock!$E$3<'Carton Stock'!$E$4,0,SUMIFS('Carton Entry'!$C$7:$C$5006,'Carton Entry'!$B$7:$B$5006,$B28,'Carton Entry'!$A$7:$A$5006,Stock!$E$3))) | E28: =IF($B28="","",SUMIF(Packing!$D$8:$D$101,$B28,Packing!$I$8:$I$101)) | F28: =IF($B28="","",IF(Stock!$E$3<'Carton Stock'!$E$4,0,SUMIFS('Carton Entry'!$C$7:$C$5006,'Carton Entry'!$B$7:$B$5006,$B28,'Carton Entry'!$A$7:$A$5006,">="&'Carton Stock'!$E$4,'Carton Entry'!$A$7:$A$5006,"<="&Stock!$E$3))) | G28: =IF($B28="","",SUMIF(Packing!$D$8:$D$101,$B28,Packing!$G$8:$G$101)) | H28: =IF($B28="","",IF(Stock!$E$3<'Carton Stock'!$E$4,0,SUMIFS('Carton Entry'!$D$7:$D$5006,'Carton Entry'!$B$7:$B$5006,$B28,'Carton Entry'!$A$7:$A$5006,">="&'Carton Stock'!$E$4,'Carton Entry'!$A$7:$A$5006,"<="&Stock!$E$3))) | I28: =IF(OR($B28="",$C28=""),"",$C28+$F28-$G28+$H28) | K28: =IF($B28="","",IF($C28="","Count needed",IF($I28<0,"Negative — check",IF(AND($J28<>"",$I28<=$J28),"Reorder","OK")))) | L28: =IF($I28="","",IF($I28<=0,0,IF(N($O28)<=0,"—",ROUNDDOWN($I28/$O28,0)))) | O28: =IF($B28="","",SUMIF(Packing!$D$8:$D$101,$B28,Packing!$Q$8:$Q$101)/$P$4) | P28: =IF($B28="",0,IF(COUNTIF($B$8:$B$47,$B28)>1,1,0))
D29: =IF($B29="","",IF(Stock!$E$3<'Carton Stock'!$E$4,0,SUMIFS('Carton Entry'!$C$7:$C$5006,'Carton Entry'!$B$7:$B$5006,$B29,'Carton Entry'!$A$7:$A$5006,Stock!$E$3))) | E29: =IF($B29="","",SUMIF(Packing!$D$8:$D$101,$B29,Packing!$I$8:$I$101)) | F29: =IF($B29="","",IF(Stock!$E$3<'Carton Stock'!$E$4,0,SUMIFS('Carton Entry'!$C$7:$C$5006,'Carton Entry'!$B$7:$B$5006,$B29,'Carton Entry'!$A$7:$A$5006,">="&'Carton Stock'!$E$4,'Carton Entry'!$A$7:$A$5006,"<="&Stock!$E$3))) | G29: =IF($B29="","",SUMIF(Packing!$D$8:$D$101,$B29,Packing!$G$8:$G$101)) | H29: =IF($B29="","",IF(Stock!$E$3<'Carton Stock'!$E$4,0,SUMIFS('Carton Entry'!$D$7:$D$5006,'Carton Entry'!$B$7:$B$5006,$B29,'Carton Entry'!$A$7:$A$5006,">="&'Carton Stock'!$E$4,'Carton Entry'!$A$7:$A$5006,"<="&Stock!$E$3))) | I29: =IF(OR($B29="",$C29=""),"",$C29+$F29-$G29+$H29) | K29: =IF($B29="","",IF($C29="","Count needed",IF($I29<0,"Negative — check",IF(AND($J29<>"",$I29<=$J29),"Reorder","OK")))) | L29: =IF($I29="","",IF($I29<=0,0,IF(N($O29)<=0,"—",ROUNDDOWN($I29/$O29,0)))) | O29: =IF($B29="","",SUMIF(Packing!$D$8:$D$101,$B29,Packing!$Q$8:$Q$101)/$P$4) | P29: =IF($B29="",0,IF(COUNTIF($B$8:$B$47,$B29)>1,1,0))
D30: =IF($B30="","",IF(Stock!$E$3<'Carton Stock'!$E$4,0,SUMIFS('Carton Entry'!$C$7:$C$5006,'Carton Entry'!$B$7:$B$5006,$B30,'Carton Entry'!$A$7:$A$5006,Stock!$E$3))) | E30: =IF($B30="","",SUMIF(Packing!$D$8:$D$101,$B30,Packing!$I$8:$I$101)) | F30: =IF($B30="","",IF(Stock!$E$3<'Carton Stock'!$E$4,0,SUMIFS('Carton Entry'!$C$7:$C$5006,'Carton Entry'!$B$7:$B$5006,$B30,'Carton Entry'!$A$7:$A$5006,">="&'Carton Stock'!$E$4,'Carton Entry'!$A$7:$A$5006,"<="&Stock!$E$3))) | G30: =IF($B30="","",SUMIF(Packing!$D$8:$D$101,$B30,Packing!$G$8:$G$101)) | H30: =IF($B30="","",IF(Stock!$E$3<'Carton Stock'!$E$4,0,SUMIFS('Carton Entry'!$D$7:$D$5006,'Carton Entry'!$B$7:$B$5006,$B30,'Carton Entry'!$A$7:$A$5006,">="&'Carton Stock'!$E$4,'Carton Entry'!$A$7:$A$5006,"<="&Stock!$E$3))) | I30: =IF(OR($B30="",$C30=""),"",$C30+$F30-$G30+$H30) | K30: =IF($B30="","",IF($C30="","Count needed",IF($I30<0,"Negative — check",IF(AND($J30<>"",$I30<=$J30),"Reorder","OK")))) | L30: =IF($I30="","",IF($I30<=0,0,IF(N($O30)<=0,"—",ROUNDDOWN($I30/$O30,0)))) | O30: =IF($B30="","",SUMIF(Packing!$D$8:$D$101,$B30,Packing!$Q$8:$Q$101)/$P$4) | P30: =IF($B30="",0,IF(COUNTIF($B$8:$B$47,$B30)>1,1,0))
D31: =IF($B31="","",IF(Stock!$E$3<'Carton Stock'!$E$4,0,SUMIFS('Carton Entry'!$C$7:$C$5006,'Carton Entry'!$B$7:$B$5006,$B31,'Carton Entry'!$A$7:$A$5006,Stock!$E$3))) | E31: =IF($B31="","",SUMIF(Packing!$D$8:$D$101,$B31,Packing!$I$8:$I$101)) | F31: =IF($B31="","",IF(Stock!$E$3<'Carton Stock'!$E$4,0,SUMIFS('Carton Entry'!$C$7:$C$5006,'Carton Entry'!$B$7:$B$5006,$B31,'Carton Entry'!$A$7:$A$5006,">="&'Carton Stock'!$E$4,'Carton Entry'!$A$7:$A$5006,"<="&Stock!$E$3))) | G31: =IF($B31="","",SUMIF(Packing!$D$8:$D$101,$B31,Packing!$G$8:$G$101)) | H31: =IF($B31="","",IF(Stock!$E$3<'Carton Stock'!$E$4,0,SUMIFS('Carton Entry'!$D$7:$D$5006,'Carton Entry'!$B$7:$B$5006,$B31,'Carton Entry'!$A$7:$A$5006,">="&'Carton Stock'!$E$4,'Carton Entry'!$A$7:$A$5006,"<="&Stock!$E$3))) | I31: =IF(OR($B31="",$C31=""),"",$C31+$F31-$G31+$H31) | K31: =IF($B31="","",IF($C31="","Count needed",IF($I31<0,"Negative — check",IF(AND($J31<>"",$I31<=$J31),"Reorder","OK")))) | L31: =IF($I31="","",IF($I31<=0,0,IF(N($O31)<=0,"—",ROUNDDOWN($I31/$O31,0)))) | O31: =IF($B31="","",SUMIF(Packing!$D$8:$D$101,$B31,Packing!$Q$8:$Q$101)/$P$4) | P31: =IF($B31="",0,IF(COUNTIF($B$8:$B$47,$B31)>1,1,0))
D32: =IF($B32="","",IF(Stock!$E$3<'Carton Stock'!$E$4,0,SUMIFS('Carton Entry'!$C$7:$C$5006,'Carton Entry'!$B$7:$B$5006,$B32,'Carton Entry'!$A$7:$A$5006,Stock!$E$3))) | E32: =IF($B32="","",SUMIF(Packing!$D$8:$D$101,$B32,Packing!$I$8:$I$101)) | F32: =IF($B32="","",IF(Stock!$E$3<'Carton Stock'!$E$4,0,SUMIFS('Carton Entry'!$C$7:$C$5006,'Carton Entry'!$B$7:$B$5006,$B32,'Carton Entry'!$A$7:$A$5006,">="&'Carton Stock'!$E$4,'Carton Entry'!$A$7:$A$5006,"<="&Stock!$E$3))) | G32: =IF($B32="","",SUMIF(Packing!$D$8:$D$101,$B32,Packing!$G$8:$G$101)) | H32: =IF($B32="","",IF(Stock!$E$3<'Carton Stock'!$E$4,0,SUMIFS('Carton Entry'!$D$7:$D$5006,'Carton Entry'!$B$7:$B$5006,$B32,'Carton Entry'!$A$7:$A$5006,">="&'Carton Stock'!$E$4,'Carton Entry'!$A$7:$A$5006,"<="&Stock!$E$3))) | I32: =IF(OR($B32="",$C32=""),"",$C32+$F32-$G32+$H32) | K32: =IF($B32="","",IF($C32="","Count needed",IF($I32<0,"Negative — check",IF(AND($J32<>"",$I32<=$J32),"Reorder","OK")))) | L32: =IF($I32="","",IF($I32<=0,0,IF(N($O32)<=0,"—",ROUNDDOWN($I32/$O32,0)))) | O32: =IF($B32="","",SUMIF(Packing!$D$8:$D$101,$B32,Packing!$Q$8:$Q$101)/$P$4) | P32: =IF($B32="",0,IF(COUNTIF($B$8:$B$47,$B32)>1,1,0))
... D47: =IF($B47="","",IF(Stock!$E$3<'Carton Stock'!$E$4,0,SUMIFS('Carton Entry'!$C$7:$C$5006,'Carton Entry'!$B$7:$B$5006,$B47,'Carton Entry'!$A$7:$A$5006,Stock!$E$3))) | E47: =IF($B47="","",SUMIF(Packing!$D$8:$D$101,$B47,Packing!$I$8:$I$101)) | F47: =IF($B47="","",IF(Stock!$E$3<'Carton Stock'!$E$4,0,SUMIFS('Carton Entry'!$C$7:$C$5006,'Carton Entry'!$B$7:$B$5006,$B47,'Carton Entry'!$A$7:$A$5006,">="&'Carton Stock'!$E$4,'Carton Entry'!$A$7:$A$5006,"<="&Stock!$E$3))) | G47: =IF($B47="","",SUMIF(Packing!$D$8:$D$101,$B47,Packing!$G$8:$G$101)) | H47: =IF($B47="","",IF(Stock!$E$3<'Carton Stock'!$E$4,0,SUMIFS('Carton Entry'!$D$7:$D$5006,'Carton Entry'!$B$7:$B$5006,$B47,'Carton Entry'!$A$7:$A$5006,">="&'Carton Stock'!$E$4,'Carton Entry'!$A$7:$A$5006,"<="&Stock!$E$3))) | I47: =IF(OR($B47="",$C47=""),"",$C47+$F47-$G47+$H47) | K47: =IF($B47="","",IF($C47="","Count needed",IF($I47<0,"Negative — check",IF(AND($J47<>"",$I47<=$J47),"Reorder","OK")))) | L47: =IF($I47="","",IF($I47<=0,0,IF(N($O47)<=0,"—",ROUNDDOWN($I47/$O47,0)))) | O47: =IF($B47="","",SUMIF(Packing!$D$8:$D$101,$B47,Packing!$Q$8:$Q$101)/$P$4) | P47: =IF($B47="",0,IF(COUNTIF($B$8:$B$47,$B47)>1,1,0))
A48: TOTAL (cartons) | C48: =SUM(C8:C47) | D48: =SUM(D8:D47) | E48: =SUM(E8:E47) | F48: =SUM(F8:F47) | G48: =SUM(G8:G47) | H48: =SUM(H8:H47) | I48: =SUM(I8:I47) | K48: =IF(COUNTIF($K$8:$K$47,"Reorder")=0,"",COUNTIF($K$8:$K$47,"Reorder")&" to reorder")
A50: =IF(SUM(Packing!$R$8:$R$101)=0,"",SUM(Packing!$R$8:$R$101)&" product(s) packed since the count have no carton or no Packed per Carton on Packing — their cartons are not taken off. Fill them in on Packing.")
A51: =IF(SUM(Packing!$S$8:$S$101)=0,"",SUM(Packing!$S$8:$S$101)&" product(s) on Packing name a carton that is not on this list — check the spelling.")
A52: =IF(SUMPRODUCT(('Carton Entry'!$B$7:$B$5006<>"")*(COUNTIF($B$8:$B$47,'Carton Entry'!$B$7:$B$5006)=0))=0,"",SUMPRODUCT(('Carton Entry'!$B$7:$B$5006<>"")*(COUNTIF($B$8:$B$47,'Carton Entry'!$B$7:$B$5006)=0))&" row(s) on Carton Entry name a carton that is not on this list — they are not counted.")
A53: =IF(SUM($P$8:$P$47)=0,"","Two rows share a carton name — deliveries and usage would be counted on both. Rename one.")
A54: =IF(Stock!$E$3<'Carton Stock'!$E$4,"The Statement Date on Stock is before the Count Date — nothing after the count is counted yet.","")
A55: =IF(SUM(Packing!$T$8:$T$101)=0,"",SUM(Packing!$T$8:$T$101)&" product(s) on Packing have no carton size yet — fill them in before they are packed.")

Sheet Carton Entry
A1: PREMIER EXPORTS INTERNATIONAL
A2: CARTON ENTRY — ONE ROW PER DELIVERY OR ADJUSTMENT
A4: When cartons arrive, add a row: date, carton from the dropdown, number received. | G4: Rows that will not reach Carton Stock: | J4: =SUMPRODUCT((B7:B5006<>"")*(COUNTIF('Carton Stock'!$B$8:$B$47,B7:B5006)=0)) | K4: ← must stay at 0; anything else is a mistyped carton
A5: Damaged, or a recount differs: Adjustment, minus or plus. Packing is taken off by itself from production — never enter it here.
A6: Date | B6: Carton (pick from list) | C6: Received (cartons) | D6: Adjustment (+ / −) | E6: Supplier / Invoice No. | F6: Note

Sheet Packing
A1: PREMIER EXPORTS INTERNATIONAL
A2: PACKING — WHICH CARTON EACH PRODUCT GOES INTO
A4: Set once per product: the carton it is packed in, and how many units — slabs, or kilos for products counted in kilos — fill one carton. Products come from Stock by themselves.
A5: Cartons Used = Production since Count ÷ Packed per Carton, rounded up: a part-filled carton is a carton used.
A7: Brand | B7: Product | C7: Unit | D7: Carton (pick from list) | E7: Packed per Carton | F7: Production since Count | G7: Cartons Used | H7: Today's Production | I7: Cartons Used Today | O7: Key (do not edit) | P7: Production, last 30 days | Q7: Cartons, last 30 days | R7: Packed, no carton | S7: Carton not on list | T7: No carton set
A8: =IF(Stock!$A8="","",Stock!$A8) | B8: =IF(Stock!$A8="","",Stock!$B8) | C8: =IF(Stock!$A8="","",IF(Stock!$C8="","",Stock!$C8)) | D8: Blue Dolphin carton | E8: 10 | F8: =IF($A8="","",IF(Stock!$E$3<'Carton Stock'!$E$4,0,SUMIFS('Daily Entry'!$C$7:$C$10003,'Daily Entry'!$B$7:$B$10003,$O8,'Daily Entry'!$A$7:$A$10003,">="&'Carton Stock'!$E$4,'Daily Entry'!$A$7:$A$10003,"<="&Stock!$E$3))) | G8: =IF(OR($A8="",$D8="",N($E8)<=0),"",ROUNDUP($F8/$E8,0)) | H8: =IF($A8="","",IF(Stock!$E$3<'Carton Stock'!$E$4,0,SUMIFS('Daily Entry'!$C$7:$C$10003,'Daily Entry'!$B$7:$B$10003,$O8,'Daily Entry'!$A$7:$A$10003,Stock!$E$3))) | I8: =IF($G8="","",$G8-ROUNDUP(($F8-$H8)/$E8,0)) | O8: =IF(Stock!$A8="","",Stock!$O8) | P8: =IF($A8="",0,SUMIFS('Daily Entry'!$C$7:$C$10003,'Daily Entry'!$B$7:$B$10003,$O8,'Daily Entry'!$A$7:$A$10003,">="&MAX('Carton Stock'!$E$4,Stock!$E$3-29),'Daily Entry'!$A$7:$A$10003,"<="&Stock!$E$3)) | Q8: =IF(OR($A8="",$D8="",N($E8)<=0),0,$P8/$E8) | R8: =IF(AND($A8<>"",N($F8)>0,OR($D8="",N($E8)<=0)),1,0) | S8: =IF(AND($A8<>"",$D8<>""),IF(COUNTIF('Carton Stock'!$B$8:$B$47,$D8)=0,1,0),0) | T8: =IF(AND($A8<>"",OR($D8="",N($E8)<=0)),1,0)
A9: =IF(Stock!$A9="","",Stock!$A9) | B9: =IF(Stock!$A9="","",Stock!$B9) | C9: =IF(Stock!$A9="","",IF(Stock!$C9="","",Stock!$C9)) | D9: Blue Dolphin carton | E9: 10 | F9: =IF($A9="","",IF(Stock!$E$3<'Carton Stock'!$E$4,0,SUMIFS('Daily Entry'!$C$7:$C$10003,'Daily Entry'!$B$7:$B$10003,$O9,'Daily Entry'!$A$7:$A$10003,">="&'Carton Stock'!$E$4,'Daily Entry'!$A$7:$A$10003,"<="&Stock!$E$3))) | G9: =IF(OR($A9="",$D9="",N($E9)<=0),"",ROUNDUP($F9/$E9,0)) | H9: =IF($A9="","",IF(Stock!$E$3<'Carton Stock'!$E$4,0,SUMIFS('Daily Entry'!$C$7:$C$10003,'Daily Entry'!$B$7:$B$10003,$O9,'Daily Entry'!$A$7:$A$10003,Stock!$E$3))) | I9: =IF($G9="","",$G9-ROUNDUP(($F9-$H9)/$E9,0)) | O9: =IF(Stock!$A9="","",Stock!$O9) | P9: =IF($A9="",0,SUMIFS('Daily Entry'!$C$7:$C$10003,'Daily Entry'!$B$7:$B$10003,$O9,'Daily Entry'!$A$7:$A$10003,">="&MAX('Carton Stock'!$E$4,Stock!$E$3-29),'Daily Entry'!$A$7:$A$10003,"<="&Stock!$E$3)) | Q9: =IF(OR($A9="",$D9="",N($E9)<=0),0,$P9/$E9) | R9: =IF(AND($A9<>"",N($F9)>0,OR($D9="",N($E9)<=0)),1,0) | S9: =IF(AND($A9<>"",$D9<>""),IF(COUNTIF('Carton Stock'!$B$8:$B$47,$D9)=0,1,0),0) | T9: =IF(AND($A9<>"",OR($D9="",N($E9)<=0)),1,0)
A10: =IF(Stock!$A10="","",Stock!$A10) | B10: =IF(Stock!$A10="","",Stock!$B10) | C10: =IF(Stock!$A10="","",IF(Stock!$C10="","",Stock!$C10)) | D10: Blue Dolphin carton | E10: 10 | F10: =IF($A10="","",IF(Stock!$E$3<'Carton Stock'!$E$4,0,SUMIFS('Daily Entry'!$C$7:$C$10003,'Daily Entry'!$B$7:$B$10003,$O10,'Daily Entry'!$A$7:$A$10003,">="&'Carton Stock'!$E$4,'Daily Entry'!$A$7:$A$10003,"<="&Stock!$E$3))) | G10: =IF(OR($A10="",$D10="",N($E10)<=0),"",ROUNDUP($F10/$E10,0)) | H10: =IF($A10="","",IF(Stock!$E$3<'Carton Stock'!$E$4,0,SUMIFS('Daily Entry'!$C$7:$C$10003,'Daily Entry'!$B$7:$B$10003,$O10,'Daily Entry'!$A$7:$A$10003,Stock!$E$3))) | I10: =IF($G10="","",$G10-ROUNDUP(($F10-$H10)/$E10,0)) | O10: =IF(Stock!$A10="","",Stock!$O10) | P10: =IF($A10="",0,SUMIFS('Daily Entry'!$C$7:$C$10003,'Daily Entry'!$B$7:$B$10003,$O10,'Daily Entry'!$A$7:$A$10003,">="&MAX('Carton Stock'!$E$4,Stock!$E$3-29),'Daily Entry'!$A$7:$A$10003,"<="&Stock!$E$3)) | Q10: =IF(OR($A10="",$D10="",N($E10)<=0),0,$P10/$E10) | R10: =IF(AND($A10<>"",N($F10)>0,OR($D10="",N($E10)<=0)),1,0) | S10: =IF(AND($A10<>"",$D10<>""),IF(COUNTIF('Carton Stock'!$B$8:$B$47,$D10)=0,1,0),0) | T10: =IF(AND($A10<>"",OR($D10="",N($E10)<=0)),1,0)
A11: =IF(Stock!$A11="","",Stock!$A11) | B11: =IF(Stock!$A11="","",Stock!$B11) | C11: =IF(Stock!$A11="","",IF(Stock!$C11="","",Stock!$C11)) | D11: Blue Dolphin carton | E11: 10 | F11: =IF($A11="","",IF(Stock!$E$3<'Carton Stock'!$E$4,0,SUMIFS('Daily Entry'!$C$7:$C$10003,'Daily Entry'!$B$7:$B$10003,$O11,'Daily Entry'!$A$7:$A$10003,">="&'Carton Stock'!$E$4,'Daily Entry'!$A$7:$A$10003,"<="&Stock!$E$3))) | G11: =IF(OR($A11="",$D11="",N($E11)<=0),"",ROUNDUP($F11/$E11,0)) | H11: =IF($A11="","",IF(Stock!$E$3<'Carton Stock'!$E$4,0,SUMIFS('Daily Entry'!$C$7:$C$10003,'Daily Entry'!$B$7:$B$10003,$O11,'Daily Entry'!$A$7:$A$10003,Stock!$E$3))) | I11: =IF($G11="","",$G11-ROUNDUP(($F11-$H11)/$E11,0)) | O11: =IF(Stock!$A11="","",Stock!$O11) | P11: =IF($A11="",0,SUMIFS('Daily Entry'!$C$7:$C$10003,'Daily Entry'!$B$7:$B$10003,$O11,'Daily Entry'!$A$7:$A$10003,">="&MAX('Carton Stock'!$E$4,Stock!$E$3-29),'Daily Entry'!$A$7:$A$10003,"<="&Stock!$E$3)) | Q11: =IF(OR($A11="",$D11="",N($E11)<=0),0,$P11/$E11) | R11: =IF(AND($A11<>"",N($F11)>0,OR($D11="",N($E11)<=0)),1,0) | S11: =IF(AND($A11<>"",$D11<>""),IF(COUNTIF('Carton Stock'!$B$8:$B$47,$D11)=0,1,0),0) | T11: =IF(AND($A11<>"",OR($D11="",N($E11)<=0)),1,0)
A12: =IF(Stock!$A12="","",Stock!$A12) | B12: =IF(Stock!$A12="","",Stock!$B12) | C12: =IF(Stock!$A12="","",IF(Stock!$C12="","",Stock!$C12)) | D12: Blue Dolphin carton | E12: 10 | F12: =IF($A12="","",IF(Stock!$E$3<'Carton Stock'!$E$4,0,SUMIFS('Daily Entry'!$C$7:$C$10003,'Daily Entry'!$B$7:$B$10003,$O12,'Daily Entry'!$A$7:$A$10003,">="&'Carton Stock'!$E$4,'Daily Entry'!$A$7:$A$10003,"<="&Stock!$E$3))) | G12: =IF(OR($A12="",$D12="",N($E12)<=0),"",ROUNDUP($F12/$E12,0)) | H12: =IF($A12="","",IF(Stock!$E$3<'Carton Stock'!$E$4,0,SUMIFS('Daily Entry'!$C$7:$C$10003,'Daily Entry'!$B$7:$B$10003,$O12,'Daily Entry'!$A$7:$A$10003,Stock!$E$3))) | I12: =IF($G12="","",$G12-ROUNDUP(($F12-$H12)/$E12,0)) | O12: =IF(Stock!$A12="","",Stock!$O12) | P12: =IF($A12="",0,SUMIFS('Daily Entry'!$C$7:$C$10003,'Daily Entry'!$B$7:$B$10003,$O12,'Daily Entry'!$A$7:$A$10003,">="&MAX('Carton Stock'!$E$4,Stock!$E$3-29),'Daily Entry'!$A$7:$A$10003,"<="&Stock!$E$3)) | Q12: =IF(OR($A12="",$D12="",N($E12)<=0),0,$P12/$E12) | R12: =IF(AND($A12<>"",N($F12)>0,OR($D12="",N($E12)<=0)),1,0) | S12: =IF(AND($A12<>"",$D12<>""),IF(COUNTIF('Carton Stock'!$B$8:$B$47,$D12)=0,1,0),0) | T12: =IF(AND($A12<>"",OR($D12="",N($E12)<=0)),1,0)
A13: =IF(Stock!$A13="","",Stock!$A13) | B13: =IF(Stock!$A13="","",Stock!$B13) | C13: =IF(Stock!$A13="","",IF(Stock!$C13="","",Stock!$C13)) | D13: Blue Dolphin carton | E13: 10 | F13: =IF($A13="","",IF(Stock!$E$3<'Carton Stock'!$E$4,0,SUMIFS('Daily Entry'!$C$7:$C$10003,'Daily Entry'!$B$7:$B$10003,$O13,'Daily Entry'!$A$7:$A$10003,">="&'Carton Stock'!$E$4,'Daily Entry'!$A$7:$A$10003,"<="&Stock!$E$3))) | G13: =IF(OR($A13="",$D13="",N($E13)<=0),"",ROUNDUP($F13/$E13,0)) | H13: =IF($A13="","",IF(Stock!$E$3<'Carton Stock'!$E$4,0,SUMIFS('Daily Entry'!$C$7:$C$10003,'Daily Entry'!$B$7:$B$10003,$O13,'Daily Entry'!$A$7:$A$10003,Stock!$E$3))) | I13: =IF($G13="","",$G13-ROUNDUP(($F13-$H13)/$E13,0)) | O13: =IF(Stock!$A13="","",Stock!$O13) | P13: =IF($A13="",0,SUMIFS('Daily Entry'!$C$7:$C$10003,'Daily Entry'!$B$7:$B$10003,$O13,'Daily Entry'!$A$7:$A$10003,">="&MAX('Carton Stock'!$E$4,Stock!$E$3-29),'Daily Entry'!$A$7:$A$10003,"<="&Stock!$E$3)) | Q13: =IF(OR($A13="",$D13="",N($E13)<=0),0,$P13/$E13) | R13: =IF(AND($A13<>"",N($F13)>0,OR($D13="",N($E13)<=0)),1,0) | S13: =IF(AND($A13<>"",$D13<>""),IF(COUNTIF('Carton Stock'!$B$8:$B$47,$D13)=0,1,0),0) | T13: =IF(AND($A13<>"",OR($D13="",N($E13)<=0)),1,0)
A14: =IF(Stock!$A14="","",Stock!$A14) | B14: =IF(Stock!$A14="","",Stock!$B14) | C14: =IF(Stock!$A14="","",IF(Stock!$C14="","",Stock!$C14)) | D14: Blue Dolphin carton | E14: 10 | F14: =IF($A14="","",IF(Stock!$E$3<'Carton Stock'!$E$4,0,SUMIFS('Daily Entry'!$C$7:$C$10003,'Daily Entry'!$B$7:$B$10003,$O14,'Daily Entry'!$A$7:$A$10003,">="&'Carton Stock'!$E$4,'Daily Entry'!$A$7:$A$10003,"<="&Stock!$E$3))) | G14: =IF(OR($A14="",$D14="",N($E14)<=0),"",ROUNDUP($F14/$E14,0)) | H14: =IF($A14="","",IF(Stock!$E$3<'Carton Stock'!$E$4,0,SUMIFS('Daily Entry'!$C$7:$C$10003,'Daily Entry'!$B$7:$B$10003,$O14,'Daily Entry'!$A$7:$A$10003,Stock!$E$3))) | I14: =IF($G14="","",$G14-ROUNDUP(($F14-$H14)/$E14,0)) | O14: =IF(Stock!$A14="","",Stock!$O14) | P14: =IF($A14="",0,SUMIFS('Daily Entry'!$C$7:$C$10003,'Daily Entry'!$B$7:$B$10003,$O14,'Daily Entry'!$A$7:$A$10003,">="&MAX('Carton Stock'!$E$4,Stock!$E$3-29),'Daily Entry'!$A$7:$A$10003,"<="&Stock!$E$3)) | Q14: =IF(OR($A14="",$D14="",N($E14)<=0),0,$P14/$E14) | R14: =IF(AND($A14<>"",N($F14)>0,OR($D14="",N($E14)<=0)),1,0) | S14: =IF(AND($A14<>"",$D14<>""),IF(COUNTIF('Carton Stock'!$B$8:$B$47,$D14)=0,1,0),0) | T14: =IF(AND($A14<>"",OR($D14="",N($E14)<=0)),1,0)
A15: =IF(Stock!$A15="","",Stock!$A15) | B15: =IF(Stock!$A15="","",Stock!$B15) | C15: =IF(Stock!$A15="","",IF(Stock!$C15="","",Stock!$C15)) | D15: Blue Dolphin carton | E15: 10 | F15: =IF($A15="","",IF(Stock!$E$3<'Carton Stock'!$E$4,0,SUMIFS('Daily Entry'!$C$7:$C$10003,'Daily Entry'!$B$7:$B$10003,$O15,'Daily Entry'!$A$7:$A$10003,">="&'Carton Stock'!$E$4,'Daily Entry'!$A$7:$A$10003,"<="&Stock!$E$3))) | G15: =IF(OR($A15="",$D15="",N($E15)<=0),"",ROUNDUP($F15/$E15,0)) | H15: =IF($A15="","",IF(Stock!$E$3<'Carton Stock'!$E$4,0,SUMIFS('Daily Entry'!$C$7:$C$10003,'Daily Entry'!$B$7:$B$10003,$O15,'Daily Entry'!$A$7:$A$10003,Stock!$E$3))) | I15: =IF($G15="","",$G15-ROUNDUP(($F15-$H15)/$E15,0)) | O15: =IF(Stock!$A15="","",Stock!$O15) | P15: =IF($A15="",0,SUMIFS('Daily Entry'!$C$7:$C$10003,'Daily Entry'!$B$7:$B$10003,$O15,'Daily Entry'!$A$7:$A$10003,">="&MAX('Carton Stock'!$E$4,Stock!$E$3-29),'Daily Entry'!$A$7:$A$10003,"<="&Stock!$E$3)) | Q15: =IF(OR($A15="",$D15="",N($E15)<=0),0,$P15/$E15) | R15: =IF(AND($A15<>"",N($F15)>0,OR($D15="",N($E15)<=0)),1,0) | S15: =IF(AND($A15<>"",$D15<>""),IF(COUNTIF('Carton Stock'!$B$8:$B$47,$D15)=0,1,0),0) | T15: =IF(AND($A15<>"",OR($D15="",N($E15)<=0)),1,0)
A16: =IF(Stock!$A16="","",Stock!$A16) | B16: =IF(Stock!$A16="","",Stock!$B16) | C16: =IF(Stock!$A16="","",IF(Stock!$C16="","",Stock!$C16)) | D16: Primus Japan carton | E16: 10 | F16: =IF($A16="","",IF(Stock!$E$3<'Carton Stock'!$E$4,0,SUMIFS('Daily Entry'!$C$7:$C$10003,'Daily Entry'!$B$7:$B$10003,$O16,'Daily Entry'!$A$7:$A$10003,">="&'Carton Stock'!$E$4,'Daily Entry'!$A$7:$A$10003,"<="&Stock!$E$3))) | G16: =IF(OR($A16="",$D16="",N($E16)<=0),"",ROUNDUP($F16/$E16,0)) | H16: =IF($A16="","",IF(Stock!$E$3<'Carton Stock'!$E$4,0,SUMIFS('Daily Entry'!$C$7:$C$10003,'Daily Entry'!$B$7:$B$10003,$O16,'Daily Entry'!$A$7:$A$10003,Stock!$E$3))) | I16: =IF($G16="","",$G16-ROUNDUP(($F16-$H16)/$E16,0)) | O16: =IF(Stock!$A16="","",Stock!$O16) | P16: =IF($A16="",0,SUMIFS('Daily Entry'!$C$7:$C$10003,'Daily Entry'!$B$7:$B$10003,$O16,'Daily Entry'!$A$7:$A$10003,">="&MAX('Carton Stock'!$E$4,Stock!$E$3-29),'Daily Entry'!$A$7:$A$10003,"<="&Stock!$E$3)) | Q16: =IF(OR($A16="",$D16="",N($E16)<=0),0,$P16/$E16) | R16: =IF(AND($A16<>"",N($F16)>0,OR($D16="",N($E16)<=0)),1,0) | S16: =IF(AND($A16<>"",$D16<>""),IF(COUNTIF('Carton Stock'!$B$8:$B$47,$D16)=0,1,0),0) | T16: =IF(AND($A16<>"",OR($D16="",N($E16)<=0)),1,0)
A17: =IF(Stock!$A17="","",Stock!$A17) | B17: =IF(Stock!$A17="","",Stock!$B17) | C17: =IF(Stock!$A17="","",IF(Stock!$C17="","",Stock!$C17)) | D17: Primus Japan carton | E17: 10 | F17: =IF($A17="","",IF(Stock!$E$3<'Carton Stock'!$E$4,0,SUMIFS('Daily Entry'!$C$7:$C$10003,'Daily Entry'!$B$7:$B$10003,$O17,'Daily Entry'!$A$7:$A$10003,">="&'Carton Stock'!$E$4,'Daily Entry'!$A$7:$A$10003,"<="&Stock!$E$3))) | G17: =IF(OR($A17="",$D17="",N($E17)<=0),"",ROUNDUP($F17/$E17,0)) | H17: =IF($A17="","",IF(Stock!$E$3<'Carton Stock'!$E$4,0,SUMIFS('Daily Entry'!$C$7:$C$10003,'Daily Entry'!$B$7:$B$10003,$O17,'Daily Entry'!$A$7:$A$10003,Stock!$E$3))) | I17: =IF($G17="","",$G17-ROUNDUP(($F17-$H17)/$E17,0)) | O17: =IF(Stock!$A17="","",Stock!$O17) | P17: =IF($A17="",0,SUMIFS('Daily Entry'!$C$7:$C$10003,'Daily Entry'!$B$7:$B$10003,$O17,'Daily Entry'!$A$7:$A$10003,">="&MAX('Carton Stock'!$E$4,Stock!$E$3-29),'Daily Entry'!$A$7:$A$10003,"<="&Stock!$E$3)) | Q17: =IF(OR($A17="",$D17="",N($E17)<=0),0,$P17/$E17) | R17: =IF(AND($A17<>"",N($F17)>0,OR($D17="",N($E17)<=0)),1,0) | S17: =IF(AND($A17<>"",$D17<>""),IF(COUNTIF('Carton Stock'!$B$8:$B$47,$D17)=0,1,0),0) | T17: =IF(AND($A17<>"",OR($D17="",N($E17)<=0)),1,0)
A18: =IF(Stock!$A18="","",Stock!$A18) | B18: =IF(Stock!$A18="","",Stock!$B18) | C18: =IF(Stock!$A18="","",IF(Stock!$C18="","",Stock!$C18)) | D18: Primus Japan carton | E18: 10 | F18: =IF($A18="","",IF(Stock!$E$3<'Carton Stock'!$E$4,0,SUMIFS('Daily Entry'!$C$7:$C$10003,'Daily Entry'!$B$7:$B$10003,$O18,'Daily Entry'!$A$7:$A$10003,">="&'Carton Stock'!$E$4,'Daily Entry'!$A$7:$A$10003,"<="&Stock!$E$3))) | G18: =IF(OR($A18="",$D18="",N($E18)<=0),"",ROUNDUP($F18/$E18,0)) | H18: =IF($A18="","",IF(Stock!$E$3<'Carton Stock'!$E$4,0,SUMIFS('Daily Entry'!$C$7:$C$10003,'Daily Entry'!$B$7:$B$10003,$O18,'Daily Entry'!$A$7:$A$10003,Stock!$E$3))) | I18: =IF($G18="","",$G18-ROUNDUP(($F18-$H18)/$E18,0)) | O18: =IF(Stock!$A18="","",Stock!$O18) | P18: =IF($A18="",0,SUMIFS('Daily Entry'!$C$7:$C$10003,'Daily Entry'!$B$7:$B$10003,$O18,'Daily Entry'!$A$7:$A$10003,">="&MAX('Carton Stock'!$E$4,Stock!$E$3-29),'Daily Entry'!$A$7:$A$10003,"<="&Stock!$E$3)) | Q18: =IF(OR($A18="",$D18="",N($E18)<=0),0,$P18/$E18) | R18: =IF(AND($A18<>"",N($F18)>0,OR($D18="",N($E18)<=0)),1,0) | S18: =IF(AND($A18<>"",$D18<>""),IF(COUNTIF('Carton Stock'!$B$8:$B$47,$D18)=0,1,0),0) | T18: =IF(AND($A18<>"",OR($D18="",N($E18)<=0)),1,0)
